Workbook
Name 是否: [1]选项!$A$1:$A$2
Name Hidden000cdfc206468fca52c_1_11: [2]Hidden000cdfc206468fca52c!$A$1:$A$71
Name Hidden000cdfc206468fca52c_1_17: [2]Hidden000cdfc206468fca52c!$B$1:$B$7
Name Hidden000cdfc206468fca52c_1_22: [2]Hidden000cdfc206468fca52c!$C$1:$C$7
Name Hidden000cdfc206468fca52c_1_23: [2]Hidden000cdfc206468fca52c!$D$1:$D$2
Name Hidden000cdfc206468fca52c_1_24: [2]Hidden000cdfc206468fca52c!$E$1:$E$8
Name Hidden000cdfc206468fca52c_1_27: [2]Hidden000cdfc206468fca52c!$F$1:$F$10
Name Hidden000cdfc206468fca52c_1_32: [2]Hidden000cdfc206468fca52c!$G$1:$G$2
Name Hidden000cdfc206468fca52c_1_33: [2]Hidden000cdfc206468fca52c!$H$1:$H$5
Name Hidden000cdfc206468fca52c_1_34: [2]Hidden000cdfc206468fca52c!$I$1:$I$5
Name Hidden000cdfc206468fca52c_1_35: [2]Hidden000cdfc206468fca52c!$J$1:$J$58
Name Hidden000cdfc206468fca52c_1_43: [2]Hidden000cdfc206468fca52c!$K$1:$K$9
Name Hidden000cdfc206468fca52c_1_44: [2]Hidden000cdfc206468fca52c!$L$1:$L$4
Name Hidden000cdfc206468fca52c_1_56: [2]Hidden000cdfc206468fca52c!$M$1:$M$8
Name Hidden000cdfc206468fca52c_1_57: [2]Hidden000cdfc206468fca52c!$N$1:$N$7
Name Hidden000cdfc206468fca52c_1_58: [2]Hidden000cdfc206468fca52c!$O$1:$O$8
Name Hidden000cdfc206468fca52c_1_63: [2]Hidden000cdfc206468fca52c!$P$1:$P$5
Name Hidden000cdfc206468fca52c_1_67: [2]Hidden000cdfc206468fca52c!$Q$1:$Q$6
Name Hidden000cdfc206468fca52c_1_70: [2]Hidden000cdfc206468fca52c!$R$1:$R$6
Name Hidden000cdfc206468fca52c_1_71: [2]Hidden000cdfc206468fca52c!$S$1:$S$2
Name categoryHidden33: [3]categoryHidden33!A1:A170
Name categoryHidden9: #REF!
Name 证件类型: [4]填表说明!$A$6:$A$17
Name 法定假日: #REF!
Name 补班日: #REF!
Name 港澳居民来往内地通行证: [5]填表说明!$G$7
Name 国籍地区: [5]填表说明!$C$7:$C$249
Name 开户银行: [5]填表说明!$M$5:$M$717
Name 涉税事由: [5]填表说明!$A$39:$A$43
Name 省份: [5]填表说明!$K$5:$K$38
Name 证照类型: [5]填表说明!$E$6:$J$6
Name 所得项目: [6]填表说明!$A$5:$A$6
Name Hidden000cdfc206468fca52c_1_27: [7]Hidden000cdfc206468fca52c!$F$1:$F$10
Name Hidden000cdfc206468fca52c_1_27: [7]Hidden000cdfc206468fca52c!$F$1:$F$10
Name Hidden000cdfc206468fca52c_1_27: [7]Hidden000cdfc206468fca52c!$F$1:$F$10
Name Hidden000cdfc206468fca52c_1_27: [7]Hidden000cdfc206468fca52c!$F$1:$F$10
Name Hidden000cdfc206468fca52c_1_27: [7]Hidden000cdfc206468fca52c!$F$1:$F$10
Name Hidden000cdfc206468fca52c_1_27: [7]Hidden000cdfc206468fca52c!$F$1:$F$10
Name Hidden000cdfc206468fca52c_1_27: [7]Hidden000cdfc206468fca52c!$F$1:$F$10

Sheet 汇总
B1: 2026年7月六棱镜工资情况
B2: 主体 | C2: 实发工资 | D2: 个税 | E2: 社保公司 | F2: 社保个人 | G2: 公积金公司 | H2: 公积金个人 | I2: 发薪人数 | K2: 下发项目 | L2: 金额
B3: 北分 | C3: =SUMIFS(工资表明细!AX:AX,工资表明细!B:B,B3) -> 0 | D3: =SUMIFS(工资表明细!AU:AU,工资表明细!B:B,B3) -> 0 | E3: =SUMIFS(工资表明细!BD:BD,工资表明细!B:B,B3) -> 0 | F3: =SUMIFS(工资表明细!AS:AS,工资表明细!B:B,B3) -> 0 | G3: =SUMIFS(工资表明细!BE:BE,工资表明细!B:B,B3) -> 0 | H3: =SUMIFS(工资表明细!AT:AT,工资表明细!B:B,B3) -> 0 | I3: =COUNTIFS(工资表明细!AX:AX,">0",工资表明细!B:B,B3) -> 0 | K3: 在职实发 | L3: =SUMIFS(工资表明细!AX:AX,工资表明细!G:G,0) -> 0 | M3: =L3+L4-工资表明细!AX4 -> 0
B4: 成都 | C4: =SUMIFS(工资表明细!AX:AX,工资表明细!B:B,B4) -> 0 | D4: =SUMIFS(工资表明细!AU:AU,工资表明细!B:B,B4) -> 0 | E4: =SUMIFS(工资表明细!BD:BD,工资表明细!B:B,B4) -> 0 | F4: =SUMIFS(工资表明细!AS:AS,工资表明细!B:B,B4) -> 0 | G4: =SUMIFS(工资表明细!BE:BE,工资表明细!B:B,B4) -> 0 | H4: =SUMIFS(工资表明细!AT:AT,工资表明细!B:B,B4) -> 0 | I4: =COUNTIFS(工资表明细!AX:AX,">0",工资表明细!B:B,B4) -> 0 | K4: 离职实发 | L4: =SUMIFS(工资表明细!AX:AX,工资表明细!G:G,">0") -> 0
B5: 杭州 | C5: =SUMIFS(工资表明细!AX:AX,工资表明细!B:B,B5) -> 0 | D5: =SUMIFS(工资表明细!AU:AU,工资表明细!B:B,B5) -> 0 | E5: =SUMIFS(工资表明细!BD:BD,工资表明细!B:B,B5) -> 0 | F5: =SUMIFS(工资表明细!AS:AS,工资表明细!B:B,B5) -> 0 | G5: =SUMIFS(工资表明细!BE:BE,工资表明细!B:B,B5) -> 0 | H5: =SUMIFS(工资表明细!AT:AT,工资表明细!B:B,B5) -> 0 | I5: =COUNTIFS(工资表明细!AX:AX,">0",工资表明细!B:B,B5) -> 0 | K5: 本月离职分期下发 | L5: 86196.98
B6: 深圳 | C6: =SUMIFS(工资表明细!AX:AX,工资表明细!B:B,B6) -> 0 | D6: =SUMIFS(工资表明细!AU:AU,工资表明细!B:B,B6) -> 0 | E6: =SUMIFS(工资表明细!BD:BD,工资表明细!B:B,B6) -> 0 | F6: =SUMIFS(工资表明细!AS:AS,工资表明细!B:B,B6) -> 0 | G6: =SUMIFS(工资表明细!BE:BE,工资表明细!B:B,B6) -> 0 | H6: =SUMIFS(工资表明细!AT:AT,工资表明细!B:B,B6) -> 0 | I6: =COUNTIFS(工资表明细!AX:AX,">0",工资表明细!B:B,B6) -> 0 | K6: 本月在职分期下发 | L6: 0
B7: 武汉 | C7: =SUMIFS(工资表明细!AX:AX,工资表明细!B:B,B7) -> 0 | D7: =SUMIFS(工资表明细!AU:AU,工资表明细!B:B,B7) -> 0 | E7: =SUMIFS(工资表明细!BD:BD,工资表明细!B:B,B7) -> 0 | F7: =SUMIFS(工资表明细!AS:AS,工资表明细!B:B,B7) -> 0 | G7: =SUMIFS(工资表明细!BE:BE,工资表明细!B:B,B7) -> 0 | H7: =SUMIFS(工资表明细!AT:AT,工资表明细!B:B,B7) -> 0 | I7: =COUNTIFS(工资表明细!AX:AX,">0",工资表明细!B:B,B7) -> 0 | K7: 合计 | L7: =SUM(L3:L6) -> 86196.98
B8: 北京 | C8: =SUMIFS(工资表明细!AX:AX,工资表明细!B:B,B8) -> 0 | D8: =SUMIFS(工资表明细!AU:AU,工资表明细!B:B,B8) -> 0 | E8: =SUMIFS(工资表明细!BD:BD,工资表明细!B:B,B8) -> 0 | F8: =SUMIFS(工资表明细!AS:AS,工资表明细!B:B,B8) -> 0 | G8: =SUMIFS(工资表明细!BE:BE,工资表明细!B:B,B8) -> 0 | H8: =SUMIFS(工资表明细!AT:AT,工资表明细!B:B,B8) -> 0 | I8: =COUNTIFS(工资表明细!AX:AX,">0",工资表明细!B:B,B8) -> 0
B9: 总计 | C9: =SUM(C3:C8) -> 0 | D9: =SUM(D3:D8) -> 0 | E9: =SUM(E3:E8) -> 0 | F9: =SUM(F3:F8) -> 0 | G9: =SUM(G3:G8) -> 0 | H9: =SUM(H3:H8) -> 0 | I9: =SUM(I3:I8) -> 0
B12: 主体 | C12: 实发工资 | D12: 个税 | E12: 社保公司 | F12: 社保个人 | G12: 公积金公司 | H12: 公积金个人 | I12: 发薪人数
B13: 中汽 | C13: =SUMIFS(工资表明细!AX:AX,工资表明细!B:B,B13) -> 0 | D13: =SUMIFS(工资表明细!AU:AU,工资表明细!B:B,B13) -> 0 | E13: =SUMIFS(工资表明细!BD:BD,工资表明细!B:B,B13) -> 0 | F13: =SUMIFS(工资表明细!AS:AS,工资表明细!B:B,B13) -> 0 | G13: =SUMIFS(工资表明细!BE:BE,工资表明细!B:B,B13) -> 0 | H13: =SUMIFS(工资表明细!AT:AT,工资表明细!B:B,B13) -> 0 | I13: =COUNTIFS(工资表明细!AX:AX,">0",工资表明细!B:B,B13) -> 0
B14: 总计 | C14: =SUM(C13:C13) -> 0 | D14: =SUM(D13:D13) -> 0 | E14: =SUM(E13:E13) -> 0 | F14: =SUM(F13:F13) -> 0 | G14: =SUM(G13:G13) -> 0 | H14: =SUM(H13:H13) -> 0 | I14: =SUM(I13:I13) -> 0
C16: =C14+C9-工资表明细!AX4 -> 0 | D16: =D9+D14-工资表明细!AU4 -> 0 | E16: =E9+E14-工资表明细!BD4 -> 0 | F16: =F9+F14-工资表明细!AS4 -> 0 | G16: =G9+G14-工资表明细!BE4 -> 0 | H16: =H9+H14-工资表明细!AT4 -> 0

Sheet 工资表明细
A1: C | AD1: 工资表
A2: 序号 | B2: 员工信息 | N2: 年薪（万元） | O2: 当月薪资标准 | P2: 固定薪资 | AC2: 绩效薪资 | AK2: 业绩提成奖 | AL2: 其他增减项 | AO2: 本月应发工资合计 | AP2: 代扣代缴 | AV2: 税后补款 | AW2: 税后扣款 | AX2: 实发工资 | AY2: 社保公积金公司承担部分 | BF2: 人工成本 | BG2: 备注 | BH2: 报税 | BM2: 公司 | BN2: 银行卡号 | BO2: 开户行 | BP2: 备注
A3: 序号 | B3: 主体简称 | C3: 姓名 | D3: 身份证号 | E3: 入职日期 | F3: 转正日期 | G3: 离职日期 | H3: 一级部门 | I3: 二级部门 | J3: 三级部门 | K3: 职务 | L3: 劳动合同类型 | M3: 职级 | N3: 年薪（万元） | O3: 当月薪资标准 | P3: 当月固定薪资标准 | Q3: 迟到早退 扣款 | R3: 缺卡扣款 | S3: 事假扣款 | T3: 病假 扣款 | U3: 旷工 扣款 | V3: 产假扣款 | W3: 当月未出勤（入离职） | X3: 考勤扣款合计 | Y3: 考勤激励 | Z3: 工资增项 | AA3: 工资减项 | AB3: 应发固定工资 | AC3: 当月绩效标准 | AD3: 绩效 系数 | AE3: 本月工作日天数 | AF3: 实际出勤天数 | AG3: 绩效增项 | AH3: 绩效减项 | AI3: 绩效工资 支付方式 | AJ3: 应发绩效工资 | AK3: 业绩提成奖 | AL3: 经济补偿金 | AM3: 其他增项 | AN3: 其他减项 | AO3: 本月应发工资合计 | AP3: 养老扣款 个人 | AQ3: 医疗扣款 个人 | AR3: 失业扣款 个人 | AS3: 社保扣款 个人合计 | AT3: 公积金扣款 个人 | AU3: 个税 | AV3: 税后补款 | AW3: 税后扣款 | AX3: 实发工资 | AY3: 养老扣款 （单位） | AZ3: 医疗扣款 （单位） | BA3: 失业扣款 （单位） | BB3: 工伤扣款 （单位） | BC3: 生育保险（单位） | BD3: 公司社保合计 | BE3: 住房公积金扣款（单位） | BF3: 人工成本 | BG3: 备注 | BH3: 经济补偿金 | BI3: 年终一次性奖申报 | BJ3: 劳务申报 | BK3: 调整报税金额 | BL3: 正常工资申报 | BM3: 公司 | BN3: 银行卡号 | BO3: 开户行（存疑） | BP3: 备注
B4: 合计 | O4: =SUBTOTAL(9,O2:O3) -> 0 | P4: =SUBTOTAL(9,P2:P3) -> 0 | Q4: =SUBTOTAL(9,Q2:Q3) -> 0 | R4: =SUBTOTAL(9,R2:R3) -> 0 | S4: =SUBTOTAL(9,S2:S3) -> 0 | T4: =SUBTOTAL(9,T2:T3) -> 0 | U4: =SUBTOTAL(9,U2:U3) -> 0 | V4: =SUBTOTAL(9,V2:V3) -> 0 | ... BL4: =SUBTOTAL(9,BL2:BL3) -> 0
A7: 说明：
B8: 产假员工
B9: 调薪调动员工
B10: 新入职员工
B11: 劳务或特殊员工
B12: 离职员工

Sheet 考勤表
O1: 考勤截止日期 | P1: 46234 | Q1: 46204
A2: 身份证号 | B2: 姓名 | C2: 公司 | D2: 一级部门 | E2: 二级部门 | F2: 三级部门 | G2: 入职日期 | H2: 转正日期 | I2: 离职日期 | J2: 试用期固定薪资 | K2: 试用期绩效 | L2: 转正固定薪资 | M2: 转正绩效 | N2: 当月固定薪资标准 | O2: 当月绩效标准 | P2: 当期考勤基数 | Q2: 当地最低工资 | R2: 试用期工作日天数 | S2: 转正工作日天数 | T2: 工作日天数合计 | U2: 实际出勤天数 | V2: 请假外未出勤天数（当月入离职） | W2: 迟到时长 | X2: 早退时长 | Y2: 缺卡次数 | Z2: 旷工天数 | AA2: 事假天数 | AB2: 病假天数 | AC2: 年假天数 | AD2: 产假天数 | AE2: 产检假天数 | AF2: 陪产假天数 | AG2: 育儿假天数 | AH2: 婚假天数 | AI2: 丧假天数 | AJ2: 其他福利假 | AK2: 调休天数 | AL2: 工作日加班时长 | AM2: 休息日加班时长 | AN2: 法定节假日加班时长 | AO2: 请假外未出勤扣款 | AP2: 迟到/早退扣款 | AQ2: 缺卡扣款 | AR2: 事假扣款 | AS2: 病假扣款 | AT2: 产假扣款 | AU2: 旷工扣款 | AV2: 总扣款 | AW2: 工作日加班费 | AX2: 休息日加班费 | AY2: 法定节假日加班费 | AZ2: 全勤奖 | BA2: 合计 | BB2: 转正标记 | BC2: 效验 | BD2: 转正后实际出勤

Sheet 增减项异动表
A1: 序号 | B1: 身份证号 | C1: 姓名 | D1: 项目 | E1: 金额 | F1: 备注

Sheet 花名册
A1: 序号 | B1: 证件号码 | C1: 姓名 | D1: 主体简称 | E1: 公司主体全称 | F1: 一级部门 | G1: 二级部门 | H1: 三级部门 | I1: 岗位 | J1: 职级 | K1: 一级岗位 | L1: 二级岗位 | M1: 直属上级 | N1: 入职时间 | O1: 转正日期 | P1: 离职时间 | Q1: 手机号 | R1: 银行卡号 | S1: 开户行 | T1: 转正固定薪资 | U1: 转正绩效标准 | V1: 试用期底薪 | W1: 试用期绩效 | X1: 劳动合同类型 | Y1: 绩效支付周期 | Z1: 备注 | AA1: 年薪（万元） | AB1: 企业微信邮箱

Sheet 社保公积金明细
A1: 序号 | B1: 姓名 | C1: 身份证号码 | D1: 缴纳主体 | E1: 缴费地区 | F1: 社保基数 | G1: 住房公积金基数 | H1: 养老保险 | J1: 医疗保险 | L1: 失业保险 | N1: 工伤保险 | O1: 生育保险 | P1: 社会保险合计 | R1: 公积金 | T1: 公司合计 | U1: 个人合计 | V1: 滞纳金 | W1: 服务费 | X1: 其他费用 | Y1: 合计 | Z1: 备注
H2: 企业 | I2: 个人 | J2: 企业 | K2: 个人 | L2: 企业 | M2: 个人 | P2: 企业 | Q2: 个人 | R2: 企业 | S2: 个人

Sheet 最低工资标准
A1: 公司全称 | B1: 公司简称 | C1: 地区 | D1: 当地最低工资标准 | E1: 备注
A2: 六棱镜（杭州）科技有限公司北京分公司 | B2: 北分 | C2: 北京 | D2: 2540 | F2: https://rsj.beijing.gov.cn/xxgk/zcwj/202307/t20230714_3162615.html
A3: 北京六棱镜数字科技发展有限公司 | B3: 北京 | C3: 北京 | D3: 2540
A4: 成都六棱镜数字科技有限公司 | B4: 成都 | C4: 成都 | D4: 2330
A5: 六棱镜（杭州）科技有限公司 | B5: 杭州 | C5: 杭州 | D5: 2660 | E5: 浙江1档
A6: 广东六棱镜数字科技发展有限公司 | B6: 深圳 | C6: 深圳 | D6: 2520
A7: 中城六棱镜（武汉）科技有限公司 | B7: 武汉 | C7: 武汉 | D7: 2400
B8: 广州 | C8: 广州 | D8: 2500
B9: 中汽-长沙 | C9: 长沙 | D9: 2200
A10: 中汽知识产权投资运营中心（北京）有限公司 | B10: 中汽-北京 | C10: 北京 | D10: 2540

Sheet 工资条
A1: 身份证号 | B1: 姓名 | C1: 固定工资标准 | D1: 绩效工资标准 | E1: 本月工作 日天数 | F1: 实际出勤天数 | G1: 迟到早退时长 | H1: 事假 | I1: 当月未出勤（入离职）（天） | J1: 病假 （天） | K1: 考勤扣款合计 | L1: 应发固定工资 | M1: 增项合计 | N1: 减项合计 | O1: 本月应发工资合计 | P1: 社保 个人合计 | Q1: 公积金 个人合计 | R1: 个税 | S1: 税后补款 | T1: 税后扣款 | U1: 实发工资 | V1: 备注 | W1: 辅助列-赔偿金 | X1: 辅助列-实发金额核验

Sheet 个税计算
A1: 报税属期 | D1: 8 | E1: 月 | BK1: 46235
A2: 序号 | B2: 姓名 | C2: 身份证件类型 | D2: 身份证件号码 | E2: 是否为非居民个人 | F2: 所得项目 | G2: 本月（次）情况 | AC2: 累计情况 | AN2: 减按计税比例 | AO2: 准予扣除的捐赠额 | AP2: 税款计算 | AW2: 备注 | AX2: 累计情况
G3: 收入额计算 | J3: 减除费用 | K3: 专项扣除 | O3: 其他扣除 | AC3: 累计收入额 | AD3: 累计减除费用 | AE3: 累计专项扣除 | AF3: 累计专项附加扣除 | AL3: 累计个人养老金 | AM3: 累计其他扣除 | AP3: 应纳税所得额 | AQ3: 税率/预扣率 | AR3: 速算扣除数 | AS3: 应纳税额 | AT3: 减免税额 | AU3: 已缴税额 | AV3: 应补/退税额 | AX3: 累计收入额 | AY3: 累计减除费用 | AZ3: 累计专项扣除 | BA3: 累计专项附加扣除 | BG3: 累计个人养老金 | BH3: 累计其他扣除
G4: 收入 | H4: 费用 | I4: 免税收入 | K4: 基本养老保险费 | L4: 基本医疗保险费 | M4: 失业保险费 | N4: 住房公积金 | O4: 年金 | P4: 商业健康保险 | Q4: 税延养老保险 | R4: 财产原值 | S4: 允许扣除的税费 | T4: 公务交通费用 | U4: 通讯费用 | V4: 律师办案费用 | W4: 展业成本 | X4: 西藏附加减除费用 | Y4: 修缮费用 | Z4: 有关合理费用 | AA4: 向出租方支付的租金 | AB4: 其他 | AF4: 子女教育 | AG4: 赡养老人 | AH4: 住房贷款利息 | AI4: 住房租金 | AJ4: 继续教育 | AK4: 3岁以下婴幼儿照护 | BA4: 子女教育 | BB4: 赡养老人 | BC4: 住房贷款利息 | BD4: 住房租金 | BE4: 继续教育 | BF4: 3岁以下婴幼儿照护 | BI4: 上期已缴税额 | BJ4: 上期缴纳税额 | BK4: 辅助列-入职时间
B5: 耿德强 | C5: 居民身份证 | D5: 37028519831217171X | E5: 否 | F5: 正常工资薪金 | G5: {=_xlfn.IFS(F5="正常工资薪金",VLOOKUP(D5&"*",工资表明细!D:BL,61,0),F5="一般劳务报酬所得",VLOOKUP(D5&"*",工资表明细!D:BJ,59,0),F5="全年一次性奖金收入",VLOOKUP(D5&"*",工资表明细!D:BI,58,0),F5="解除劳动合同一次性补偿金",VLOOKUP(D5&"*",工资表明细!D:BH,57,0))} -> #N/A | H5: =IF(F5="一般劳务报酬所得",800,0) -> 0 | I5: 0 | J5: =IF(F5="正常工资薪金",5000,0) -> 5000 | K5: =IF(F5="正常工资薪金",VLOOKUP(D5&"*",工资表明细!D:AP,39,0),0) -> #N/A | L5: =IF(F5="正常工资薪金",VLOOKUP(D5&"*",工资表明细!D:AQ,40,0),0) -> #N/A | M5: =IF(F5="正常工资薪金",VLOOKUP(D5&"*",工资表明细!D:AR,41,0),0) -> #N/A | N5: =IF(F5="正常工资薪金",VLOOKUP(D5&"*",工资表明细!D:AT,43,0),0) -> #N/A | O5: 0 | P5: 0 | Q5: 0 | R5: 0 | S5: 0 | T5: 0 | U5: 0 | V5: 0 | W5: - | X5: 0 | Y5: - | Z5: - | AA5: - | AB5: 0 | AC5: =IF(F5="正常工资薪金",G5+AX5,"-") -> #N/A | AD5: =IF(F5="正常工资薪金",J5+AY5,"-") -> 40000 | AE5: =IF(F5="正常工资薪金",K5+L5+M5+N5+AZ5,"-") -> #N/A | AF5: =IFERROR(IF($F$5="正常工资薪金",IF(YEAR(BK5)<YEAR($BK$1),BA5/($D$1-1)*$D$1,BA5/DATEDIF(BK5,$BK$1,"M")*DATEDIF(BK5,$BK$1,"M")),"-"),0) -> 0 | AG5: =IFERROR(IF($F$5="正常工资薪金",IF(YEAR(BK5)<YEAR($BK$1),BB5/($D$1-1)*$D$1,BB5/DATEDIF(BK5,$BK$1,"M")*DATEDIF(BK5,$BK$1,"M")),"-"),0) -> 0 | AH5: =IFERROR(IF($F$5="正常工资薪金",IF(YEAR(BK5)<YEAR($BK$1),BC5/($D$1-1)*$D$1,BC5/(MONTH($BK$1)-MONTH(BK5))*(MONTH($BK$1)-MONTH(BK5)+1)),"-"),0) -> 0 | AI5: =IFERROR(IF($F$5="正常工资薪金",IF(YEAR(BK5)<YEAR($BK$1),BD5/($D$1-1)*$D$1,BD5/(MONTH($BK$1)-MONTH(BK5))*(MONTH($BK$1)-MONTH(BK5)+1)),"-"),0) -> 0 | AJ5: =IFERROR(IF($F$5="正常工资薪金",IF(YEAR(BK5)<YEAR($BK$1),BE5/($D$1-1)*$D$1,BE5/(MONTH($BK$1)-MONTH(BK5))*(MONTH($BK$1)-MONTH(BK5)+1)),"-"),0) -> 0 | AK5: =IFERROR(IF($F$5="正常工资薪金",IF(YEAR(BK5)<YEAR($BK$1),BF5/($D$1-1)*$D$1,BF5/(MONTH($BK$1)-MONTH(BK5))*(MONTH($BK$1)-MONTH(BK5)+1)),"-"),0) -> 0 | AL5: 0 | AM5: 0 | AN5: 100% | AO5: 0 | AP5: =IF(IF(F5="正常工资薪金",AC5-AD5-AE5-AF5-AG5-AH5-AI5-AJ5-AK5-AL5-AM5,G5-H5-I5)<0,0,IF(F5="正常工资薪金",AC5-AD5-AE5-AF5-AG5-AH5-AI5-AJ5-AK5-AL5-AM5,G5-H5-I5)) -> #N/A | AQ5: {=_xlfn.IFS(F5="正常工资薪金",VLOOKUP(AP5,{0,0.03;36000,0.1;144000,0.2;300000,0.25;420000,0.3;660000,0.35;960000,0.45},2,1),F5="一般劳务报酬所得",IF(AP5<=20000,0.2,IF(AP5<=50000,0.3,0.4)),F5="全年一次性奖金收入",VLOOKUP(AP5/12,{0,0.03;3000,0.1;12000,0.2;25000,0.25;35000,0.3;55000,0.35;80000,0.45},2,1),F5="解除劳动合同一次性补偿金",VLOOKUP(AP5,{0,0.03;36000,0.1;144000,0.2;300000,0.25;420000,0.3;660000,0.35;960000,0.45},2,1))} -> #N/A | AR5: {=_xlfn.IFS(F5="正常工资薪金",VLOOKUP(AP5,{0,0;36000,2520;144000,16920;300000,31920;420000,52920;660000,85920;960000,181920},2,1),F5="一般劳务报酬所得",IF(AP5<=20000,0,IF(AS<=50000,2000,7000)),F5="全年一次性奖金收入",VLOOKUP(AP5/12,{0,0;3000,210;12000,1410;25000,2660;35000,4410;55000,7160;80000,15160},2,1),F5="解除劳动合同一次性补偿金",VLOOKUP(AP5,{0,0;36000,2520;144000,16920;300000,31920;420000,52920;660000,85920;960000,181920},2,1))} -> #N/A | AS5: =AP5*AQ5-AR5 -> #N/A | AT5: 0 | AU5: =BI5+BJ5 -> 28160.43 | AV5: =IF(AS5-AT5-AU5>0,AS5-AT5-AU5,0) -> #N/A | AX5: =IFERROR(IF(F5="正常工资薪金",VLOOKUP(D5&"*",个税上月累计情况!E:AL,26,0),0),0) -> 280000 | AY5: =IFERROR(IF(F5="正常工资薪金",VLOOKUP(D5&"*",个税上月累计情况!E:AL,27,0),0),0) -> 35000 | AZ5: =IFERROR(IF(F5="正常工资薪金",VLOOKUP(D5&"*",个税上月累计情况!E:AL,28,0),0),0) -> 19597.83 | BA5: =IFERROR(IF(F5="正常工资薪金",VLOOKUP(D5&"*",个税上月累计情况!E:AL,29,0),0),0) -> 0 | BB5: =IFERROR(IF(F5="正常工资薪金",VLOOKUP(D5&"*",个税上月累计情况!E:AL,30,0),0),0) -> 0 | BC5: =IFERROR(IF(F5="正常工资薪金",VLOOKUP(D5&"*",个税上月累计情况!E:AL,31,0),0),0) -> 0 | BD5: =IFERROR(IF(F5="正常工资薪金",VLOOKUP(D5&"*",个税上月累计情况!E:AL,32,0),0),0) -> 0 | BE5: =IFERROR(IF(F5="正常工资薪金",VLOOKUP(D5&"*",个税上月累计情况!E:AL,33,0),0),0) -> 0 | BF5: =IFERROR(IF(F5="正常工资薪金",VLOOKUP(D5&"*",个税上月累计情况!E:AL,34,0),0),0) -> 0 | BG5: =IFERROR(IF(F5="正常工资薪金",VLOOKUP(D5&"*",个税上月累计情况!E:AN,35,0),0),0) -> 0 | BH5: =IFERROR(IF(F5="正常工资薪金",VLOOKUP(D5&"*",个税上月累计情况!E:AN,36,0),0),0) -> 0 | BI5: =IFERROR(IF(F5="正常工资薪金",VLOOKUP(D5&"*",个税上月累计情况!D:AW,46,0),0),0) -> 21660.54 | BJ5: =IFERROR(IF(F5="正常工资薪金",VLOOKUP(D5&"*",个税上月累计情况!D:AX,47,0),0),0) -> 6499.89 | BK5: =VLOOKUP(B5,花名册!C:N,12,0) -> #N/A
B6: 牛飞芸 | C6: 居民身份证 | D6: 620402199105092732 | E6: 否 | F6: 正常工资薪金 | G6: {=_xlfn.IFS(F6="正常工资薪金",VLOOKUP(D6&"*",工资表明细!D:BL,61,0),F6="一般劳务报酬所得",VLOOKUP(D6&"*",工资表明细!D:BJ,59,0),F6="全年一次性奖金收入",VLOOKUP(D6&"*",工资表明细!D:BI,58,0),F6="解除劳动合同一次性补偿金",VLOOKUP(D6&"*",工资表明细!D:BH,57,0))} -> #N/A | H6: =IF(F6="一般劳务报酬所得",800,0) -> 0 | I6: 0 | J6: =IF(F6="正常工资薪金",5000,0) -> 5000 | K6: =IF(F6="正常工资薪金",VLOOKUP(D6&"*",工资表明细!D:AP,39,0),0) -> #N/A | L6: =IF(F6="正常工资薪金",VLOOKUP(D6&"*",工资表明细!D:AQ,40,0),0) -> #N/A | M6: =IF(F6="正常工资薪金",VLOOKUP(D6&"*",工资表明细!D:AR,41,0),0) -> #N/A | N6: =IF(F6="正常工资薪金",VLOOKUP(D6&"*",工资表明细!D:AT,43,0),0) -> #N/A | O6: 1 | P6: 1 | Q6: 1 | R6: 1 | S6: 1 | T6: 1 | U6: 1 | V6: 1 | W6: - | X6: 1 | Y6: - | Z6: - | AA6: - | AB6: 1 | AC6: =IF(F6="正常工资薪金",G6+AX6,"-") -> #N/A | AD6: =IF(F6="正常工资薪金",J6+AY6,"-") -> 40000 | AE6: =IF(F6="正常工资薪金",K6+L6+M6+N6+AZ6,"-") -> #N/A | AF6: =IFERROR(IF($F$5="正常工资薪金",IF(YEAR(BK6)<YEAR($BK$1),BA6/($D$1-1)*$D$1,BA6/DATEDIF(BK6,$BK$1,"M")*DATEDIF(BK6,$BK$1,"M")),"-"),0) -> 0 | AG6: =IFERROR(IF($F$5="正常工资薪金",IF(YEAR(BK6)<YEAR($BK$1),BB6/($D$1-1)*$D$1,BB6/DATEDIF(BK6,$BK$1,"M")*DATEDIF(BK6,$BK$1,"M")),"-"),0) -> 0 | AH6: =IFERROR(IF($F$5="正常工资薪金",IF(YEAR(BK6)<YEAR($BK$1),BC6/($D$1-1)*$D$1,BC6/(MONTH($BK$1)-MONTH(BK6))*(MONTH($BK$1)-MONTH(BK6)+1)),"-"),0) -> 0 | AI6: =IFERROR(IF($F$5="正常工资薪金",IF(YEAR(BK6)<YEAR($BK$1),BD6/($D$1-1)*$D$1,BD6/(MONTH($BK$1)-MONTH(BK6))*(MONTH($BK$1)-MONTH(BK6)+1)),"-"),0) -> 0 | AJ6: =IFERROR(IF($F$5="正常工资薪金",IF(YEAR(BK6)<YEAR($BK$1),BE6/($D$1-1)*$D$1,BE6/(MONTH($BK$1)-MONTH(BK6))*(MONTH($BK$1)-MONTH(BK6)+1)),"-"),0) -> 0 | AK6: =IFERROR(IF($F$5="正常工资薪金",IF(YEAR(BK6)<YEAR($BK$1),BF6/($D$1-1)*$D$1,BF6/(MONTH($BK$1)-MONTH(BK6))*(MONTH($BK$1)-MONTH(BK6)+1)),"-"),0) -> 0 | AL6: 0 | AM6: 0 | AN6: 100% | AO6: 0 | AP6: =IF(IF(F6="正常工资薪金",AC6-AD6-AE6-AF6-AG6-AH6-AI6-AJ6-AK6-AL6-AM6,G6-H6-I6)<0,0,IF(F6="正常工资薪金",AC6-AD6-AE6-AF6-AG6-AH6-AI6-AJ6-AK6-AL6-AM6,G6-H6-I6)) -> #N/A | AQ6: {=_xlfn.IFS(F6="正常工资薪金",VLOOKUP(AP6,{0,0.03;36000,0.1;144000,0.2;300000,0.25;420000,0.3;660000,0.35;960000,0.45},2,1),F6="一般劳务报酬所得",IF(AP6<=20000,0.2,IF(AP6<=50000,0.3,0.4)),F6="全年一次性奖金收入",VLOOKUP(AP6/12,{0,0.03;3000,0.1;12000,0.2;25000,0.25;35000,0.3;55000,0.35;80000,0.45},2,1),F6="解除劳动合同一次性补偿金",VLOOKUP(AP6,{0,0.03;36000,0.1;144000,0.2;300000,0.25;420000,0.3;660000,0.35;960000,0.45},2,1))} -> #N/A | AR6: {=_xlfn.IFS(F6="正常工资薪金",VLOOKUP(AP6,{0,0;36000,2520;144000,16920;300000,31920;420000,52920;660000,85920;960000,181920},2,1),F6="一般劳务报酬所得",IF(AP6<=20000,0,IF(AS<=50000,2000,7000)),F6="全年一次性奖金收入",VLOOKUP(AP6/12,{0,0;3000,210;12000,1410;25000,2660;35000,4410;55000,7160;80000,15160},2,1),F6="解除劳动合同一次性补偿金",VLOOKUP(AP6,{0,0;36000,2520;144000,16920;300000,31920;420000,52920;660000,85920;960000,181920},2,1))} -> #N/A | AS6: =AP6*AQ6-AR6 -> #N/A | AT6: 0 | AU6: =BI6+BJ6 -> 2596.72 | AV6: =IF(AS6-AT6-AU6>0,AS6-AT6-AU6,0) -> #N/A | AX6: =IFERROR(IF(F6="正常工资薪金",VLOOKUP(D6&"*",个税上月累计情况!E:AL,26,0),0),0) -> 109505.3 | AY6: =IFERROR(IF(F6="正常工资薪金",VLOOKUP(D6&"*",个税上月累计情况!E:AL,27,0),0),0) -> 35000 | AZ6: =IFERROR(IF(F6="正常工资薪金",VLOOKUP(D6&"*",个税上月累计情况!E:AL,28,0),0),0) -> 12838.07 | BA6: =IFERROR(IF(F6="正常工资薪金",VLOOKUP(D6&"*",个税上月累计情况!E:AL,29,0),0),0) -> 0 | BB6: =IFERROR(IF(F6="正常工资薪金",VLOOKUP(D6&"*",个税上月累计情况!E:AL,30,0),0),0) -> 0 | BC6: =IFERROR(IF(F6="正常工资薪金",VLOOKUP(D6&"*",个税上月累计情况!E:AL,31,0),0),0) -> 0 | BD6: =IFERROR(IF(F6="正常工资薪金",VLOOKUP(D6&"*",个税上月累计情况!E:AL,32,0),0),0) -> 10500 | BE6: =IFERROR(IF(F6="正常工资薪金",VLOOKUP(D6&"*",个税上月累计情况!E:AL,33,0),0),0) -> 0 | BF6: =IFERROR(IF(F6="正常工资薪金",VLOOKUP(D6&"*",个税上月累计情况!E:AL,34,0),0),0) -> 0 | BG6: =IFERROR(IF(F6="正常工资薪金",VLOOKUP(D6&"*",个税上月累计情况!E:AN,35,0),0),0) -> 0 | BH6: =IFERROR(IF(F6="正常工资薪金",VLOOKUP(D6&"*",个税上月累计情况!E:AN,36,0),0),0) -> 0 | BI6: =IFERROR(IF(F6="正常工资薪金",VLOOKUP(D6&"*",个税上月累计情况!D:AW,46,0),0),0) -> 1841.91 | BJ6: =IFERROR(IF(F6="正常工资薪金",VLOOKUP(D6&"*",个税上月累计情况!D:AX,47,0),0),0) -> 754.81 | BK6: =VLOOKUP(B6,花名册!C:N,12,0) -> #N/A
B7: 刘洋 | C7: 居民身份证 | D7: 411102198406050051 | E7: 否 | F7: 正常工资薪金 | G7: {=_xlfn.IFS(F7="正常工资薪金",VLOOKUP(D7&"*",工资表明细!D:BL,61,0),F7="一般劳务报酬所得",VLOOKUP(D7&"*",工资表明细!D:BJ,59,0),F7="全年一次性奖金收入",VLOOKUP(D7&"*",工资表明细!D:BI,58,0),F7="解除劳动合同一次性补偿金",VLOOKUP(D7&"*",工资表明细!D:BH,57,0))} -> #N/A | H7: =IF(F7="一般劳务报酬所得",800,0) -> 0 | I7: 0 | J7: =IF(F7="正常工资薪金",5000,0) -> 5000 | K7: =IF(F7="正常工资薪金",VLOOKUP(D7&"*",工资表明细!D:AP,39,0),0) -> #N/A | L7: =IF(F7="正常工资薪金",VLOOKUP(D7&"*",工资表明细!D:AQ,40,0),0) -> #N/A | M7: =IF(F7="正常工资薪金",VLOOKUP(D7&"*",工资表明细!D:AR,41,0),0) -> #N/A | N7: =IF(F7="正常工资薪金",VLOOKUP(D7&"*",工资表明细!D:AT,43,0),0) -> #N/A | O7: 2 | P7: 2 | Q7: 2 | R7: 2 | S7: 2 | T7: 2 | U7: 2 | V7: 2 | W7: - | X7: 2 | Y7: - | Z7: - | AA7: - | AB7: 2 | AC7: =IF(F7="正常工资薪金",G7+AX7,"-") -> #N/A | AD7: =IF(F7="正常工资薪金",J7+AY7,"-") -> 40000 | AE7: =IF(F7="正常工资薪金",K7+L7+M7+N7+AZ7,"-") -> #N/A | AF7: =IFERROR(IF($F$5="正常工资薪金",IF(YEAR(BK7)<YEAR($BK$1),BA7/($D$1-1)*$D$1,BA7/DATEDIF(BK7,$BK$1,"M")*DATEDIF(BK7,$BK$1,"M")),"-"),0) -> 0 | AG7: =IFERROR(IF($F$5="正常工资薪金",IF(YEAR(BK7)<YEAR($BK$1),BB7/($D$1-1)*$D$1,BB7/DATEDIF(BK7,$BK$1,"M")*DATEDIF(BK7,$BK$1,"M")),"-"),0) -> 0 | AH7: =IFERROR(IF($F$5="正常工资薪金",IF(YEAR(BK7)<YEAR($BK$1),BC7/($D$1-1)*$D$1,BC7/(MONTH($BK$1)-MONTH(BK7))*(MONTH($BK$1)-MONTH(BK7)+1)),"-"),0) -> 0 | AI7: =IFERROR(IF($F$5="正常工资薪金",IF(YEAR(BK7)<YEAR($BK$1),BD7/($D$1-1)*$D$1,BD7/(MONTH($BK$1)-MONTH(BK7))*(MONTH($BK$1)-MONTH(BK7)+1)),"-"),0) -> 0 | AJ7: =IFERROR(IF($F$5="正常工资薪金",IF(YEAR(BK7)<YEAR($BK$1),BE7/($D$1-1)*$D$1,BE7/(MONTH($BK$1)-MONTH(BK7))*(MONTH($BK$1)-MONTH(BK7)+1)),"-"),0) -> 0 | AK7: =IFERROR(IF($F$5="正常工资薪金",IF(YEAR(BK7)<YEAR($BK$1),BF7/($D$1-1)*$D$1,BF7/(MONTH($BK$1)-MONTH(BK7))*(MONTH($BK$1)-MONTH(BK7)+1)),"-"),0) -> 0 | AL7: 0 | AM7: 0 | AN7: 100% | AO7: 0 | AP7: =IF(IF(F7="正常工资薪金",AC7-AD7-AE7-AF7-AG7-AH7-AI7-AJ7-AK7-AL7-AM7,G7-H7-I7)<0,0,IF(F7="正常工资薪金",AC7-AD7-AE7-AF7-AG7-AH7-AI7-AJ7-AK7-AL7-AM7,G7-H7-I7)) -> #N/A | AQ7: {=_xlfn.IFS(F7="正常工资薪金",VLOOKUP(AP7,{0,0.03;36000,0.1;144000,0.2;300000,0.25;420000,0.3;660000,0.35;960000,0.45},2,1),F7="一般劳务报酬所得",IF(AP7<=20000,0.2,IF(AP7<=50000,0.3,0.4)),F7="全年一次性奖金收入",VLOOKUP(AP7/12,{0,0.03;3000,0.1;12000,0.2;25000,0.25;35000,0.3;55000,0.35;80000,0.45},2,1),F7="解除劳动合同一次性补偿金",VLOOKUP(AP7,{0,0.03;36000,0.1;144000,0.2;300000,0.25;420000,0.3;660000,0.35;960000,0.45},2,1))} -> #N/A | AR7: {=_xlfn.IFS(F7="正常工资薪金",VLOOKUP(AP7,{0,0;36000,2520;144000,16920;300000,31920;420000,52920;660000,85920;960000,181920},2,1),F7="一般劳务报酬所得",IF(AP7<=20000,0,IF(AS<=50000,2000,7000)),F7="全年一次性奖金收入",VLOOKUP(AP7/12,{0,0;3000,210;12000,1410;25000,2660;35000,4410;55000,7160;80000,15160},2,1),F7="解除劳动合同一次性补偿金",VLOOKUP(AP7,{0,0;36000,2520;144000,16920;300000,31920;420000,52920;660000,85920;960000,181920},2,1))} -> #N/A | AS7: =AP7*AQ7-AR7 -> #N/A | AT7: 0 | AU7: =BI7+BJ7 -> 23960.43 | AV7: =IF(AS7-AT7-AU7>0,AS7-AT7-AU7,0) -> #N/A | AX7: =IFERROR(IF(F7="正常工资薪金",VLOOKUP(D7&"*",个税上月累计情况!E:AL,26,0),0),0) -> 280000 | AY7: =IFERROR(IF(F7="正常工资薪金",VLOOKUP(D7&"*",个税上月累计情况!E:AL,27,0),0),0) -> 35000 | AZ7: =IFERROR(IF(F7="正常工资薪金",VLOOKUP(D7&"*",个税上月累计情况!E:AL,28,0),0),0) -> 19597.83 | BA7: =IFERROR(IF(F7="正常工资薪金",VLOOKUP(D7&"*",个税上月累计情况!E:AL,29,0),0),0) -> 0 | BB7: =IFERROR(IF(F7="正常工资薪金",VLOOKUP(D7&"*",个税上月累计情况!E:AL,30,0),0),0) -> 21000 | BC7: =IFERROR(IF(F7="正常工资薪金",VLOOKUP(D7&"*",个税上月累计情况!E:AL,31,0),0),0) -> 0 | BD7: =IFERROR(IF(F7="正常工资薪金",VLOOKUP(D7&"*",个税上月累计情况!E:AL,32,0),0),0) -> 0 | BE7: =IFERROR(IF(F7="正常工资薪金",VLOOKUP(D7&"*",个税上月累计情况!E:AL,33,0),0),0) -> 0 | BF7: =IFERROR(IF(F7="正常工资薪金",VLOOKUP(D7&"*",个税上月累计情况!E:AL,34,0),0),0) -> 0 | BG7: =IFERROR(IF(F7="正常工资薪金",VLOOKUP(D7&"*",个税上月累计情况!E:AN,35,0),0),0) -> 0 | BH7: =IFERROR(IF(F7="正常工资薪金",VLOOKUP(D7&"*",个税上月累计情况!E:AN,36,0),0),0) -> 0 | BI7: =IFERROR(IF(F7="正常工资薪金",VLOOKUP(D7&"*",个税上月累计情况!D:AW,46,0),0),0) -> 18060.54 | BJ7: =IFERROR(IF(F7="正常工资薪金",VLOOKUP(D7&"*",个税上月累计情况!D:AX,47,0),0),0) -> 5899.89 | BK7: =VLOOKUP(B7,花名册!C:N,12,0) -> #N/A
B8: 杨娟 | C8: 居民身份证 | D8: 141034199511170105 | E8: 否 | F8: 正常工资薪金 | G8: {=_xlfn.IFS(F8="正常工资薪金",VLOOKUP(D8&"*",工资表明细!D:BL,61,0),F8="一般劳务报酬所得",VLOOKUP(D8&"*",工资表明细!D:BJ,59,0),F8="全年一次性奖金收入",VLOOKUP(D8&"*",工资表明细!D:BI,58,0),F8="解除劳动合同一次性补偿金",VLOOKUP(D8&"*",工资表明细!D:BH,57,0))} -> #N/A | H8: =IF(F8="一般劳务报酬所得",800,0) -> 0 | I8: 3935.01 | J8: =IF(F8="正常工资薪金",5000,0) -> 5000 | K8: =IF(F8="正常工资薪金",VLOOKUP(D8&"*",工资表明细!D:AP,39,0),0) -> #N/A | L8: =IF(F8="正常工资薪金",VLOOKUP(D8&"*",工资表明细!D:AQ,40,0),0) -> #N/A | M8: =IF(F8="正常工资薪金",VLOOKUP(D8&"*",工资表明细!D:AR,41,0),0) -> #N/A | N8: =IF(F8="正常工资薪金",VLOOKUP(D8&"*",工资表明细!D:AT,43,0),0) -> #N/A | O8: 3 | P8: 3 | Q8: 3 | R8: 3 | S8: 3 | T8: 3 | U8: 3 | V8: 3 | W8: - | X8: 3 | Y8: - | Z8: - | AA8: - | AB8: 3 | AC8: =IF(F8="正常工资薪金",G8+AX8,"-") -> #N/A | AD8: =IF(F8="正常工资薪金",J8+AY8,"-") -> 40000 | AE8: =IF(F8="正常工资薪金",K8+L8+M8+N8+AZ8,"-") -> #N/A | AF8: =IFERROR(IF($F$5="正常工资薪金",IF(YEAR(BK8)<YEAR($BK$1),BA8/($D$1-1)*$D$1,BA8/DATEDIF(BK8,$BK$1,"M")*DATEDIF(BK8,$BK$1,"M")),"-"),0) -> 0 | AG8: =IFERROR(IF($F$5="正常工资薪金",IF(YEAR(BK8)<YEAR($BK$1),BB8/($D$1-1)*$D$1,BB8/DATEDIF(BK8,$BK$1,"M")*DATEDIF(BK8,$BK$1,"M")),"-"),0) -> 0 | AH8: =IFERROR(IF($F$5="正常工资薪金",IF(YEAR(BK8)<YEAR($BK$1),BC8/($D$1-1)*$D$1,BC8/(MONTH($BK$1)-MONTH(BK8))*(MONTH($BK$1)-MONTH(BK8)+1)),"-"),0) -> 0 | AI8: =IFERROR(IF($F$5="正常工资薪金",IF(YEAR(BK8)<YEAR($BK$1),BD8/($D$1-1)*$D$1,BD8/(MONTH($BK$1)-MONTH(BK8))*(MONTH($BK$1)-MONTH(BK8)+1)),"-"),0) -> 0 | AJ8: =IFERROR(IF($F$5="正常工资薪金",IF(YEAR(BK8)<YEAR($BK$1),BE8/($D$1-1)*$D$1,BE8/(MONTH($BK$1)-MONTH(BK8))*(MONTH($BK$1)-MONTH(BK8)+1)),"-"),0) -> 0 | AK8: =IFERROR(IF($F$5="正常工资薪金",IF(YEAR(BK8)<YEAR($BK$1),BF8/($D$1-1)*$D$1,BF8/(MONTH($BK$1)-MONTH(BK8))*(MONTH($BK$1)-MONTH(BK8)+1)),"-"),0) -> 0 | AL8: 0 | AM8: 0 | AN8: 100% | AO8: 0 | AP8: =IF(IF(F8="正常工资薪金",AC8-AD8-AE8-AF8-AG8-AH8-AI8-AJ8-AK8-AL8-AM8,G8-H8-I8)<0,0,IF(F8="正常工资薪金",AC8-AD8-AE8-AF8-AG8-AH8-AI8-AJ8-AK8-AL8-AM8,G8-H8-I8)) -> #N/A | AQ8: {=_xlfn.IFS(F8="正常工资薪金",VLOOKUP(AP8,{0,0.03;36000,0.1;144000,0.2;300000,0.25;420000,0.3;660000,0.35;960000,0.45},2,1),F8="一般劳务报酬所得",IF(AP8<=20000,0.2,IF(AP8<=50000,0.3,0.4)),F8="全年一次性奖金收入",VLOOKUP(AP8/12,{0,0.03;3000,0.1;12000,0.2;25000,0.25;35000,0.3;55000,0.35;80000,0.45},2,1),F8="解除劳动合同一次性补偿金",VLOOKUP(AP8,{0,0.03;36000,0.1;144000,0.2;300000,0.25;420000,0.3;660000,0.35;960000,0.45},2,1))} -> #N/A | AR8: {=_xlfn.IFS(F8="正常工资薪金",VLOOKUP(AP8,{0,0;36000,2520;144000,16920;300000,31920;420000,52920;660000,85920;960000,181920},2,1),F8="一般劳务报酬所得",IF(AP8<=20000,0,IF(AS<=50000,2000,7000)),F8="全年一次性奖金收入",VLOOKUP(AP8/12,{0,0;3000,210;12000,1410;25000,2660;35000,4410;55000,7160;80000,15160},2,1),F8="解除劳动合同一次性补偿金",VLOOKUP(AP8,{0,0;36000,2520;144000,16920;300000,31920;420000,52920;660000,85920;960000,181920},2,1))} -> #N/A | AS8: =AP8*AQ8-AR8 -> #N/A | AT8: 0 | AU8: =BI8+BJ8 -> 518.97 | AV8: =IF(AS8-AT8-AU8>0,AS8-AT8-AU8,0) -> #N/A | AX8: =IFERROR(IF(F8="正常工资薪金",VLOOKUP(D8&"*",个税上月累计情况!E:AL,26,0),0),0) -> 39781.1 | AY8: =IFERROR(IF(F8="正常工资薪金",VLOOKUP(D8&"*",个税上月累计情况!E:AL,27,0),0),0) -> 35000 | AZ8: =IFERROR(IF(F8="正常工资薪金",VLOOKUP(D8&"*",个税上月累计情况!E:AL,28,0),0),0) -> 10535.07 | BA8: =IFERROR(IF(F8="正常工资薪金",VLOOKUP(D8&"*",个税上月累计情况!E:AL,29,0),0),0) -> 0 | BB8: =IFERROR(IF(F8="正常工资薪金",VLOOKUP(D8&"*",个税上月累计情况!E:AL,30,0),0),0) -> 0 | BC8: =IFERROR(IF(F8="正常工资薪金",VLOOKUP(D8&"*",个税上月累计情况!E:AL,31,0),0),0) -> 0 | BD8: =IFERROR(IF(F8="正常工资薪金",VLOOKUP(D8&"*",个税上月累计情况!E:AL,32,0),0),0) -> 0 | BE8: =IFERROR(IF(F8="正常工资薪金",VLOOKUP(D8&"*",个税上月累计情况!E:AL,33,0),0),0) -> 0 | BF8: =IFERROR(IF(F8="正常工资薪金",VLOOKUP(D8&"*",个税上月累计情况!E:AL,34,0),0),0) -> 0 | BG8: =IFERROR(IF(F8="正常工资薪金",VLOOKUP(D8&"*",个税上月累计情况!E:AN,35,0),0),0) -> 0 | BH8: =IFERROR(IF(F8="正常工资薪金",VLOOKUP(D8&"*",个税上月累计情况!E:AN,36,0),0),0) -> 0 | BI8: =IFERROR(IF(F8="正常工资薪金",VLOOKUP(D8&"*",个税上月累计情况!D:AW,46,0),0),0) -> 518.97 | BJ8: =IFERROR(IF(F8="正常工资薪金",VLOOKUP(D8&"*",个税上月累计情况!D:AX,47,0),0),0) -> 0 | BK8: =VLOOKUP(B8,花名册!C:N,12,0) -> #N/A
B9: 杨金雪 | C9: 居民身份证 | D9: 211382199701014125 | E9: 否 | F9: 正常工资薪金 | G9: {=_xlfn.IFS(F9="正常工资薪金",VLOOKUP(D9&"*",工资表明细!D:BL,61,0),F9="一般劳务报酬所得",VLOOKUP(D9&"*",工资表明细!D:BJ,59,0),F9="全年一次性奖金收入",VLOOKUP(D9&"*",工资表明细!D:BI,58,0),F9="解除劳动合同一次性补偿金",VLOOKUP(D9&"*",工资表明细!D:BH,57,0))} -> #N/A | H9: =IF(F9="一般劳务报酬所得",800,0) -> 0 | I9: 0 | J9: =IF(F9="正常工资薪金",5000,0) -> 5000 | K9: =IF(F9="正常工资薪金",VLOOKUP(D9&"*",工资表明细!D:AP,39,0),0) -> #N/A | L9: =IF(F9="正常工资薪金",VLOOKUP(D9&"*",工资表明细!D:AQ,40,0),0) -> #N/A | M9: =IF(F9="正常工资薪金",VLOOKUP(D9&"*",工资表明细!D:AR,41,0),0) -> #N/A | N9: =IF(F9="正常工资薪金",VLOOKUP(D9&"*",工资表明细!D:AT,43,0),0) -> #N/A | O9: 4 | P9: 4 | Q9: 4 | R9: 4 | S9: 4 | T9: 4 | U9: 4 | V9: 4 | W9: - | X9: 4 | Y9: - | Z9: - | AA9: - | AB9: 4 | AC9: =IF(F9="正常工资薪金",G9+AX9,"-") -> #N/A | AD9: =IF(F9="正常工资薪金",J9+AY9,"-") -> 40000 | AE9: =IF(F9="正常工资薪金",K9+L9+M9+N9+AZ9,"-") -> #N/A | AF9: =IFERROR(IF($F$5="正常工资薪金",IF(YEAR(BK9)<YEAR($BK$1),BA9/($D$1-1)*$D$1,BA9/DATEDIF(BK9,$BK$1,"M")*DATEDIF(BK9,$BK$1,"M")),"-"),0) -> 0 | AG9: =IFERROR(IF($F$5="正常工资薪金",IF(YEAR(BK9)<YEAR($BK$1),BB9/($D$1-1)*$D$1,BB9/DATEDIF(BK9,$BK$1,"M")*DATEDIF(BK9,$BK$1,"M")),"-"),0) -> 0 | AH9: =IFERROR(IF($F$5="正常工资薪金",IF(YEAR(BK9)<YEAR($BK$1),BC9/($D$1-1)*$D$1,BC9/(MONTH($BK$1)-MONTH(BK9))*(MONTH($BK$1)-MONTH(BK9)+1)),"-"),0) -> 0 | AI9: =IFERROR(IF($F$5="正常工资薪金",IF(YEAR(BK9)<YEAR($BK$1),BD9/($D$1-1)*$D$1,BD9/(MONTH($BK$1)-MONTH(BK9))*(MONTH($BK$1)-MONTH(BK9)+1)),"-"),0) -> 0 | AJ9: =IFERROR(IF($F$5="正常工资薪金",IF(YEAR(BK9)<YEAR($BK$1),BE9/($D$1-1)*$D$1,BE9/(MONTH($BK$1)-MONTH(BK9))*(MONTH($BK$1)-MONTH(BK9)+1)),"-"),0) -> 0 | AK9: =IFERROR(IF($F$5="正常工资薪金",IF(YEAR(BK9)<YEAR($BK$1),BF9/($D$1-1)*$D$1,BF9/(MONTH($BK$1)-MONTH(BK9))*(MONTH($BK$1)-MONTH(BK9)+1)),"-"),0) -> 0 | AL9: 0 | AM9: 0 | AN9: 100% | AO9: 0 | AP9: =IF(IF(F9="正常工资薪金",AC9-AD9-AE9-AF9-AG9-AH9-AI9-AJ9-AK9-AL9-AM9,G9-H9-I9)<0,0,IF(F9="正常工资薪金",AC9-AD9-AE9-AF9-AG9-AH9-AI9-AJ9-AK9-AL9-AM9,G9-H9-I9)) -> #N/A | AQ9: {=_xlfn.IFS(F9="正常工资薪金",VLOOKUP(AP9,{0,0.03;36000,0.1;144000,0.2;300000,0.25;420000,0.3;660000,0.35;960000,0.45},2,1),F9="一般劳务报酬所得",IF(AP9<=20000,0.2,IF(AP9<=50000,0.3,0.4)),F9="全年一次性奖金收入",VLOOKUP(AP9/12,{0,0.03;3000,0.1;12000,0.2;25000,0.25;35000,0.3;55000,0.35;80000,0.45},2,1),F9="解除劳动合同一次性补偿金",VLOOKUP(AP9,{0,0.03;36000,0.1;144000,0.2;300000,0.25;420000,0.3;660000,0.35;960000,0.45},2,1))} -> #N/A | AR9: {=_xlfn.IFS(F9="正常工资薪金",VLOOKUP(AP9,{0,0;36000,2520;144000,16920;300000,31920;420000,52920;660000,85920;960000,181920},2,1),F9="一般劳务报酬所得",IF(AP9<=20000,0,IF(AS<=50000,2000,7000)),F9="全年一次性奖金收入",VLOOKUP(AP9/12,{0,0;3000,210;12000,1410;25000,2660;35000,4410;55000,7160;80000,15160},2,1),F9="解除劳动合同一次性补偿金",VLOOKUP(AP9,{0,0;36000,2520;144000,16920;300000,31920;420000,52920;660000,85920;960000,181920},2,1))} -> #N/A | AS9: =AP9*AQ9-AR9 -> #N/A | AT9: 0 | AU9: =BI9+BJ9 -> 711.99 | AV9: =IF(AS9-AT9-AU9>0,AS9-AT9-AU9,0) -> #N/A | AX9: =IFERROR(IF(F9="正常工资薪金",VLOOKUP(D9&"*",个税上月累计情况!E:AL,26,0),0),0) -> 66881.14 | AY9: =IFERROR(IF(F9="正常工资薪金",VLOOKUP(D9&"*",个税上月累计情况!E:AL,27,0),0),0) -> 35000 | AZ9: =IFERROR(IF(F9="正常工资薪金",VLOOKUP(D9&"*",个税上月累计情况!E:AL,28,0),0),0) -> 8148.07 | BA9: =IFERROR(IF(F9="正常工资薪金",VLOOKUP(D9&"*",个税上月累计情况!E:AL,29,0),0),0) -> 0 | BB9: =IFERROR(IF(F9="正常工资薪金",VLOOKUP(D9&"*",个税上月累计情况!E:AL,30,0),0),0) -> 0 | BC9: =IFERROR(IF(F9="正常工资薪金",VLOOKUP(D9&"*",个税上月累计情况!E:AL,31,0),0),0) -> 0 | BD9: =IFERROR(IF(F9="正常工资薪金",VLOOKUP(D9&"*",个税上月累计情况!E:AL,32,0),0),0) -> 0 | BE9: =IFERROR(IF(F9="正常工资薪金",VLOOKUP(D9&"*",个税上月累计情况!E:AL,33,0),0),0) -> 0 | BF9: =IFERROR(IF(F9="正常工资薪金",VLOOKUP(D9&"*",个税上月累计情况!E:AL,34,0),0),0) -> 0 | BG9: =IFERROR(IF(F9="正常工资薪金",VLOOKUP(D9&"*",个税上月累计情况!E:AN,35,0),0),0) -> 0 | BH9: =IFERROR(IF(F9="正常工资薪金",VLOOKUP(D9&"*",个税上月累计情况!E:AN,36,0),0),0) -> 0 | BI9: =IFERROR(IF(F9="正常工资薪金",VLOOKUP(D9&"*",个税上月累计情况!D:AW,46,0),0),0) -> 654.69 | BJ9: =IFERROR(IF(F9="正常工资薪金",VLOOKUP(D9&"*",个税上月累计情况!D:AX,47,0),0),0) -> 57.3 | BK9: =VLOOKUP(B9,花名册!C:N,12,0) -> #N/A
B10: 马顺华 | C10: 居民身份证 | D10: 429006198803300316 | E10: 否 | F10: 正常工资薪金 | G10: {=_xlfn.IFS(F10="正常工资薪金",VLOOKUP(D10&"*",工资表明细!D:BL,61,0),F10="一般劳务报酬所得",VLOOKUP(D10&"*",工资表明细!D:BJ,59,0),F10="全年一次性奖金收入",VLOOKUP(D10&"*",工资表明细!D:BI,58,0),F10="解除劳动合同一次性补偿金",VLOOKUP(D10&"*",工资表明细!D:BH,57,0))} -> #N/A | H10: =IF(F10="一般劳务报酬所得",800,0) -> 0 | I10: 0 | J10: =IF(F10="正常工资薪金",5000,0) -> 5000 | K10: =IF(F10="正常工资薪金",VLOOKUP(D10&"*",工资表明细!D:AP,39,0),0) -> #N/A | L10: =IF(F10="正常工资薪金",VLOOKUP(D10&"*",工资表明细!D:AQ,40,0),0) -> #N/A | M10: =IF(F10="正常工资薪金",VLOOKUP(D10&"*",工资表明细!D:AR,41,0),0) -> #N/A | N10: =IF(F10="正常工资薪金",VLOOKUP(D10&"*",工资表明细!D:AT,43,0),0) -> #N/A | O10: 5 | P10: 5 | Q10: 5 | R10: 5 | S10: 5 | T10: 5 | U10: 5 | V10: 5 | W10: - | X10: 5 | Y10: - | Z10: - | AA10: - | AB10: 5 | AC10: =IF(F10="正常工资薪金",G10+AX10,"-") -> #N/A | AD10: =IF(F10="正常工资薪金",J10+AY10,"-") -> 40000 | AE10: =IF(F10="正常工资薪金",K10+L10+M10+N10+AZ10,"-") -> #N/A | AF10: =IFERROR(IF($F$5="正常工资薪金",IF(YEAR(BK10)<YEAR($BK$1),BA10/($D$1-1)*$D$1,BA10/DATEDIF(BK10,$BK$1,"M")*DATEDIF(BK10,$BK$1,"M")),"-"),0) -> 0 | AG10: =IFERROR(IF($F$5="正常工资薪金",IF(YEAR(BK10)<YEAR($BK$1),BB10/($D$1-1)*$D$1,BB10/DATEDIF(BK10,$BK$1,"M")*DATEDIF(BK10,$BK$1,"M")),"-"),0) -> 0 | AH10: =IFERROR(IF($F$5="正常工资薪金",IF(YEAR(BK10)<YEAR($BK$1),BC10/($D$1-1)*$D$1,BC10/(MONTH($BK$1)-MONTH(BK10))*(MONTH($BK$1)-MONTH(BK10)+1)),"-"),0) -> 0 | AI10: =IFERROR(IF($F$5="正常工资薪金",IF(YEAR(BK10)<YEAR($BK$1),BD10/($D$1-1)*$D$1,BD10/(MONTH($BK$1)-MONTH(BK10))*(MONTH($BK$1)-MONTH(BK10)+1)),"-"),0) -> 0 | AJ10: =IFERROR(IF($F$5="正常工资薪金",IF(YEAR(BK10)<YEAR($BK$1),BE10/($D$1-1)*$D$1,BE10/(MONTH($BK$1)-MONTH(BK10))*(MONTH($BK$1)-MONTH(BK10)+1)),"-"),0) -> 0 | AK10: =IFERROR(IF($F$5="正常工资薪金",IF(YEAR(BK10)<YEAR($BK$1),BF10/($D$1-1)*$D$1,BF10/(MONTH($BK$1)-MONTH(BK10))*(MONTH($BK$1)-MONTH(BK10)+1)),"-"),0) -> 0 | AL10: 0 | AM10: 0 | AN10: 100% | AO10: 0 | AP10: =IF(IF(F10="正常工资薪金",AC10-AD10-AE10-AF10-AG10-AH10-AI10-AJ10-AK10-AL10-AM10,G10-H10-I10)<0,0,IF(F10="正常工资薪金",AC10-AD10-AE10-AF10-AG10-AH10-AI10-AJ10-AK10-AL10-AM10,G10-H10-I10)) -> #N/A | AQ10: {=_xlfn.IFS(F10="正常工资薪金",VLOOKUP(AP10,{0,0.03;36000,0.1;144000,0.2;300000,0.25;420000,0.3;660000,0.35;960000,0.45},2,1),F10="一般劳务报酬所得",IF(AP10<=20000,0.2,IF(AP10<=50000,0.3,0.4)),F10="全年一次性奖金收入",VLOOKUP(AP10/12,{0,0.03;3000,0.1;12000,0.2;25000,0.25;35000,0.3;55000,0.35;80000,0.45},2,1),F10="解除劳动合同一次性补偿金",VLOOKUP(AP10,{0,0.03;36000,0.1;144000,0.2;300000,0.25;420000,0.3;660000,0.35;960000,0.45},2,1))} -> #N/A | AR10: {=_xlfn.IFS(F10="正常工资薪金",VLOOKUP(AP10,{0,0;36000,2520;144000,16920;300000,31920;420000,52920;660000,85920;960000,181920},2,1),F10="一般劳务报酬所得",IF(AP10<=20000,0,IF(AS<=50000,2000,7000)),F10="全年一次性奖金收入",VLOOKUP(AP10/12,{0,0;3000,210;12000,1410;25000,2660;35000,4410;55000,7160;80000,15160},2,1),F10="解除劳动合同一次性补偿金",VLOOKUP(AP10,{0,0;36000,2520;144000,16920;300000,31920;420000,52920;660000,85920;960000,181920},2,1))} -> #N/A | AS10: =AP10*AQ10-AR10 -> #N/A | AT10: 0 | AU10: =BI10+BJ10 -> 566.73 | AV10: =IF(AS10-AT10-AU10>0,AS10-AT10-AU10,0) -> #N/A | AX10: =IFERROR(IF(F10="正常工资薪金",VLOOKUP(D10&"*",个税上月累计情况!E:AL,26,0),0),0) -> 72991.45 | AY10: =IFERROR(IF(F10="正常工资薪金",VLOOKUP(D10&"*",个税上月累计情况!E:AL,27,0),0),0) -> 35000 | AZ10: =IFERROR(IF(F10="正常工资薪金",VLOOKUP(D10&"*",个税上月累计情况!E:AL,28,0),0),0) -> 8600.34 | BA10: =IFERROR(IF(F10="正常工资薪金",VLOOKUP(D10&"*",个税上月累计情况!E:AL,29,0),0),0) -> 0 | BB10: =IFERROR(IF(F10="正常工资薪金",VLOOKUP(D10&"*",个税上月累计情况!E:AL,30,0),0),0) -> 10500 | BC10: =IFERROR(IF(F10="正常工资薪金",VLOOKUP(D10&"*",个税上月累计情况!E:AL,31,0),0),0) -> 0 | BD10: =IFERROR(IF(F10="正常工资薪金",VLOOKUP(D10&"*",个税上月累计情况!E:AL,32,0),0),0) -> 0 | BE10: =IFERROR(IF(F10="正常工资薪金",VLOOKUP(D10&"*",个税上月累计情况!E:AL,33,0),0),0) -> 0 | BF10: =IFERROR(IF(F10="正常工资薪金",VLOOKUP(D10&"*",个税上月累计情况!E:AL,34,0),0),0) -> 0 | BG10: =IFERROR(IF(F10="正常工资薪金",VLOOKUP(D10&"*",个税上月累计情况!E:AN,35,0),0),0) -> 0 | BH10: =IFERROR(IF(F10="正常工资薪金",VLOOKUP(D10&"*",个税上月累计情况!E:AN,36,0),0),0) -> 0 | BI10: =IFERROR(IF(F10="正常工资薪金",VLOOKUP(D10&"*",个税上月累计情况!D:AW,46,0),0),0) -> 481.94 | BJ10: =IFERROR(IF(F10="正常工资薪金",VLOOKUP(D10&"*",个税上月累计情况!D:AX,47,0),0),0) -> 84.79 | BK10: =VLOOKUP(B10,花名册!C:N,12,0) -> #N/A
B11: 耿惠欣 | C11: 居民身份证 | D11: 37028519940425172X | E11: 否 | F11: 正常工资薪金 | G11: {=_xlfn.IFS(F11="正常工资薪金",VLOOKUP(D11&"*",工资表明细!D:BL,61,0),F11="一般劳务报酬所得",VLOOKUP(D11&"*",工资表明细!D:BJ,59,0),F11="全年一次性奖金收入",VLOOKUP(D11&"*",工资表明细!D:BI,58,0),F11="解除劳动合同一次性补偿金",VLOOKUP(D11&"*",工资表明细!D:BH,57,0))} -> #N/A | H11: =IF(F11="一般劳务报酬所得",800,0) -> 0 | I11: 3763.53 | J11: =IF(F11="正常工资薪金",5000,0) -> 5000 | K11: =IF(F11="正常工资薪金",VLOOKUP(D11&"*",工资表明细!D:AP,39,0),0) -> #N/A | L11: =IF(F11="正常工资薪金",VLOOKUP(D11&"*",工资表明细!D:AQ,40,0),0) -> #N/A | M11: =IF(F11="正常工资薪金",VLOOKUP(D11&"*",工资表明细!D:AR,41,0),0) -> #N/A | N11: =IF(F11="正常工资薪金",VLOOKUP(D11&"*",工资表明细!D:AT,43,0),0) -> #N/A | O11: 6 | P11: 6 | Q11: 6 | R11: 6 | S11: 6 | T11: 6 | U11: 6 | V11: 6 | W11: - | X11: 6 | Y11: - | Z11: - | AA11: - | AB11: 6 | AC11: =IF(F11="正常工资薪金",G11+AX11,"-") -> #N/A | AD11: =IF(F11="正常工资薪金",J11+AY11,"-") -> 40000 | AE11: =IF(F11="正常工资薪金",K11+L11+M11+N11+AZ11,"-") -> #N/A | AF11: =IFERROR(IF($F$5="正常工资薪金",IF(YEAR(BK11)<YEAR($BK$1),BA11/($D$1-1)*$D$1,BA11/DATEDIF(BK11,$BK$1,"M")*DATEDIF(BK11,$BK$1,"M")),"-"),0) -> 0 | AG11: =IFERROR(IF($F$5="正常工资薪金",IF(YEAR(BK11)<YEAR($BK$1),BB11/($D$1-1)*$D$1,BB11/DATEDIF(BK11,$BK$1,"M")*DATEDIF(BK11,$BK$1,"M")),"-"),0) -> 0 | AH11: =IFERROR(IF($F$5="正常工资薪金",IF(YEAR(BK11)<YEAR($BK$1),BC11/($D$1-1)*$D$1,BC11/(MONTH($BK$1)-MONTH(BK11))*(MONTH($BK$1)-MONTH(BK11)+1)),"-"),0) -> 0 | AI11: =IFERROR(IF($F$5="正常工资薪金",IF(YEAR(BK11)<YEAR($BK$1),BD11/($D$1-1)*$D$1,BD11/(MONTH($BK$1)-MONTH(BK11))*(MONTH($BK$1)-MONTH(BK11)+1)),"-"),0) -> 0 | AJ11: =IFERROR(IF($F$5="正常工资薪金",IF(YEAR(BK11)<YEAR($BK$1),BE11/($D$1-1)*$D$1,BE11/(MONTH($BK$1)-MONTH(BK11))*(MONTH($BK$1)-MONTH(BK11)+1)),"-"),0) -> 0 | AK11: =IFERROR(IF($F$5="正常工资薪金",IF(YEAR(BK11)<YEAR($BK$1),BF11/($D$1-1)*$D$1,BF11/(MONTH($BK$1)-MONTH(BK11))*(MONTH($BK$1)-MONTH(BK11)+1)),"-"),0) -> 0 | AL11: 0 | AM11: 0 | AN11: 100% | AO11: 0 | AP11: =IF(IF(F11="正常工资薪金",AC11-AD11-AE11-AF11-AG11-AH11-AI11-AJ11-AK11-AL11-AM11,G11-H11-I11)<0,0,IF(F11="正常工资薪金",AC11-AD11-AE11-AF11-AG11-AH11-AI11-AJ11-AK11-AL11-AM11,G11-H11-I11)) -> #N/A | AQ11: {=_xlfn.IFS(F11="正常工资薪金",VLOOKUP(AP11,{0,0.03;36000,0.1;144000,0.2;300000,0.25;420000,0.3;660000,0.35;960000,0.45},2,1),F11="一般劳务报酬所得",IF(AP11<=20000,0.2,IF(AP11<=50000,0.3,0.4)),F11="全年一次性奖金收入",VLOOKUP(AP11/12,{0,0.03;3000,0.1;12000,0.2;25000,0.25;35000,0.3;55000,0.35;80000,0.45},2,1),F11="解除劳动合同一次性补偿金",VLOOKUP(AP11,{0,0.03;36000,0.1;144000,0.2;300000,0.25;420000,0.3;660000,0.35;960000,0.45},2,1))} -> #N/A | AR11: {=_xlfn.IFS(F11="正常工资薪金",VLOOKUP(AP11,{0,0;36000,2520;144000,16920;300000,31920;420000,52920;660000,85920;960000,181920},2,1),F11="一般劳务报酬所得",IF(AP11<=20000,0,IF(AS<=50000,2000,7000)),F11="全年一次性奖金收入",VLOOKUP(AP11/12,{0,0;3000,210;12000,1410;25000,2660;35000,4410;55000,7160;80000,15160},2,1),F11="解除劳动合同一次性补偿金",VLOOKUP(AP11,{0,0;36000,2520;144000,16920;300000,31920;420000,52920;660000,85920;960000,181920},2,1))} -> #N/A | AS11: =AP11*AQ11-AR11 -> #N/A | AT11: 0 | AU11: =BI11+BJ11 -> 436.85 | AV11: =IF(AS11-AT11-AU11>0,AS11-AT11-AU11,0) -> #N/A | AX11: =IFERROR(IF(F11="正常工资薪金",VLOOKUP(D11&"*",个税上月累计情况!E:AL,26,0),0),0) -> 48198.57 | AY11: =IFERROR(IF(F11="正常工资薪金",VLOOKUP(D11&"*",个税上月累计情况!E:AL,27,0),0),0) -> 35000 | AZ11: =IFERROR(IF(F11="正常工资薪金",VLOOKUP(D11&"*",个税上月累计情况!E:AL,28,0),0),0) -> 9719.43 | BA11: =IFERROR(IF(F11="正常工资薪金",VLOOKUP(D11&"*",个税上月累计情况!E:AL,29,0),0),0) -> 0 | BB11: =IFERROR(IF(F11="正常工资薪金",VLOOKUP(D11&"*",个税上月累计情况!E:AL,30,0),0),0) -> 0 | BC11: =IFERROR(IF(F11="正常工资薪金",VLOOKUP(D11&"*",个税上月累计情况!E:AL,31,0),0),0) -> 0 | BD11: =IFERROR(IF(F11="正常工资薪金",VLOOKUP(D11&"*",个税上月累计情况!E:AL,32,0),0),0) -> 10500 | BE11: =IFERROR(IF(F11="正常工资薪金",VLOOKUP(D11&"*",个税上月累计情况!E:AL,33,0),0),0) -> 0 | BF11: =IFERROR(IF(F11="正常工资薪金",VLOOKUP(D11&"*",个税上月累计情况!E:AL,34,0),0),0) -> 0 | BG11: =IFERROR(IF(F11="正常工资薪金",VLOOKUP(D11&"*",个税上月累计情况!E:AN,35,0),0),0) -> 0 | BH11: =IFERROR(IF(F11="正常工资薪金",VLOOKUP(D11&"*",个税上月累计情况!E:AN,36,0),0),0) -> 0 | BI11: =IFERROR(IF(F11="正常工资薪金",VLOOKUP(D11&"*",个税上月累计情况!D:AW,46,0),0),0) -> 436.85 | BJ11: =IFERROR(IF(F11="正常工资薪金",VLOOKUP(D11&"*",个税上月累计情况!D:AX,47,0),0),0) -> 0 | BK11: =VLOOKUP(B11,花名册!C:N,12,0) -> #N/A
B12: 王鹏辉 | C12: 居民身份证 | D12: 421181198909130413 | E12: 否 | F12: 正常工资薪金 | G12: {=_xlfn.IFS(F12="正常工资薪金",VLOOKUP(D12&"*",工资表明细!D:BL,61,0),F12="一般劳务报酬所得",VLOOKUP(D12&"*",工资表明细!D:BJ,59,0),F12="全年一次性奖金收入",VLOOKUP(D12&"*",工资表明细!D:BI,58,0),F12="解除劳动合同一次性补偿金",VLOOKUP(D12&"*",工资表明细!D:BH,57,0))} -> #N/A | H12: =IF(F12="一般劳务报酬所得",800,0) -> 0 | I12: 0 | J12: =IF(F12="正常工资薪金",5000,0) -> 5000 | K12: =IF(F12="正常工资薪金",VLOOKUP(D12&"*",工资表明细!D:AP,39,0),0) -> #N/A | L12: =IF(F12="正常工资薪金",VLOOKUP(D12&"*",工资表明细!D:AQ,40,0),0) -> #N/A | M12: =IF(F12="正常工资薪金",VLOOKUP(D12&"*",工资表明细!D:AR,41,0),0) -> #N/A | N12: =IF(F12="正常工资薪金",VLOOKUP(D12&"*",工资表明细!D:AT,43,0),0) -> #N/A | O12: 7 | P12: 7 | Q12: 7 | R12: 7 | S12: 7 | T12: 7 | U12: 7 | V12: 7 | W12: - | X12: 7 | Y12: - | Z12: - | AA12: - | AB12: 7 | AC12: =IF(F12="正常工资薪金",G12+AX12,"-") -> #N/A | AD12: =IF(F12="正常工资薪金",J12+AY12,"-") -> 40000 | AE12: =IF(F12="正常工资薪金",K12+L12+M12+N12+AZ12,"-") -> #N/A | AF12: =IFERROR(IF($F$5="正常工资薪金",IF(YEAR(BK12)<YEAR($BK$1),BA12/($D$1-1)*$D$1,BA12/DATEDIF(BK12,$BK$1,"M")*DATEDIF(BK12,$BK$1,"M")),"-"),0) -> 0 | AG12: =IFERROR(IF($F$5="正常工资薪金",IF(YEAR(BK12)<YEAR($BK$1),BB12/($D$1-1)*$D$1,BB12/DATEDIF(BK12,$BK$1,"M")*DATEDIF(BK12,$BK$1,"M")),"-"),0) -> 0 | AH12: =IFERROR(IF($F$5="正常工资薪金",IF(YEAR(BK12)<YEAR($BK$1),BC12/($D$1-1)*$D$1,BC12/(MONTH($BK$1)-MONTH(BK12))*(MONTH($BK$1)-MONTH(BK12)+1)),"-"),0) -> 0 | AI12: =IFERROR(IF($F$5="正常工资薪金",IF(YEAR(BK12)<YEAR($BK$1),BD12/($D$1-1)*$D$1,BD12/(MONTH($BK$1)-MONTH(BK12))*(MONTH($BK$1)-MONTH(BK12)+1)),"-"),0) -> 0 | AJ12: =IFERROR(IF($F$5="正常工资薪金",IF(YEAR(BK12)<YEAR($BK$1),BE12/($D$1-1)*$D$1,BE12/(MONTH($BK$1)-MONTH(BK12))*(MONTH($BK$1)-MONTH(BK12)+1)),"-"),0) -> 0 | AK12: =IFERROR(IF($F$5="正常工资薪金",IF(YEAR(BK12)<YEAR($BK$1),BF12/($D$1-1)*$D$1,BF12/(MONTH($BK$1)-MONTH(BK12))*(MONTH($BK$1)-MONTH(BK12)+1)),"-"),0) -> 0 | AL12: 0 | AM12: 0 | AN12: 100% | AO12: 0 | AP12: =IF(IF(F12="正常工资薪金",AC12-AD12-AE12-AF12-AG12-AH12-AI12-AJ12-AK12-AL12-AM12,G12-H12-I12)<0,0,IF(F12="正常工资薪金",AC12-AD12-AE12-AF12-AG12-AH12-AI12-AJ12-AK12-AL12-AM12,G12-H12-I12)) -> #N/A | AQ12: {=_xlfn.IFS(F12="正常工资薪金",VLOOKUP(AP12,{0,0.03;36000,0.1;144000,0.2;300000,0.25;420000,0.3;660000,0.35;960000,0.45},2,1),F12="一般劳务报酬所得",IF(AP12<=20000,0.2,IF(AP12<=50000,0.3,0.4)),F12="全年一次性奖金收入",VLOOKUP(AP12/12,{0,0.03;3000,0.1;12000,0.2;25000,0.25;35000,0.3;55000,0.35;80000,0.45},2,1),F12="解除劳动合同一次性补偿金",VLOOKUP(AP12,{0,0.03;36000,0.1;144000,0.2;300000,0.25;420000,0.3;660000,0.35;960000,0.45},2,1))} -> #N/A | AR12: {=_xlfn.IFS(F12="正常工资薪金",VLOOKUP(AP12,{0,0;36000,2520;144000,16920;300000,31920;420000,52920;660000,85920;960000,181920},2,1),F12="一般劳务报酬所得",IF(AP12<=20000,0,IF(AS<=50000,2000,7000)),F12="全年一次性奖金收入",VLOOKUP(AP12/12,{0,0;3000,210;12000,1410;25000,2660;35000,4410;55000,7160;80000,15160},2,1),F12="解除劳动合同一次性补偿金",VLOOKUP(AP12,{0,0;36000,2520;144000,16920;300000,31920;420000,52920;660000,85920;960000,181920},2,1))} -> #N/A | AS12: =AP12*AQ12-AR12 -> #N/A | AT12: 0 | AU12: =BI12+BJ12 -> 5150.77 | AV12: =IF(AS12-AT12-AU12>0,AS12-AT12-AU12,0) -> #N/A | AX12: =IFERROR(IF(F12="正常工资薪金",VLOOKUP(D12&"*",个税上月累计情况!E:AL,26,0),0),0) -> 147222.56 | AY12: =IFERROR(IF(F12="正常工资薪金",VLOOKUP(D12&"*",个税上月累计情况!E:AL,27,0),0),0) -> 35000 | AZ12: =IFERROR(IF(F12="正常工资薪金",VLOOKUP(D12&"*",个税上月累计情况!E:AL,28,0),0),0) -> 25014.85 | BA12: =IFERROR(IF(F12="正常工资薪金",VLOOKUP(D12&"*",个税上月累计情况!E:AL,29,0),0),0) -> 0 | BB12: =IFERROR(IF(F12="正常工资薪金",VLOOKUP(D12&"*",个税上月累计情况!E:AL,30,0),0),0) -> 0 | BC12: =IFERROR(IF(F12="正常工资薪金",VLOOKUP(D12&"*",个税上月累计情况!E:AL,31,0),0),0) -> 0 | BD12: =IFERROR(IF(F12="正常工资薪金",VLOOKUP(D12&"*",个税上月累计情况!E:AL,32,0),0),0) -> 10500 | BE12: =IFERROR(IF(F12="正常工资薪金",VLOOKUP(D12&"*",个税上月累计情况!E:AL,33,0),0),0) -> 0 | BF12: =IFERROR(IF(F12="正常工资薪金",VLOOKUP(D12&"*",个税上月累计情况!E:AL,34,0),0),0) -> 0 | BG12: =IFERROR(IF(F12="正常工资薪金",VLOOKUP(D12&"*",个税上月累计情况!E:AN,35,0),0),0) -> 0 | BH12: =IFERROR(IF(F12="正常工资薪金",VLOOKUP(D12&"*",个税上月累计情况!E:AN,36,0),0),0) -> 0 | BI12: =IFERROR(IF(F12="正常工资薪金",VLOOKUP(D12&"*",个税上月累计情况!D:AW,46,0),0),0) -> 4202.79 | BJ12: =IFERROR(IF(F12="正常工资薪金",VLOOKUP(D12&"*",个税上月累计情况!D:AX,47,0),0),0) -> 947.98 | BK12: =VLOOKUP(B12,花名册!C:N,12,0) -> #N/A
B13: 郭子轶 | C13: 居民身份证 | D13: 510106197603021421 | E13: 否 | F13: 正常工资薪金 | G13: {=_xlfn.IFS(F13="正常工资薪金",VLOOKUP(D13&"*",工资表明细!D:BL,61,0),F13="一般劳务报酬所得",VLOOKUP(D13&"*",工资表明细!D:BJ,59,0),F13="全年一次性奖金收入",VLOOKUP(D13&"*",工资表明细!D:BI,58,0),F13="解除劳动合同一次性补偿金",VLOOKUP(D13&"*",工资表明细!D:BH,57,0))} -> #N/A | H13: =IF(F13="一般劳务报酬所得",800,0) -> 0 | I13: 0 | J13: =IF(F13="正常工资薪金",5000,0) -> 5000 | K13: =IF(F13="正常工资薪金",VLOOKUP(D13&"*",工资表明细!D:AP,39,0),0) -> #N/A | L13: =IF(F13="正常工资薪金",VLOOKUP(D13&"*",工资表明细!D:AQ,40,0),0) -> #N/A | M13: =IF(F13="正常工资薪金",VLOOKUP(D13&"*",工资表明细!D:AR,41,0),0) -> #N/A | N13: =IF(F13="正常工资薪金",VLOOKUP(D13&"*",工资表明细!D:AT,43,0),0) -> #N/A | O13: 8 | P13: 8 | Q13: 8 | R13: 8 | S13: 8 | T13: 8 | U13: 8 | V13: 8 | W13: - | X13: 8 | Y13: - | Z13: - | AA13: - | AB13: 8 | AC13: =IF(F13="正常工资薪金",G13+AX13,"-") -> #N/A | AD13: =IF(F13="正常工资薪金",J13+AY13,"-") -> 40000 | AE13: =IF(F13="正常工资薪金",K13+L13+M13+N13+AZ13,"-") -> #N/A | AF13: =IFERROR(IF($F$5="正常工资薪金",IF(YEAR(BK13)<YEAR($BK$1),BA13/($D$1-1)*$D$1,BA13/DATEDIF(BK13,$BK$1,"M")*DATEDIF(BK13,$BK$1,"M")),"-"),0) -> 0 | AG13: =IFERROR(IF($F$5="正常工资薪金",IF(YEAR(BK13)<YEAR($BK$1),BB13/($D$1-1)*$D$1,BB13/DATEDIF(BK13,$BK$1,"M")*DATEDIF(BK13,$BK$1,"M")),"-"),0) -> 0 | AH13: =IFERROR(IF($F$5="正常工资薪金",IF(YEAR(BK13)<YEAR($BK$1),BC13/($D$1-1)*$D$1,BC13/(MONTH($BK$1)-MONTH(BK13))*(MONTH($BK$1)-MONTH(BK13)+1)),"-"),0) -> 0 | AI13: =IFERROR(IF($F$5="正常工资薪金",IF(YEAR(BK13)<YEAR($BK$1),BD13/($D$1-1)*$D$1,BD13/(MONTH($BK$1)-MONTH(BK13))*(MONTH($BK$1)-MONTH(BK13)+1)),"-"),0) -> 0 | AJ13: =IFERROR(IF($F$5="正常工资薪金",IF(YEAR(BK13)<YEAR($BK$1),BE13/($D$1-1)*$D$1,BE13/(MONTH($BK$1)-MONTH(BK13))*(MONTH($BK$1)-MONTH(BK13)+1)),"-"),0) -> 0 | AK13: =IFERROR(IF($F$5="正常工资薪金",IF(YEAR(BK13)<YEAR($BK$1),BF13/($D$1-1)*$D$1,BF13/(MONTH($BK$1)-MONTH(BK13))*(MONTH($BK$1)-MONTH(BK13)+1)),"-"),0) -> 0 | AL13: 0 | AM13: 0 | AN13: 100% | AO13: 0 | AP13: =IF(IF(F13="正常工资薪金",AC13-AD13-AE13-AF13-AG13-AH13-AI13-AJ13-AK13-AL13-AM13,G13-H13-I13)<0,0,IF(F13="正常工资薪金",AC13-AD13-AE13-AF13-AG13-AH13-AI13-AJ13-AK13-AL13-AM13,G13-H13-I13)) -> #N/A | AQ13: {=_xlfn.IFS(F13="正常工资薪金",VLOOKUP(AP13,{0,0.03;36000,0.1;144000,0.2;300000,0.25;420000,0.3;660000,0.35;960000,0.45},2,1),F13="一般劳务报酬所得",IF(AP13<=20000,0.2,IF(AP13<=50000,0.3,0.4)),F13="全年一次性奖金收入",VLOOKUP(AP13/12,{0,0.03;3000,0.1;12000,0.2;25000,0.25;35000,0.3;55000,0.35;80000,0.45},2,1),F13="解除劳动合同一次性补偿金",VLOOKUP(AP13,{0,0.03;36000,0.1;144000,0.2;300000,0.25;420000,0.3;660000,0.35;960000,0.45},2,1))} -> #N/A | AR13: {=_xlfn.IFS(F13="正常工资薪金",VLOOKUP(AP13,{0,0;36000,2520;144000,16920;300000,31920;420000,52920;660000,85920;960000,181920},2,1),F13="一般劳务报酬所得",IF(AP13<=20000,0,IF(AS<=50000,2000,7000)),F13="全年一次性奖金收入",VLOOKUP(AP13/12,{0,0;3000,210;12000,1410;25000,2660;35000,4410;55000,7160;80000,15160},2,1),F13="解除劳动合同一次性补偿金",VLOOKUP(AP13,{0,0;36000,2520;144000,16920;300000,31920;420000,52920;660000,85920;960000,181920},2,1))} -> #N/A | AS13: =AP13*AQ13-AR13 -> #N/A | AT13: 0 | AU13: =BI13+BJ13 -> 13809.79 | AV13: =IF(AS13-AT13-AU13>0,AS13-AT13-AU13,0) -> #N/A | AX13: =IFERROR(IF(F13="正常工资薪金",VLOOKUP(D13&"*",个税上月累计情况!E:AL,26,0),0),0) -> 226856.07 | AY13: =IFERROR(IF(F13="正常工资薪金",VLOOKUP(D13&"*",个税上月累计情况!E:AL,27,0),0),0) -> 35000 | AZ13: =IFERROR(IF(F13="正常工资薪金",VLOOKUP(D13&"*",个税上月累计情况!E:AL,28,0),0),0) -> 38207.12 | BA13: =IFERROR(IF(F13="正常工资薪金",VLOOKUP(D13&"*",个税上月累计情况!E:AL,29,0),0),0) -> 0 | BB13: =IFERROR(IF(F13="正常工资薪金",VLOOKUP(D13&"*",个税上月累计情况!E:AL,30,0),0),0) -> 0 | BC13: =IFERROR(IF(F13="正常工资薪金",VLOOKUP(D13&"*",个税上月累计情况!E:AL,31,0),0),0) -> 0 | BD13: =IFERROR(IF(F13="正常工资薪金",VLOOKUP(D13&"*",个税上月累计情况!E:AL,32,0),0),0) -> 0 | BE13: =IFERROR(IF(F13="正常工资薪金",VLOOKUP(D13&"*",个税上月累计情况!E:AL,33,0),0),0) -> 0 | BF13: =IFERROR(IF(F13="正常工资薪金",VLOOKUP(D13&"*",个税上月累计情况!E:AL,34,0),0),0) -> 0 | BG13: =IFERROR(IF(F13="正常工资薪金",VLOOKUP(D13&"*",个税上月累计情况!E:AN,35,0),0),0) -> 0 | BH13: =IFERROR(IF(F13="正常工资薪金",VLOOKUP(D13&"*",个税上月累计情况!E:AN,36,0),0),0) -> 0 | BI13: =IFERROR(IF(F13="正常工资薪金",VLOOKUP(D13&"*",个税上月累计情况!D:AW,46,0),0),0) -> 10649.91 | BJ13: =IFERROR(IF(F13="正常工资薪金",VLOOKUP(D13&"*",个税上月累计情况!D:AX,47,0),0),0) -> 3159.88 | BK13: =VLOOKUP(B13,花名册!C:N,12,0) -> #N/A
B14: 陈昱光 | C14: 居民身份证 | D14: 410881199208201514 | E14: 否 | F14: 正常工资薪金 | G14: {=_xlfn.IFS(F14="正常工资薪金",VLOOKUP(D14&"*",工资表明细!D:BL,61,0),F14="一般劳务报酬所得",VLOOKUP(D14&"*",工资表明细!D:BJ,59,0),F14="全年一次性奖金收入",VLOOKUP(D14&"*",工资表明细!D:BI,58,0),F14="解除劳动合同一次性补偿金",VLOOKUP(D14&"*",工资表明细!D:BH,57,0))} -> #N/A | H14: =IF(F14="一般劳务报酬所得",800,0) -> 0 | I14: 0 | J14: =IF(F14="正常工资薪金",5000,0) -> 5000 | K14: =IF(F14="正常工资薪金",VLOOKUP(D14&"*",工资表明细!D:AP,39,0),0) -> #N/A | L14: =IF(F14="正常工资薪金",VLOOKUP(D14&"*",工资表明细!D:AQ,40,0),0) -> #N/A | M14: =IF(F14="正常工资薪金",VLOOKUP(D14&"*",工资表明细!D:AR,41,0),0) -> #N/A | N14: =IF(F14="正常工资薪金",VLOOKUP(D14&"*",工资表明细!D:AT,43,0),0) -> #N/A | O14: 9 | P14: 9 | Q14: 9 | R14: 9 | S14: 9 | T14: 9 | U14: 9 | V14: 9 | W14: - | X14: 9 | Y14: - | Z14: - | AA14: - | AB14: 9 | AC14: =IF(F14="正常工资薪金",G14+AX14,"-") -> #N/A | AD14: =IF(F14="正常工资薪金",J14+AY14,"-") -> 40000 | AE14: =IF(F14="正常工资薪金",K14+L14+M14+N14+AZ14,"-") -> #N/A | AF14: =IFERROR(IF($F$5="正常工资薪金",IF(YEAR(BK14)<YEAR($BK$1),BA14/($D$1-1)*$D$1,BA14/DATEDIF(BK14,$BK$1,"M")*DATEDIF(BK14,$BK$1,"M")),"-"),0) -> 0 | AG14: =IFERROR(IF($F$5="正常工资薪金",IF(YEAR(BK14)<YEAR($BK$1),BB14/($D$1-1)*$D$1,BB14/DATEDIF(BK14,$BK$1,"M")*DATEDIF(BK14,$BK$1,"M")),"-"),0) -> 0 | AH14: =IFERROR(IF($F$5="正常工资薪金",IF(YEAR(BK14)<YEAR($BK$1),BC14/($D$1-1)*$D$1,BC14/(MONTH($BK$1)-MONTH(BK14))*(MONTH($BK$1)-MONTH(BK14)+1)),"-"),0) -> 0 | AI14: =IFERROR(IF($F$5="正常工资薪金",IF(YEAR(BK14)<YEAR($BK$1),BD14/($D$1-1)*$D$1,BD14/(MONTH($BK$1)-MONTH(BK14))*(MONTH($BK$1)-MONTH(BK14)+1)),"-"),0) -> 0 | AJ14: =IFERROR(IF($F$5="正常工资薪金",IF(YEAR(BK14)<YEAR($BK$1),BE14/($D$1-1)*$D$1,BE14/(MONTH($BK$1)-MONTH(BK14))*(MONTH($BK$1)-MONTH(BK14)+1)),"-"),0) -> 0 | AK14: =IFERROR(IF($F$5="正常工资薪金",IF(YEAR(BK14)<YEAR($BK$1),BF14/($D$1-1)*$D$1,BF14/(MONTH($BK$1)-MONTH(BK14))*(MONTH($BK$1)-MONTH(BK14)+1)),"-"),0) -> 0 | AL14: 0 | AM14: 0 | AN14: 100% | AO14: 0 | AP14: =IF(IF(F14="正常工资薪金",AC14-AD14-AE14-AF14-AG14-AH14-AI14-AJ14-AK14-AL14-AM14,G14-H14-I14)<0,0,IF(F14="正常工资薪金",AC14-AD14-AE14-AF14-AG14-AH14-AI14-AJ14-AK14-AL14-AM14,G14-H14-I14)) -> #N/A | AQ14: {=_xlfn.IFS(F14="正常工资薪金",VLOOKUP(AP14,{0,0.03;36000,0.1;144000,0.2;300000,0.25;420000,0.3;660000,0.35;960000,0.45},2,1),F14="一般劳务报酬所得",IF(AP14<=20000,0.2,IF(AP14<=50000,0.3,0.4)),F14="全年一次性奖金收入",VLOOKUP(AP14/12,{0,0.03;3000,0.1;12000,0.2;25000,0.25;35000,0.3;55000,0.35;80000,0.45},2,1),F14="解除劳动合同一次性补偿金",VLOOKUP(AP14,{0,0.03;36000,0.1;144000,0.2;300000,0.25;420000,0.3;660000,0.35;960000,0.45},2,1))} -> #N/A | AR14: {=_xlfn.IFS(F14="正常工资薪金",VLOOKUP(AP14,{0,0;36000,2520;144000,16920;300000,31920;420000,52920;660000,85920;960000,181920},2,1),F14="一般劳务报酬所得",IF(AP14<=20000,0,IF(AS<=50000,2000,7000)),F14="全年一次性奖金收入",VLOOKUP(AP14/12,{0,0;3000,210;12000,1410;25000,2660;35000,4410;55000,7160;80000,15160},2,1),F14="解除劳动合同一次性补偿金",VLOOKUP(AP14,{0,0;36000,2520;144000,16920;300000,31920;420000,52920;660000,85920;960000,181920},2,1))} -> #N/A | AS14: =AP14*AQ14-AR14 -> #N/A | AT14: 0 | AU14: =BI14+BJ14 -> 4043.85 | AV14: =IF(AS14-AT14-AU14>0,AS14-AT14-AU14,0) -> #N/A | AX14: =IFERROR(IF(F14="正常工资薪金",VLOOKUP(D14&"*",个税上月累计情况!E:AL,26,0),0),0) -> 112643.55 | AY14: =IFERROR(IF(F14="正常工资薪金",VLOOKUP(D14&"*",个税上月累计情况!E:AL,27,0),0),0) -> 35000 | AZ14: =IFERROR(IF(F14="正常工资薪金",VLOOKUP(D14&"*",个税上月累计情况!E:AL,28,0),0),0) -> 12005.07 | BA14: =IFERROR(IF(F14="正常工资薪金",VLOOKUP(D14&"*",个税上月累计情况!E:AL,29,0),0),0) -> 0 | BB14: =IFERROR(IF(F14="正常工资薪金",VLOOKUP(D14&"*",个税上月累计情况!E:AL,30,0),0),0) -> 0 | BC14: =IFERROR(IF(F14="正常工资薪金",VLOOKUP(D14&"*",个税上月累计情况!E:AL,31,0),0),0) -> 0 | BD14: =IFERROR(IF(F14="正常工资薪金",VLOOKUP(D14&"*",个税上月累计情况!E:AL,32,0),0),0) -> 0 | BE14: =IFERROR(IF(F14="正常工资薪金",VLOOKUP(D14&"*",个税上月累计情况!E:AL,33,0),0),0) -> 0 | BF14: =IFERROR(IF(F14="正常工资薪金",VLOOKUP(D14&"*",个税上月累计情况!E:AL,34,0),0),0) -> 0 | BG14: =IFERROR(IF(F14="正常工资薪金",VLOOKUP(D14&"*",个税上月累计情况!E:AN,35,0),0),0) -> 0 | BH14: =IFERROR(IF(F14="正常工资薪金",VLOOKUP(D14&"*",个税上月累计情况!E:AN,36,0),0),0) -> 0 | BI14: =IFERROR(IF(F14="正常工资薪金",VLOOKUP(D14&"*",个税上月累计情况!D:AW,46,0),0),0) -> 3107.68 | BJ14: =IFERROR(IF(F14="正常工资薪金",VLOOKUP(D14&"*",个税上月累计情况!D:AX,47,0),0),0) -> 936.17 | BK14: =VLOOKUP(B14,花名册!C:N,12,0) -> #N/A
B15: 姜文超 | C15: 居民身份证 | D15: 370831198704081514 | E15: 否 | F15: 正常工资薪金 | G15: {=_xlfn.IFS(F15="正常工资薪金",VLOOKUP(D15&"*",工资表明细!D:BL,61,0),F15="一般劳务报酬所得",VLOOKUP(D15&"*",工资表明细!D:BJ,59,0),F15="全年一次性奖金收入",VLOOKUP(D15&"*",工资表明细!D:BI,58,0),F15="解除劳动合同一次性补偿金",VLOOKUP(D15&"*",工资表明细!D:BH,57,0))} -> #N/A | H15: =IF(F15="一般劳务报酬所得",800,0) -> 0 | I15: 0 | J15: =IF(F15="正常工资薪金",5000,0) -> 5000 | K15: =IF(F15="正常工资薪金",VLOOKUP(D15&"*",工资表明细!D:AP,39,0),0) -> #N/A | L15: =IF(F15="正常工资薪金",VLOOKUP(D15&"*",工资表明细!D:AQ,40,0),0) -> #N/A | M15: =IF(F15="正常工资薪金",VLOOKUP(D15&"*",工资表明细!D:AR,41,0),0) -> #N/A | N15: =IF(F15="正常工资薪金",VLOOKUP(D15&"*",工资表明细!D:AT,43,0),0) -> #N/A | O15: 10 | P15: 10 | Q15: 10 | R15: 10 | S15: 10 | T15: 10 | U15: 10 | V15: 10 | W15: - | X15: 10 | Y15: - | Z15: - | AA15: - | AB15: 10 | AC15: =IF(F15="正常工资薪金",G15+AX15,"-") -> #N/A | AD15: =IF(F15="正常工资薪金",J15+AY15,"-") -> 40000 | AE15: =IF(F15="正常工资薪金",K15+L15+M15+N15+AZ15,"-") -> #N/A | AF15: =IFERROR(IF($F$5="正常工资薪金",IF(YEAR(BK15)<YEAR($BK$1),BA15/($D$1-1)*$D$1,BA15/DATEDIF(BK15,$BK$1,"M")*DATEDIF(BK15,$BK$1,"M")),"-"),0) -> 0 | AG15: =IFERROR(IF($F$5="正常工资薪金",IF(YEAR(BK15)<YEAR($BK$1),BB15/($D$1-1)*$D$1,BB15/DATEDIF(BK15,$BK$1,"M")*DATEDIF(BK15,$BK$1,"M")),"-"),0) -> 0 | AH15: =IFERROR(IF($F$5="正常工资薪金",IF(YEAR(BK15)<YEAR($BK$1),BC15/($D$1-1)*$D$1,BC15/(MONTH($BK$1)-MONTH(BK15))*(MONTH($BK$1)-MONTH(BK15)+1)),"-"),0) -> 0 | AI15: =IFERROR(IF($F$5="正常工资薪金",IF(YEAR(BK15)<YEAR($BK$1),BD15/($D$1-1)*$D$1,BD15/(MONTH($BK$1)-MONTH(BK15))*(MONTH($BK$1)-MONTH(BK15)+1)),"-"),0) -> 0 | AJ15: =IFERROR(IF($F$5="正常工资薪金",IF(YEAR(BK15)<YEAR($BK$1),BE15/($D$1-1)*$D$1,BE15/(MONTH($BK$1)-MONTH(BK15))*(MONTH($BK$1)-MONTH(BK15)+1)),"-"),0) -> 0 | AK15: =IFERROR(IF($F$5="正常工资薪金",IF(YEAR(BK15)<YEAR($BK$1),BF15/($D$1-1)*$D$1,BF15/(MONTH($BK$1)-MONTH(BK15))*(MONTH($BK$1)-MONTH(BK15)+1)),"-"),0) -> 0 | AL15: 0 | AM15: 0 | AN15: 100% | AO15: 0 | AP15: =IF(IF(F15="正常工资薪金",AC15-AD15-AE15-AF15-AG15-AH15-AI15-AJ15-AK15-AL15-AM15,G15-H15-I15)<0,0,IF(F15="正常工资薪金",AC15-AD15-AE15-AF15-AG15-AH15-AI15-AJ15-AK15-AL15-AM15,G15-H15-I15)) -> #N/A | AQ15: {=_xlfn.IFS(F15="正常工资薪金",VLOOKUP(AP15,{0,0.03;36000,0.1;144000,0.2;300000,0.25;420000,0.3;660000,0.35;960000,0.45},2,1),F15="一般劳务报酬所得",IF(AP15<=20000,0.2,IF(AP15<=50000,0.3,0.4)),F15="全年一次性奖金收入",VLOOKUP(AP15/12,{0,0.03;3000,0.1;12000,0.2;25000,0.25;35000,0.3;55000,0.35;80000,0.45},2,1),F15="解除劳动合同一次性补偿金",VLOOKUP(AP15,{0,0.03;36000,0.1;144000,0.2;300000,0.25;420000,0.3;660000,0.35;960000,0.45},2,1))} -> #N/A | AR15: {=_xlfn.IFS(F15="正常工资薪金",VLOOKUP(AP15,{0,0;36000,2520;144000,16920;300000,31920;420000,52920;660000,85920;960000,181920},2,1),F15="一般劳务报酬所得",IF(AP15<=20000,0,IF(AS<=50000,2000,7000)),F15="全年一次性奖金收入",VLOOKUP(AP15/12,{0,0;3000,210;12000,1410;25000,2660;35000,4410;55000,7160;80000,15160},2,1),F15="解除劳动合同一次性补偿金",VLOOKUP(AP15,{0,0;36000,2520;144000,16920;300000,31920;420000,52920;660000,85920;960000,181920},2,1))} -> #N/A | AS15: =AP15*AQ15-AR15 -> #N/A | AT15: 0 | AU15: =BI15+BJ15 -> 26549.99 | AV15: =IF(AS15-AT15-AU15>0,AS15-AT15-AU15,0) -> #N/A | AX15: =IFERROR(IF(F15="正常工资薪金",VLOOKUP(D15&"*",个税上月累计情况!E:AL,26,0),0),0) -> 280000 | AY15: =IFERROR(IF(F15="正常工资薪金",VLOOKUP(D15&"*",个税上月累计情况!E:AL,27,0),0),0) -> 35000 | AZ15: =IFERROR(IF(F15="正常工资薪金",VLOOKUP(D15&"*",个税上月累计情况!E:AL,28,0),0),0) -> 17150.07 | BA15: =IFERROR(IF(F15="正常工资薪金",VLOOKUP(D15&"*",个税上月累计情况!E:AL,29,0),0),0) -> 0 | BB15: =IFERROR(IF(F15="正常工资薪金",VLOOKUP(D15&"*",个税上月累计情况!E:AL,30,0),0),0) -> 10500 | BC15: =IFERROR(IF(F15="正常工资薪金",VLOOKUP(D15&"*",个税上月累计情况!E:AL,31,0),0),0) -> 0 | BD15: =IFERROR(IF(F15="正常工资薪金",VLOOKUP(D15&"*",个税上月累计情况!E:AL,32,0),0),0) -> 0 | BE15: =IFERROR(IF(F15="正常工资薪金",VLOOKUP(D15&"*",个税上月累计情况!E:AL,33,0),0),0) -> 0 | BF15: =IFERROR(IF(F15="正常工资薪金",VLOOKUP(D15&"*",个税上月累计情况!E:AL,34,0),0),0) -> 0 | BG15: =IFERROR(IF(F15="正常工资薪金",VLOOKUP(D15&"*",个税上月累计情况!E:AN,35,0),0),0) -> 0 | BH15: =IFERROR(IF(F15="正常工资薪金",VLOOKUP(D15&"*",个税上月累计情况!E:AN,36,0),0),0) -> 0 | BI15: =IFERROR(IF(F15="正常工资薪金",VLOOKUP(D15&"*",个税上月累计情况!D:AW,46,0),0),0) -> 20339.99 | BJ15: =IFERROR(IF(F15="正常工资薪金",VLOOKUP(D15&"*",个税上月累计情况!D:AX,47,0),0),0) -> 6210 | BK15: =VLOOKUP(B15,花名册!C:N,12,0) -> #N/A
B16: 周海明 | C16: 居民身份证 | D16: 130427198606116938 | E16: 否 | F16: 正常工资薪金 | G16: {=_xlfn.IFS(F16="正常工资薪金",VLOOKUP(D16&"*",工资表明细!D:BL,61,0),F16="一般劳务报酬所得",VLOOKUP(D16&"*",工资表明细!D:BJ,59,0),F16="全年一次性奖金收入",VLOOKUP(D16&"*",工资表明细!D:BI,58,0),F16="解除劳动合同一次性补偿金",VLOOKUP(D16&"*",工资表明细!D:BH,57,0))} -> #N/A | H16: =IF(F16="一般劳务报酬所得",800,0) -> 0 | I16: 0 | J16: =IF(F16="正常工资薪金",5000,0) -> 5000 | K16: =IF(F16="正常工资薪金",VLOOKUP(D16&"*",工资表明细!D:AP,39,0),0) -> #N/A | L16: =IF(F16="正常工资薪金",VLOOKUP(D16&"*",工资表明细!D:AQ,40,0),0) -> #N/A | M16: =IF(F16="正常工资薪金",VLOOKUP(D16&"*",工资表明细!D:AR,41,0),0) -> #N/A | N16: =IF(F16="正常工资薪金",VLOOKUP(D16&"*",工资表明细!D:AT,43,0),0) -> #N/A | O16: 11 | P16: 11 | Q16: 11 | R16: 11 | S16: 11 | T16: 11 | U16: 11 | V16: 11 | W16: - | X16: 11 | Y16: - | Z16: - | AA16: - | AB16: 11 | AC16: =IF(F16="正常工资薪金",G16+AX16,"-") -> #N/A | AD16: =IF(F16="正常工资薪金",J16+AY16,"-") -> 40000 | AE16: =IF(F16="正常工资薪金",K16+L16+M16+N16+AZ16,"-") -> #N/A | AF16: =IFERROR(IF($F$5="正常工资薪金",IF(YEAR(BK16)<YEAR($BK$1),BA16/($D$1-1)*$D$1,BA16/DATEDIF(BK16,$BK$1,"M")*DATEDIF(BK16,$BK$1,"M")),"-"),0) -> 0 | AG16: =IFERROR(IF($F$5="正常工资薪金",IF(YEAR(BK16)<YEAR($BK$1),BB16/($D$1-1)*$D$1,BB16/DATEDIF(BK16,$BK$1,"M")*DATEDIF(BK16,$BK$1,"M")),"-"),0) -> 0 | AH16: =IFERROR(IF($F$5="正常工资薪金",IF(YEAR(BK16)<YEAR($BK$1),BC16/($D$1-1)*$D$1,BC16/(MONTH($BK$1)-MONTH(BK16))*(MONTH($BK$1)-MONTH(BK16)+1)),"-"),0) -> 0 | AI16: =IFERROR(IF($F$5="正常工资薪金",IF(YEAR(BK16)<YEAR($BK$1),BD16/($D$1-1)*$D$1,BD16/(MONTH($BK$1)-MONTH(BK16))*(MONTH($BK$1)-MONTH(BK16)+1)),"-"),0) -> 0 | AJ16: =IFERROR(IF($F$5="正常工资薪金",IF(YEAR(BK16)<YEAR($BK$1),BE16/($D$1-1)*$D$1,BE16/(MONTH($BK$1)-MONTH(BK16))*(MONTH($BK$1)-MONTH(BK16)+1)),"-"),0) -> 0 | AK16: =IFERROR(IF($F$5="正常工资薪金",IF(YEAR(BK16)<YEAR($BK$1),BF16/($D$1-1)*$D$1,BF16/(MONTH($BK$1)-MONTH(BK16))*(MONTH($BK$1)-MONTH(BK16)+1)),"-"),0) -> 0 | AL16: 0 | AM16: 0 | AN16: 100% | AO16: 0 | AP16: =IF(IF(F16="正常工资薪金",AC16-AD16-AE16-AF16-AG16-AH16-AI16-AJ16-AK16-AL16-AM16,G16-H16-I16)<0,0,IF(F16="正常工资薪金",AC16-AD16-AE16-AF16-AG16-AH16-AI16-AJ16-AK16-AL16-AM16,G16-H16-I16)) -> #N/A | AQ16: {=_xlfn.IFS(F16="正常工资薪金",VLOOKUP(AP16,{0,0.03;36000,0.1;144000,0.2;300000,0.25;420000,0.3;660000,0.35;960000,0.45},2,1),F16="一般劳务报酬所得",IF(AP16<=20000,0.2,IF(AP16<=50000,0.3,0.4)),F16="全年一次性奖金收入",VLOOKUP(AP16/12,{0,0.03;3000,0.1;12000,0.2;25000,0.25;35000,0.3;55000,0.35;80000,0.45},2,1),F16="解除劳动合同一次性补偿金",VLOOKUP(AP16,{0,0.03;36000,0.1;144000,0.2;300000,0.25;420000,0.3;660000,0.35;960000,0.45},2,1))} -> #N/A | AR16: {=_xlfn.IFS(F16="正常工资薪金",VLOOKUP(AP16,{0,0;36000,2520;144000,16920;300000,31920;420000,52920;660000,85920;960000,181920},2,1),F16="一般劳务报酬所得",IF(AP16<=20000,0,IF(AS<=50000,2000,7000)),F16="全年一次性奖金收入",VLOOKUP(AP16/12,{0,0;3000,210;12000,1410;25000,2660;35000,4410;55000,7160;80000,15160},2,1),F16="解除劳动合同一次性补偿金",VLOOKUP(AP16,{0,0;36000,2520;144000,16920;300000,31920;420000,52920;660000,85920;960000,181920},2,1))} -> #N/A | AS16: =AP16*AQ16-AR16 -> #N/A | AT16: 0 | AU16: =BI16+BJ16 -> 2110.11 | AV16: =IF(AS16-AT16-AU16>0,AS16-AT16-AU16,0) -> #N/A | AX16: =IFERROR(IF(F16="正常工资薪金",VLOOKUP(D16&"*",个税上月累计情况!E:AL,26,0),0),0) -> 100605.4 | AY16: =IFERROR(IF(F16="正常工资薪金",VLOOKUP(D16&"*",个税上月累计情况!E:AL,27,0),0),0) -> 35000 | AZ16: =IFERROR(IF(F16="正常工资薪金",VLOOKUP(D16&"*",个税上月累计情况!E:AL,28,0),0),0) -> 11585.07 | BA16: =IFERROR(IF(F16="正常工资薪金",VLOOKUP(D16&"*",个税上月累计情况!E:AL,29,0),0),0) -> 0 | BB16: =IFERROR(IF(F16="正常工资薪金",VLOOKUP(D16&"*",个税上月累计情况!E:AL,30,0),0),0) -> 0 | BC16: =IFERROR(IF(F16="正常工资薪金",VLOOKUP(D16&"*",个税上月累计情况!E:AL,31,0),0),0) -> 0 | BD16: =IFERROR(IF(F16="正常工资薪金",VLOOKUP(D16&"*",个税上月累计情况!E:AL,32,0),0),0) -> 10500 | BE16: =IFERROR(IF(F16="正常工资薪金",VLOOKUP(D16&"*",个税上月累计情况!E:AL,33,0),0),0) -> 0 | BF16: =IFERROR(IF(F16="正常工资薪金",VLOOKUP(D16&"*",个税上月累计情况!E:AL,34,0),0),0) -> 0 | BG16: =IFERROR(IF(F16="正常工资薪金",VLOOKUP(D16&"*",个税上月累计情况!E:AN,35,0),0),0) -> 0 | BH16: =IFERROR(IF(F16="正常工资薪金",VLOOKUP(D16&"*",个税上月累计情况!E:AN,36,0),0),0) -> 0 | BI16: =IFERROR(IF(F16="正常工资薪金",VLOOKUP(D16&"*",个税上月累计情况!D:AW,46,0),0),0) -> 2110.11 | BJ16: =IFERROR(IF(F16="正常工资薪金",VLOOKUP(D16&"*",个税上月累计情况!D:AX,47,0),0),0) -> 0 | BK16: =VLOOKUP(B16,花名册!C:N,12,0) -> #N/A
... B58: 陈鑫鑫 | C58: 居民身份证 | D58: 230121199808271040 | E58: 否 | F58: 正常工资薪金 | G58: {=_xlfn.IFS(F58="正常工资薪金",VLOOKUP(D58&"*",工资表明细!D:BL,61,0),F58="一般劳务报酬所得",VLOOKUP(D58&"*",工资表明细!D:BJ,59,0),F58="全年一次性奖金收入",VLOOKUP(D58&"*",工资表明细!D:BI,58,0),F58="解除劳动合同一次性补偿金",VLOOKUP(D58&"*",工资表明细!D:BH,57,0))} -> #N/A | H58: =IF(F58="一般劳务报酬所得",800,0) -> 0 | I58: 0 | J58: =IF(F58="正常工资薪金",5000,0) -> 5000 | K58: =IF(F58="正常工资薪金",VLOOKUP(D58&"*",工资表明细!D:AP,39,0),0) -> #N/A | L58: =IF(F58="正常工资薪金",VLOOKUP(D58&"*",工资表明细!D:AQ,40,0),0) -> #N/A | M58: =IF(F58="正常工资薪金",VLOOKUP(D58&"*",工资表明细!D:AR,41,0),0) -> #N/A | N58: =IF(F58="正常工资薪金",VLOOKUP(D58&"*",工资表明细!D:AT,43,0),0) -> #N/A | O58: 53 | P58: 53 | Q58: 53 | R58: 53 | S58: 53 | T58: 53 | U58: 53 | V58: 53 | W58: - | X58: 53 | Y58: - | Z58: - | AA58: - | AB58: 53 | AC58: =IF(F58="正常工资薪金",G58+AX58,"-") -> #N/A | AD58: =IF(F58="正常工资薪金",J58+AY58,"-") -> 25000 | AE58: =IF(F58="正常工资薪金",K58+L58+M58+N58+AZ58,"-") -> #N/A | AF58: =IFERROR(IF($F$5="正常工资薪金",IF(YEAR(BK58)<YEAR($BK$1),BA58/($D$1-1)*$D$1,BA58/DATEDIF(BK58,$BK$1,"M")*DATEDIF(BK58,$BK$1,"M")),"-"),0) -> 0 | AG58: =IFERROR(IF($F$5="正常工资薪金",IF(YEAR(BK58)<YEAR($BK$1),BB58/($D$1-1)*$D$1,BB58/DATEDIF(BK58,$BK$1,"M")*DATEDIF(BK58,$BK$1,"M")),"-"),0) -> 0 | AH58: =IFERROR(IF($F$5="正常工资薪金",IF(YEAR(BK58)<YEAR($BK$1),BC58/($D$1-1)*$D$1,BC58/(MONTH($BK$1)-MONTH(BK58))*(MONTH($BK$1)-MONTH(BK58)+1)),"-"),0) -> 0 | AI58: =IFERROR(IF($F$5="正常工资薪金",IF(YEAR(BK58)<YEAR($BK$1),BD58/($D$1-1)*$D$1,BD58/(MONTH($BK$1)-MONTH(BK58))*(MONTH($BK$1)-MONTH(BK58)+1)),"-"),0) -> 0 | AJ58: =IFERROR(IF($F$5="正常工资薪金",IF(YEAR(BK58)<YEAR($BK$1),BE58/($D$1-1)*$D$1,BE58/(MONTH($BK$1)-MONTH(BK58))*(MONTH($BK$1)-MONTH(BK58)+1)),"-"),0) -> 0 | AK58: =IFERROR(IF($F$5="正常工资薪金",IF(YEAR(BK58)<YEAR($BK$1),BF58/($D$1-1)*$D$1,BF58/(MONTH($BK$1)-MONTH(BK58))*(MONTH($BK$1)-MONTH(BK58)+1)),"-"),0) -> 0 | AL58: 0 | AM58: 0 | AN58: 100% | AO58: 0 | AP58: =IF(IF(F58="正常工资薪金",AC58-AD58-AE58-AF58-AG58-AH58-AI58-AJ58-AK58-AL58-AM58,G58-H58-I58)<0,0,IF(F58="正常工资薪金",AC58-AD58-AE58-AF58-AG58-AH58-AI58-AJ58-AK58-AL58-AM58,G58-H58-I58)) -> #N/A | AQ58: {=_xlfn.IFS(F58="正常工资薪金",VLOOKUP(AP58,{0,0.03;36000,0.1;144000,0.2;300000,0.25;420000,0.3;660000,0.35;960000,0.45},2,1),F58="一般劳务报酬所得",IF(AP58<=20000,0.2,IF(AP58<=50000,0.3,0.4)),F58="全年一次性奖金收入",VLOOKUP(AP58/12,{0,0.03;3000,0.1;12000,0.2;25000,0.25;35000,0.3;55000,0.35;80000,0.45},2,1),F58="解除劳动合同一次性补偿金",VLOOKUP(AP58,{0,0.03;36000,0.1;144000,0.2;300000,0.25;420000,0.3;660000,0.35;960000,0.45},2,1))} -> #N/A | AR58: {=_xlfn.IFS(F58="正常工资薪金",VLOOKUP(AP58,{0,0;36000,2520;144000,16920;300000,31920;420000,52920;660000,85920;960000,181920},2,1),F58="一般劳务报酬所得",IF(AP58<=20000,0,IF(AS<=50000,2000,7000)),F58="全年一次性奖金收入",VLOOKUP(AP58/12,{0,0;3000,210;12000,1410;25000,2660;35000,4410;55000,7160;80000,15160},2,1),F58="解除劳动合同一次性补偿金",VLOOKUP(AP58,{0,0;36000,2520;144000,16920;300000,31920;420000,52920;660000,85920;960000,181920},2,1))} -> #N/A | AS58: =AP58*AQ58-AR58 -> #N/A | AT58: 0 | AU58: =BI58+BJ58 -> 2.04 | AV58: =IF(AS58-AT58-AU58>0,AS58-AT58-AU58,0) -> #N/A | AX58: =IFERROR(IF(F58="正常工资薪金",VLOOKUP(D58&"*",个税上月累计情况!E:AL,26,0),0),0) -> 32187.98 | AY58: =IFERROR(IF(F58="正常工资薪金",VLOOKUP(D58&"*",个税上月累计情况!E:AL,27,0),0),0) -> 20000 | AZ58: =IFERROR(IF(F58="正常工资薪金",VLOOKUP(D58&"*",个税上月累计情况!E:AL,28,0),0),0) -> 4620.04 | BA58: =IFERROR(IF(F58="正常工资薪金",VLOOKUP(D58&"*",个税上月累计情况!E:AL,29,0),0),0) -> 0 | BB58: =IFERROR(IF(F58="正常工资薪金",VLOOKUP(D58&"*",个税上月累计情况!E:AL,30,0),0),0) -> 0 | BC58: =IFERROR(IF(F58="正常工资薪金",VLOOKUP(D58&"*",个税上月累计情况!E:AL,31,0),0),0) -> 0 | BD58: =IFERROR(IF(F58="正常工资薪金",VLOOKUP(D58&"*",个税上月累计情况!E:AL,32,0),0),0) -> 7500 | BE58: =IFERROR(IF(F58="正常工资薪金",VLOOKUP(D58&"*",个税上月累计情况!E:AL,33,0),0),0) -> 0 | BF58: =IFERROR(IF(F58="正常工资薪金",VLOOKUP(D58&"*",个税上月累计情况!E:AL,34,0),0),0) -> 0 | BG58: =IFERROR(IF(F58="正常工资薪金",VLOOKUP(D58&"*",个税上月累计情况!E:AN,35,0),0),0) -> 0 | BH58: =IFERROR(IF(F58="正常工资薪金",VLOOKUP(D58&"*",个税上月累计情况!E:AN,36,0),0),0) -> 0 | BI58: =IFERROR(IF(F58="正常工资薪金",VLOOKUP(D58&"*",个税上月累计情况!D:AW,46,0),0),0) -> 0 | BJ58: =IFERROR(IF(F58="正常工资薪金",VLOOKUP(D58&"*",个税上月累计情况!D:AX,47,0),0),0) -> 2.04 | BK58: =VLOOKUP(B58,花名册!C:N,12,0) -> #N/A
B59: 张潘丽 | C59: 居民身份证 | D59: 330726199505050329 | E59: 否 | F59: 正常工资薪金 | G59: {=_xlfn.IFS(F59="正常工资薪金",VLOOKUP(D59&"*",工资表明细!D:BL,61,0),F59="一般劳务报酬所得",VLOOKUP(D59&"*",工资表明细!D:BJ,59,0),F59="全年一次性奖金收入",VLOOKUP(D59&"*",工资表明细!D:BI,58,0),F59="解除劳动合同一次性补偿金",VLOOKUP(D59&"*",工资表明细!D:BH,57,0))} -> #N/A | H59: =IF(F59="一般劳务报酬所得",800,0) -> 0 | I59: 0 | J59: =IF(F59="正常工资薪金",5000,0) -> 5000 | K59: =IF(F59="正常工资薪金",VLOOKUP(D59&"*",工资表明细!D:AP,39,0),0) -> #N/A | L59: =IF(F59="正常工资薪金",VLOOKUP(D59&"*",工资表明细!D:AQ,40,0),0) -> #N/A | M59: =IF(F59="正常工资薪金",VLOOKUP(D59&"*",工资表明细!D:AR,41,0),0) -> #N/A | N59: =IF(F59="正常工资薪金",VLOOKUP(D59&"*",工资表明细!D:AT,43,0),0) -> #N/A | O59: 54 | P59: 54 | Q59: 54 | R59: 54 | S59: 54 | T59: 54 | U59: 54 | V59: 54 | W59: - | X59: 54 | Y59: - | Z59: - | AA59: - | AB59: 54 | AC59: =IF(F59="正常工资薪金",G59+AX59,"-") -> #N/A | AD59: =IF(F59="正常工资薪金",J59+AY59,"-") -> 25000 | AE59: =IF(F59="正常工资薪金",K59+L59+M59+N59+AZ59,"-") -> #N/A | AF59: =IFERROR(IF($F$5="正常工资薪金",IF(YEAR(BK59)<YEAR($BK$1),BA59/($D$1-1)*$D$1,BA59/DATEDIF(BK59,$BK$1,"M")*DATEDIF(BK59,$BK$1,"M")),"-"),0) -> 0 | AG59: =IFERROR(IF($F$5="正常工资薪金",IF(YEAR(BK59)<YEAR($BK$1),BB59/($D$1-1)*$D$1,BB59/DATEDIF(BK59,$BK$1,"M")*DATEDIF(BK59,$BK$1,"M")),"-"),0) -> 0 | AH59: =IFERROR(IF($F$5="正常工资薪金",IF(YEAR(BK59)<YEAR($BK$1),BC59/($D$1-1)*$D$1,BC59/(MONTH($BK$1)-MONTH(BK59))*(MONTH($BK$1)-MONTH(BK59)+1)),"-"),0) -> 0 | AI59: =IFERROR(IF($F$5="正常工资薪金",IF(YEAR(BK59)<YEAR($BK$1),BD59/($D$1-1)*$D$1,BD59/(MONTH($BK$1)-MONTH(BK59))*(MONTH($BK$1)-MONTH(BK59)+1)),"-"),0) -> 0 | AJ59: =IFERROR(IF($F$5="正常工资薪金",IF(YEAR(BK59)<YEAR($BK$1),BE59/($D$1-1)*$D$1,BE59/(MONTH($BK$1)-MONTH(BK59))*(MONTH($BK$1)-MONTH(BK59)+1)),"-"),0) -> 0 | AK59: 10000 | AL59: 0 | AM59: 0 | AN59: 100% | AO59: 0 | AP59: =IF(IF(F59="正常工资薪金",AC59-AD59-AE59-AF59-AG59-AH59-AI59-AJ59-AK59-AL59-AM59,G59-H59-I59)<0,0,IF(F59="正常工资薪金",AC59-AD59-AE59-AF59-AG59-AH59-AI59-AJ59-AK59-AL59-AM59,G59-H59-I59)) -> #N/A | AQ59: {=_xlfn.IFS(F59="正常工资薪金",VLOOKUP(AP59,{0,0.03;36000,0.1;144000,0.2;300000,0.25;420000,0.3;660000,0.35;960000,0.45},2,1),F59="一般劳务报酬所得",IF(AP59<=20000,0.2,IF(AP59<=50000,0.3,0.4)),F59="全年一次性奖金收入",VLOOKUP(AP59/12,{0,0.03;3000,0.1;12000,0.2;25000,0.25;35000,0.3;55000,0.35;80000,0.45},2,1),F59="解除劳动合同一次性补偿金",VLOOKUP(AP59,{0,0.03;36000,0.1;144000,0.2;300000,0.25;420000,0.3;660000,0.35;960000,0.45},2,1))} -> #N/A | AR59: {=_xlfn.IFS(F59="正常工资薪金",VLOOKUP(AP59,{0,0;36000,2520;144000,16920;300000,31920;420000,52920;660000,85920;960000,181920},2,1),F59="一般劳务报酬所得",IF(AP59<=20000,0,IF(AS<=50000,2000,7000)),F59="全年一次性奖金收入",VLOOKUP(AP59/12,{0,0;3000,210;12000,1410;25000,2660;35000,4410;55000,7160;80000,15160},2,1),F59="解除劳动合同一次性补偿金",VLOOKUP(AP59,{0,0;36000,2520;144000,16920;300000,31920;420000,52920;660000,85920;960000,181920},2,1))} -> #N/A | AS59: =AP59*AQ59-AR59 -> #N/A | AT59: 0 | AU59: =BI59+BJ59 -> 13.64 | AV59: =IF(AS59-AT59-AU59>0,AS59-AT59-AU59,0) -> #N/A | AX59: =IFERROR(IF(F59="正常工资薪金",VLOOKUP(D59&"*",个税上月累计情况!E:AL,26,0),0),0) -> 41454.55 | AY59: =IFERROR(IF(F59="正常工资薪金",VLOOKUP(D59&"*",个税上月累计情况!E:AL,27,0),0),0) -> 20000 | AZ59: =IFERROR(IF(F59="正常工资薪金",VLOOKUP(D59&"*",个税上月累计情况!E:AL,28,0),0),0) -> 4065.03 | BA59: =IFERROR(IF(F59="正常工资薪金",VLOOKUP(D59&"*",个税上月累计情况!E:AL,29,0),0),0) -> 0 | BB59: =IFERROR(IF(F59="正常工资薪金",VLOOKUP(D59&"*",个税上月累计情况!E:AL,30,0),0),0) -> 0 | BC59: =IFERROR(IF(F59="正常工资薪金",VLOOKUP(D59&"*",个税上月累计情况!E:AL,31,0),0),0) -> 0 | BD59: =IFERROR(IF(F59="正常工资薪金",VLOOKUP(D59&"*",个税上月累计情况!E:AL,32,0),0),0) -> 7500 | BE59: =IFERROR(IF(F59="正常工资薪金",VLOOKUP(D59&"*",个税上月累计情况!E:AL,33,0),0),0) -> 0 | BF59: =IFERROR(IF(F59="正常工资薪金",VLOOKUP(D59&"*",个税上月累计情况!E:AL,34,0),0),0) -> 10000 | BG59: =IFERROR(IF(F59="正常工资薪金",VLOOKUP(D59&"*",个税上月累计情况!E:AN,35,0),0),0) -> 0 | BH59: =IFERROR(IF(F59="正常工资薪金",VLOOKUP(D59&"*",个税上月累计情况!E:AN,36,0),0),0) -> 0 | BI59: =IFERROR(IF(F59="正常工资薪金",VLOOKUP(D59&"*",个税上月累计情况!D:AW,46,0),0),0) -> 13.64 | BJ59: =IFERROR(IF(F59="正常工资薪金",VLOOKUP(D59&"*",个税上月累计情况!D:AX,47,0),0),0) -> 0 | BK59: =VLOOKUP(B59,花名册!C:N,12,0) -> #N/A
B60: 段佳攀 | C60: 居民身份证 | D60: 421223199511130022 | E60: 否 | F60: 正常工资薪金 | G60: {=_xlfn.IFS(F60="正常工资薪金",VLOOKUP(D60&"*",工资表明细!D:BL,61,0),F60="一般劳务报酬所得",VLOOKUP(D60&"*",工资表明细!D:BJ,59,0),F60="全年一次性奖金收入",VLOOKUP(D60&"*",工资表明细!D:BI,58,0),F60="解除劳动合同一次性补偿金",VLOOKUP(D60&"*",工资表明细!D:BH,57,0))} -> #N/A | H60: =IF(F60="一般劳务报酬所得",800,0) -> 0 | I60: 0 | J60: =IF(F60="正常工资薪金",5000,0) -> 5000 | K60: =IF(F60="正常工资薪金",VLOOKUP(D60&"*",工资表明细!D:AP,39,0),0) -> #N/A | L60: =IF(F60="正常工资薪金",VLOOKUP(D60&"*",工资表明细!D:AQ,40,0),0) -> #N/A | M60: =IF(F60="正常工资薪金",VLOOKUP(D60&"*",工资表明细!D:AR,41,0),0) -> #N/A | N60: =IF(F60="正常工资薪金",VLOOKUP(D60&"*",工资表明细!D:AT,43,0),0) -> #N/A | O60: 55 | P60: 55 | Q60: 55 | R60: 55 | S60: 55 | T60: 55 | U60: 55 | V60: 55 | W60: - | X60: 55 | Y60: - | Z60: - | AA60: - | AB60: 55 | AC60: =IF(F60="正常工资薪金",G60+AX60,"-") -> #N/A | AD60: =IF(F60="正常工资薪金",J60+AY60,"-") -> 25000 | AE60: =IF(F60="正常工资薪金",K60+L60+M60+N60+AZ60,"-") -> #N/A | AF60: =IFERROR(IF($F$5="正常工资薪金",IF(YEAR(BK60)<YEAR($BK$1),BA60/($D$1-1)*$D$1,BA60/DATEDIF(BK60,$BK$1,"M")*DATEDIF(BK60,$BK$1,"M")),"-"),0) -> 0 | AG60: =IFERROR(IF($F$5="正常工资薪金",IF(YEAR(BK60)<YEAR($BK$1),BB60/($D$1-1)*$D$1,BB60/DATEDIF(BK60,$BK$1,"M")*DATEDIF(BK60,$BK$1,"M")),"-"),0) -> 0 | AH60: =IFERROR(IF($F$5="正常工资薪金",IF(YEAR(BK60)<YEAR($BK$1),BC60/($D$1-1)*$D$1,BC60/(MONTH($BK$1)-MONTH(BK60))*(MONTH($BK$1)-MONTH(BK60)+1)),"-"),0) -> 0 | AI60: =IFERROR(IF($F$5="正常工资薪金",IF(YEAR(BK60)<YEAR($BK$1),BD60/($D$1-1)*$D$1,BD60/(MONTH($BK$1)-MONTH(BK60))*(MONTH($BK$1)-MONTH(BK60)+1)),"-"),0) -> 0 | AJ60: =IFERROR(IF($F$5="正常工资薪金",IF(YEAR(BK60)<YEAR($BK$1),BE60/($D$1-1)*$D$1,BE60/(MONTH($BK$1)-MONTH(BK60))*(MONTH($BK$1)-MONTH(BK60)+1)),"-"),0) -> 0 | AK60: =IFERROR(IF($F$5="正常工资薪金",IF(YEAR(BK60)<YEAR($BK$1),BF60/($D$1-1)*$D$1,BF60/(MONTH($BK$1)-MONTH(BK60))*(MONTH($BK$1)-MONTH(BK60)+1)),"-"),0) -> 0 | AL60: 0 | AM60: 0 | AN60: 100% | AO60: 0 | AP60: =IF(IF(F60="正常工资薪金",AC60-AD60-AE60-AF60-AG60-AH60-AI60-AJ60-AK60-AL60-AM60,G60-H60-I60)<0,0,IF(F60="正常工资薪金",AC60-AD60-AE60-AF60-AG60-AH60-AI60-AJ60-AK60-AL60-AM60,G60-H60-I60)) -> #N/A | AQ60: {=_xlfn.IFS(F60="正常工资薪金",VLOOKUP(AP60,{0,0.03;36000,0.1;144000,0.2;300000,0.25;420000,0.3;660000,0.35;960000,0.45},2,1),F60="一般劳务报酬所得",IF(AP60<=20000,0.2,IF(AP60<=50000,0.3,0.4)),F60="全年一次性奖金收入",VLOOKUP(AP60/12,{0,0.03;3000,0.1;12000,0.2;25000,0.25;35000,0.3;55000,0.35;80000,0.45},2,1),F60="解除劳动合同一次性补偿金",VLOOKUP(AP60,{0,0.03;36000,0.1;144000,0.2;300000,0.25;420000,0.3;660000,0.35;960000,0.45},2,1))} -> #N/A | AR60: {=_xlfn.IFS(F60="正常工资薪金",VLOOKUP(AP60,{0,0;36000,2520;144000,16920;300000,31920;420000,52920;660000,85920;960000,181920},2,1),F60="一般劳务报酬所得",IF(AP60<=20000,0,IF(AS<=50000,2000,7000)),F60="全年一次性奖金收入",VLOOKUP(AP60/12,{0,0;3000,210;12000,1410;25000,2660;35000,4410;55000,7160;80000,15160},2,1),F60="解除劳动合同一次性补偿金",VLOOKUP(AP60,{0,0;36000,2520;144000,16920;300000,31920;420000,52920;660000,85920;960000,181920},2,1))} -> #N/A | AS60: =AP60*AQ60-AR60 -> #N/A | AT60: 0 | AU60: =BI60+BJ60 -> 0 | AV60: =IF(AS60-AT60-AU60>0,AS60-AT60-AU60,0) -> #N/A | AX60: =IFERROR(IF(F60="正常工资薪金",VLOOKUP(D60&"*",个税上月累计情况!E:AL,26,0),0),0) -> 21236.36 | AY60: =IFERROR(IF(F60="正常工资薪金",VLOOKUP(D60&"*",个税上月累计情况!E:AL,27,0),0),0) -> 20000 | AZ60: =IFERROR(IF(F60="正常工资薪金",VLOOKUP(D60&"*",个税上月累计情况!E:AL,28,0),0),0) -> 2530.59 | BA60: =IFERROR(IF(F60="正常工资薪金",VLOOKUP(D60&"*",个税上月累计情况!E:AL,29,0),0),0) -> 0 | BB60: =IFERROR(IF(F60="正常工资薪金",VLOOKUP(D60&"*",个税上月累计情况!E:AL,30,0),0),0) -> 0 | BC60: =IFERROR(IF(F60="正常工资薪金",VLOOKUP(D60&"*",个税上月累计情况!E:AL,31,0),0),0) -> 0 | BD60: =IFERROR(IF(F60="正常工资薪金",VLOOKUP(D60&"*",个税上月累计情况!E:AL,32,0),0),0) -> 0 | BE60: =IFERROR(IF(F60="正常工资薪金",VLOOKUP(D60&"*",个税上月累计情况!E:AL,33,0),0),0) -> 0 | BF60: =IFERROR(IF(F60="正常工资薪金",VLOOKUP(D60&"*",个税上月累计情况!E:AL,34,0),0),0) -> 0 | BG60: =IFERROR(IF(F60="正常工资薪金",VLOOKUP(D60&"*",个税上月累计情况!E:AN,35,0),0),0) -> 0 | BH60: =IFERROR(IF(F60="正常工资薪金",VLOOKUP(D60&"*",个税上月累计情况!E:AN,36,0),0),0) -> 0 | BI60: =IFERROR(IF(F60="正常工资薪金",VLOOKUP(D60&"*",个税上月累计情况!D:AW,46,0),0),0) -> 0 | BJ60: =IFERROR(IF(F60="正常工资薪金",VLOOKUP(D60&"*",个税上月累计情况!D:AX,47,0),0),0) -> 0 | BK60: =VLOOKUP(B60,花名册!C:N,12,0) -> #N/A
B61: 薛冬悦 | C61: 居民身份证 | D61: 130302199101310411 | E61: 否 | F61: 正常工资薪金 | G61: {=_xlfn.IFS(F61="正常工资薪金",VLOOKUP(D61&"*",工资表明细!D:BL,61,0),F61="一般劳务报酬所得",VLOOKUP(D61&"*",工资表明细!D:BJ,59,0),F61="全年一次性奖金收入",VLOOKUP(D61&"*",工资表明细!D:BI,58,0),F61="解除劳动合同一次性补偿金",VLOOKUP(D61&"*",工资表明细!D:BH,57,0))} -> #N/A | H61: =IF(F61="一般劳务报酬所得",800,0) -> 0 | I61: 0 | J61: =IF(F61="正常工资薪金",5000,0) -> 5000 | K61: =IF(F61="正常工资薪金",VLOOKUP(D61&"*",工资表明细!D:AP,39,0),0) -> #N/A | L61: =IF(F61="正常工资薪金",VLOOKUP(D61&"*",工资表明细!D:AQ,40,0),0) -> #N/A | M61: =IF(F61="正常工资薪金",VLOOKUP(D61&"*",工资表明细!D:AR,41,0),0) -> #N/A | N61: =IF(F61="正常工资薪金",VLOOKUP(D61&"*",工资表明细!D:AT,43,0),0) -> #N/A | O61: 56 | P61: 56 | Q61: 56 | R61: 56 | S61: 56 | T61: 56 | U61: 56 | V61: 56 | W61: - | X61: 56 | Y61: - | Z61: - | AA61: - | AB61: 56 | AC61: =IF(F61="正常工资薪金",G61+AX61,"-") -> #N/A | AD61: =IF(F61="正常工资薪金",J61+AY61,"-") -> 25000 | AE61: =IF(F61="正常工资薪金",K61+L61+M61+N61+AZ61,"-") -> #N/A | AF61: =IFERROR(IF($F$5="正常工资薪金",IF(YEAR(BK61)<YEAR($BK$1),BA61/($D$1-1)*$D$1,BA61/DATEDIF(BK61,$BK$1,"M")*DATEDIF(BK61,$BK$1,"M")),"-"),0) -> 0 | AG61: =IFERROR(IF($F$5="正常工资薪金",IF(YEAR(BK61)<YEAR($BK$1),BB61/($D$1-1)*$D$1,BB61/DATEDIF(BK61,$BK$1,"M")*DATEDIF(BK61,$BK$1,"M")),"-"),0) -> 0 | AH61: =IFERROR(IF($F$5="正常工资薪金",IF(YEAR(BK61)<YEAR($BK$1),BC61/($D$1-1)*$D$1,BC61/(MONTH($BK$1)-MONTH(BK61))*(MONTH($BK$1)-MONTH(BK61)+1)),"-"),0) -> 0 | AI61: =IFERROR(IF($F$5="正常工资薪金",IF(YEAR(BK61)<YEAR($BK$1),BD61/($D$1-1)*$D$1,BD61/(MONTH($BK$1)-MONTH(BK61))*(MONTH($BK$1)-MONTH(BK61)+1)),"-"),0) -> 0 | AJ61: =IFERROR(IF($F$5="正常工资薪金",IF(YEAR(BK61)<YEAR($BK$1),BE61/($D$1-1)*$D$1,BE61/(MONTH($BK$1)-MONTH(BK61))*(MONTH($BK$1)-MONTH(BK61)+1)),"-"),0) -> 0 | AK61: =IFERROR(IF($F$5="正常工资薪金",IF(YEAR(BK61)<YEAR($BK$1),BF61/($D$1-1)*$D$1,BF61/(MONTH($BK$1)-MONTH(BK61))*(MONTH($BK$1)-MONTH(BK61)+1)),"-"),0) -> 0 | AL61: 0 | AM61: 0 | AN61: 100% | AO61: 0 | AP61: =IF(IF(F61="正常工资薪金",AC61-AD61-AE61-AF61-AG61-AH61-AI61-AJ61-AK61-AL61-AM61,G61-H61-I61)<0,0,IF(F61="正常工资薪金",AC61-AD61-AE61-AF61-AG61-AH61-AI61-AJ61-AK61-AL61-AM61,G61-H61-I61)) -> #N/A | AQ61: {=_xlfn.IFS(F61="正常工资薪金",VLOOKUP(AP61,{0,0.03;36000,0.1;144000,0.2;300000,0.25;420000,0.3;660000,0.35;960000,0.45},2,1),F61="一般劳务报酬所得",IF(AP61<=20000,0.2,IF(AP61<=50000,0.3,0.4)),F61="全年一次性奖金收入",VLOOKUP(AP61/12,{0,0.03;3000,0.1;12000,0.2;25000,0.25;35000,0.3;55000,0.35;80000,0.45},2,1),F61="解除劳动合同一次性补偿金",VLOOKUP(AP61,{0,0.03;36000,0.1;144000,0.2;300000,0.25;420000,0.3;660000,0.35;960000,0.45},2,1))} -> #N/A | AR61: {=_xlfn.IFS(F61="正常工资薪金",VLOOKUP(AP61,{0,0;36000,2520;144000,16920;300000,31920;420000,52920;660000,85920;960000,181920},2,1),F61="一般劳务报酬所得",IF(AP61<=20000,0,IF(AS<=50000,2000,7000)),F61="全年一次性奖金收入",VLOOKUP(AP61/12,{0,0;3000,210;12000,1410;25000,2660;35000,4410;55000,7160;80000,15160},2,1),F61="解除劳动合同一次性补偿金",VLOOKUP(AP61,{0,0;36000,2520;144000,16920;300000,31920;420000,52920;660000,85920;960000,181920},2,1))} -> #N/A | AS61: =AP61*AQ61-AR61 -> #N/A | AT61: 0 | AU61: =BI61+BJ61 -> 1209.31 | AV61: =IF(AS61-AT61-AU61>0,AS61-AT61-AU61,0) -> #N/A | AX61: =IFERROR(IF(F61="正常工资薪金",VLOOKUP(D61&"*",个税上月累计情况!E:AL,26,0),0),0) -> 62378.08 | AY61: =IFERROR(IF(F61="正常工资薪金",VLOOKUP(D61&"*",个税上月累计情况!E:AL,27,0),0),0) -> 20000 | AZ61: =IFERROR(IF(F61="正常工资薪金",VLOOKUP(D61&"*",个税上月累计情况!E:AL,28,0),0),0) -> 5085.03 | BA61: =IFERROR(IF(F61="正常工资薪金",VLOOKUP(D61&"*",个税上月累计情况!E:AL,29,0),0),0) -> 0 | BB61: =IFERROR(IF(F61="正常工资薪金",VLOOKUP(D61&"*",个税上月累计情况!E:AL,30,0),0),0) -> 0 | BC61: =IFERROR(IF(F61="正常工资薪金",VLOOKUP(D61&"*",个税上月累计情况!E:AL,31,0),0),0) -> 0 | BD61: =IFERROR(IF(F61="正常工资薪金",VLOOKUP(D61&"*",个税上月累计情况!E:AL,32,0),0),0) -> 0 | BE61: =IFERROR(IF(F61="正常工资薪金",VLOOKUP(D61&"*",个税上月累计情况!E:AL,33,0),0),0) -> 0 | BF61: =IFERROR(IF(F61="正常工资薪金",VLOOKUP(D61&"*",个税上月累计情况!E:AL,34,0),0),0) -> 0 | BG61: =IFERROR(IF(F61="正常工资薪金",VLOOKUP(D61&"*",个税上月累计情况!E:AN,35,0),0),0) -> 0 | BH61: =IFERROR(IF(F61="正常工资薪金",VLOOKUP(D61&"*",个税上月累计情况!E:AN,36,0),0),0) -> 0 | BI61: =IFERROR(IF(F61="正常工资薪金",VLOOKUP(D61&"*",个税上月累计情况!D:AW,46,0),0),0) -> 755.7 | BJ61: =IFERROR(IF(F61="正常工资薪金",VLOOKUP(D61&"*",个税上月累计情况!D:AX,47,0),0),0) -> 453.61 | BK61: =VLOOKUP(B61,花名册!C:N,12,0) -> #N/A
B62: 卢士欣 | C62: 居民身份证 | D62: 130682199911027085 | E62: 否 | F62: 正常工资薪金 | G62: {=_xlfn.IFS(F62="正常工资薪金",VLOOKUP(D62&"*",工资表明细!D:BL,61,0),F62="一般劳务报酬所得",VLOOKUP(D62&"*",工资表明细!D:BJ,59,0),F62="全年一次性奖金收入",VLOOKUP(D62&"*",工资表明细!D:BI,58,0),F62="解除劳动合同一次性补偿金",VLOOKUP(D62&"*",工资表明细!D:BH,57,0))} -> #N/A | H62: =IF(F62="一般劳务报酬所得",800,0) -> 0 | I62: 0 | J62: =IF(F62="正常工资薪金",5000,0) -> 5000 | K62: =IF(F62="正常工资薪金",VLOOKUP(D62&"*",工资表明细!D:AP,39,0),0) -> #N/A | L62: =IF(F62="正常工资薪金",VLOOKUP(D62&"*",工资表明细!D:AQ,40,0),0) -> #N/A | M62: =IF(F62="正常工资薪金",VLOOKUP(D62&"*",工资表明细!D:AR,41,0),0) -> #N/A | N62: =IF(F62="正常工资薪金",VLOOKUP(D62&"*",工资表明细!D:AT,43,0),0) -> #N/A | O62: 57 | P62: 57 | Q62: 57 | R62: 57 | S62: 57 | T62: 57 | U62: 57 | V62: 57 | W62: - | X62: 57 | Y62: - | Z62: - | AA62: - | AB62: 57 | AC62: =IF(F62="正常工资薪金",G62+AX62,"-") -> #N/A | AD62: =IF(F62="正常工资薪金",J62+AY62,"-") -> 25000 | AE62: =IF(F62="正常工资薪金",K62+L62+M62+N62+AZ62,"-") -> #N/A | AF62: =IFERROR(IF($F$5="正常工资薪金",IF(YEAR(BK62)<YEAR($BK$1),BA62/($D$1-1)*$D$1,BA62/DATEDIF(BK62,$BK$1,"M")*DATEDIF(BK62,$BK$1,"M")),"-"),0) -> 0 | AG62: =IFERROR(IF($F$5="正常工资薪金",IF(YEAR(BK62)<YEAR($BK$1),BB62/($D$1-1)*$D$1,BB62/DATEDIF(BK62,$BK$1,"M")*DATEDIF(BK62,$BK$1,"M")),"-"),0) -> 0 | AH62: =IFERROR(IF($F$5="正常工资薪金",IF(YEAR(BK62)<YEAR($BK$1),BC62/($D$1-1)*$D$1,BC62/(MONTH($BK$1)-MONTH(BK62))*(MONTH($BK$1)-MONTH(BK62)+1)),"-"),0) -> 0 | AI62: =IFERROR(IF($F$5="正常工资薪金",IF(YEAR(BK62)<YEAR($BK$1),BD62/($D$1-1)*$D$1,BD62/(MONTH($BK$1)-MONTH(BK62))*(MONTH($BK$1)-MONTH(BK62)+1)),"-"),0) -> 0 | AJ62: =IFERROR(IF($F$5="正常工资薪金",IF(YEAR(BK62)<YEAR($BK$1),BE62/($D$1-1)*$D$1,BE62/(MONTH($BK$1)-MONTH(BK62))*(MONTH($BK$1)-MONTH(BK62)+1)),"-"),0) -> 0 | AK62: =IFERROR(IF($F$5="正常工资薪金",IF(YEAR(BK62)<YEAR($BK$1),BF62/($D$1-1)*$D$1,BF62/(MONTH($BK$1)-MONTH(BK62))*(MONTH($BK$1)-MONTH(BK62)+1)),"-"),0) -> 0 | AL62: 0 | AM62: 0 | AN62: 100% | AO62: 0 | AP62: =IF(IF(F62="正常工资薪金",AC62-AD62-AE62-AF62-AG62-AH62-AI62-AJ62-AK62-AL62-AM62,G62-H62-I62)<0,0,IF(F62="正常工资薪金",AC62-AD62-AE62-AF62-AG62-AH62-AI62-AJ62-AK62-AL62-AM62,G62-H62-I62)) -> #N/A | AQ62: {=_xlfn.IFS(F62="正常工资薪金",VLOOKUP(AP62,{0,0.03;36000,0.1;144000,0.2;300000,0.25;420000,0.3;660000,0.35;960000,0.45},2,1),F62="一般劳务报酬所得",IF(AP62<=20000,0.2,IF(AP62<=50000,0.3,0.4)),F62="全年一次性奖金收入",VLOOKUP(AP62/12,{0,0.03;3000,0.1;12000,0.2;25000,0.25;35000,0.3;55000,0.35;80000,0.45},2,1),F62="解除劳动合同一次性补偿金",VLOOKUP(AP62,{0,0.03;36000,0.1;144000,0.2;300000,0.25;420000,0.3;660000,0.35;960000,0.45},2,1))} -> #N/A | AR62: {=_xlfn.IFS(F62="正常工资薪金",VLOOKUP(AP62,{0,0;36000,2520;144000,16920;300000,31920;420000,52920;660000,85920;960000,181920},2,1),F62="一般劳务报酬所得",IF(AP62<=20000,0,IF(AS<=50000,2000,7000)),F62="全年一次性奖金收入",VLOOKUP(AP62/12,{0,0;3000,210;12000,1410;25000,2660;35000,4410;55000,7160;80000,15160},2,1),F62="解除劳动合同一次性补偿金",VLOOKUP(AP62,{0,0;36000,2520;144000,16920;300000,31920;420000,52920;660000,85920;960000,181920},2,1))} -> #N/A | AS62: =AP62*AQ62-AR62 -> #N/A | AT62: 0 | AU62: =BI62+BJ62 -> 257.64 | AV62: =IF(AS62-AT62-AU62>0,AS62-AT62-AU62,0) -> #N/A | AX62: =IFERROR(IF(F62="正常工资薪金",VLOOKUP(D62&"*",个税上月累计情况!E:AL,26,0),0),0) -> 32352.88 | AY62: =IFERROR(IF(F62="正常工资薪金",VLOOKUP(D62&"*",个税上月累计情况!E:AL,27,0),0),0) -> 20000 | AZ62: =IFERROR(IF(F62="正常工资薪金",VLOOKUP(D62&"*",个税上月累计情况!E:AL,28,0),0),0) -> 3765.03 | BA62: =IFERROR(IF(F62="正常工资薪金",VLOOKUP(D62&"*",个税上月累计情况!E:AL,29,0),0),0) -> 0 | BB62: =IFERROR(IF(F62="正常工资薪金",VLOOKUP(D62&"*",个税上月累计情况!E:AL,30,0),0),0) -> 0 | BC62: =IFERROR(IF(F62="正常工资薪金",VLOOKUP(D62&"*",个税上月累计情况!E:AL,31,0),0),0) -> 0 | BD62: =IFERROR(IF(F62="正常工资薪金",VLOOKUP(D62&"*",个税上月累计情况!E:AL,32,0),0),0) -> 0 | BE62: =IFERROR(IF(F62="正常工资薪金",VLOOKUP(D62&"*",个税上月累计情况!E:AL,33,0),0),0) -> 0 | BF62: =IFERROR(IF(F62="正常工资薪金",VLOOKUP(D62&"*",个税上月累计情况!E:AL,34,0),0),0) -> 0 | BG62: =IFERROR(IF(F62="正常工资薪金",VLOOKUP(D62&"*",个税上月累计情况!E:AN,35,0),0),0) -> 0 | BH62: =IFERROR(IF(F62="正常工资薪金",VLOOKUP(D62&"*",个税上月累计情况!E:AN,36,0),0),0) -> 0 | BI62: =IFERROR(IF(F62="正常工资薪金",VLOOKUP(D62&"*",个税上月累计情况!D:AW,46,0),0),0) -> 153.6 | BJ62: =IFERROR(IF(F62="正常工资薪金",VLOOKUP(D62&"*",个税上月累计情况!D:AX,47,0),0),0) -> 104.04 | BK62: =VLOOKUP(B62,花名册!C:N,12,0) -> #N/A
B63: 于宏斌 | C63: 居民身份证 | D63: 142226200205147430 | E63: 否 | F63: 正常工资薪金 | G63: {=_xlfn.IFS(F63="正常工资薪金",VLOOKUP(D63&"*",工资表明细!D:BL,61,0),F63="一般劳务报酬所得",VLOOKUP(D63&"*",工资表明细!D:BJ,59,0),F63="全年一次性奖金收入",VLOOKUP(D63&"*",工资表明细!D:BI,58,0),F63="解除劳动合同一次性补偿金",VLOOKUP(D63&"*",工资表明细!D:BH,57,0))} -> #N/A | H63: =IF(F63="一般劳务报酬所得",800,0) -> 0 | I63: 0 | J63: =IF(F63="正常工资薪金",5000,0) -> 5000 | K63: =IF(F63="正常工资薪金",VLOOKUP(D63&"*",工资表明细!D:AP,39,0),0) -> #N/A | L63: =IF(F63="正常工资薪金",VLOOKUP(D63&"*",工资表明细!D:AQ,40,0),0) -> #N/A | M63: =IF(F63="正常工资薪金",VLOOKUP(D63&"*",工资表明细!D:AR,41,0),0) -> #N/A | N63: =IF(F63="正常工资薪金",VLOOKUP(D63&"*",工资表明细!D:AT,43,0),0) -> #N/A | O63: 58 | P63: 58 | Q63: 58 | R63: 58 | S63: 58 | T63: 58 | U63: 58 | V63: 58 | W63: - | X63: 58 | Y63: - | Z63: - | AA63: - | AB63: 58 | AC63: =IF(F63="正常工资薪金",G63+AX63,"-") -> #N/A | AD63: =IF(F63="正常工资薪金",J63+AY63,"-") -> 25000 | AE63: =IF(F63="正常工资薪金",K63+L63+M63+N63+AZ63,"-") -> #N/A | AF63: =IFERROR(IF($F$5="正常工资薪金",IF(YEAR(BK63)<YEAR($BK$1),BA63/($D$1-1)*$D$1,BA63/DATEDIF(BK63,$BK$1,"M")*DATEDIF(BK63,$BK$1,"M")),"-"),0) -> 0 | AG63: =IFERROR(IF($F$5="正常工资薪金",IF(YEAR(BK63)<YEAR($BK$1),BB63/($D$1-1)*$D$1,BB63/DATEDIF(BK63,$BK$1,"M")*DATEDIF(BK63,$BK$1,"M")),"-"),0) -> 0 | AH63: =IFERROR(IF($F$5="正常工资薪金",IF(YEAR(BK63)<YEAR($BK$1),BC63/($D$1-1)*$D$1,BC63/(MONTH($BK$1)-MONTH(BK63))*(MONTH($BK$1)-MONTH(BK63)+1)),"-"),0) -> 0 | AI63: =IFERROR(IF($F$5="正常工资薪金",IF(YEAR(BK63)<YEAR($BK$1),BD63/($D$1-1)*$D$1,BD63/(MONTH($BK$1)-MONTH(BK63))*(MONTH($BK$1)-MONTH(BK63)+1)),"-"),0) -> 0 | AJ63: =IFERROR(IF($F$5="正常工资薪金",IF(YEAR(BK63)<YEAR($BK$1),BE63/($D$1-1)*$D$1,BE63/(MONTH($BK$1)-MONTH(BK63))*(MONTH($BK$1)-MONTH(BK63)+1)),"-"),0) -> 0 | AK63: =IFERROR(IF($F$5="正常工资薪金",IF(YEAR(BK63)<YEAR($BK$1),BF63/($D$1-1)*$D$1,BF63/(MONTH($BK$1)-MONTH(BK63))*(MONTH($BK$1)-MONTH(BK63)+1)),"-"),0) -> 0 | AL63: 0 | AM63: 0 | AN63: 100% | AO63: 0 | AP63: =IF(IF(F63="正常工资薪金",AC63-AD63-AE63-AF63-AG63-AH63-AI63-AJ63-AK63-AL63-AM63,G63-H63-I63)<0,0,IF(F63="正常工资薪金",AC63-AD63-AE63-AF63-AG63-AH63-AI63-AJ63-AK63-AL63-AM63,G63-H63-I63)) -> #N/A | AQ63: {=_xlfn.IFS(F63="正常工资薪金",VLOOKUP(AP63,{0,0.03;36000,0.1;144000,0.2;300000,0.25;420000,0.3;660000,0.35;960000,0.45},2,1),F63="一般劳务报酬所得",IF(AP63<=20000,0.2,IF(AP63<=50000,0.3,0.4)),F63="全年一次性奖金收入",VLOOKUP(AP63/12,{0,0.03;3000,0.1;12000,0.2;25000,0.25;35000,0.3;55000,0.35;80000,0.45},2,1),F63="解除劳动合同一次性补偿金",VLOOKUP(AP63,{0,0.03;36000,0.1;144000,0.2;300000,0.25;420000,0.3;660000,0.35;960000,0.45},2,1))} -> #N/A | AR63: {=_xlfn.IFS(F63="正常工资薪金",VLOOKUP(AP63,{0,0;36000,2520;144000,16920;300000,31920;420000,52920;660000,85920;960000,181920},2,1),F63="一般劳务报酬所得",IF(AP63<=20000,0,IF(AS<=50000,2000,7000)),F63="全年一次性奖金收入",VLOOKUP(AP63/12,{0,0;3000,210;12000,1410;25000,2660;35000,4410;55000,7160;80000,15160},2,1),F63="解除劳动合同一次性补偿金",VLOOKUP(AP63,{0,0;36000,2520;144000,16920;300000,31920;420000,52920;660000,85920;960000,181920},2,1))} -> #N/A | AS63: =AP63*AQ63-AR63 -> #N/A | AT63: 0 | AU63: =BI63+BJ63 -> 439.87 | AV63: =IF(AS63-AT63-AU63>0,AS63-AT63-AU63,0) -> #N/A | AX63: =IFERROR(IF(F63="正常工资薪金",VLOOKUP(D63&"*",个税上月累计情况!E:AL,26,0),0),0) -> 38727.27 | AY63: =IFERROR(IF(F63="正常工资薪金",VLOOKUP(D63&"*",个税上月累计情况!E:AL,27,0),0),0) -> 20000 | AZ63: =IFERROR(IF(F63="正常工资薪金",VLOOKUP(D63&"*",个税上月累计情况!E:AL,28,0),0),0) -> 4065.03 | BA63: =IFERROR(IF(F63="正常工资薪金",VLOOKUP(D63&"*",个税上月累计情况!E:AL,29,0),0),0) -> 0 | BB63: =IFERROR(IF(F63="正常工资薪金",VLOOKUP(D63&"*",个税上月累计情况!E:AL,30,0),0),0) -> 0 | BC63: =IFERROR(IF(F63="正常工资薪金",VLOOKUP(D63&"*",个税上月累计情况!E:AL,31,0),0),0) -> 0 | BD63: =IFERROR(IF(F63="正常工资薪金",VLOOKUP(D63&"*",个税上月累计情况!E:AL,32,0),0),0) -> 0 | BE63: =IFERROR(IF(F63="正常工资薪金",VLOOKUP(D63&"*",个税上月累计情况!E:AL,33,0),0),0) -> 0 | BF63: =IFERROR(IF(F63="正常工资薪金",VLOOKUP(D63&"*",个税上月累计情况!E:AL,34,0),0),0) -> 0 | BG63: =IFERROR(IF(F63="正常工资薪金",VLOOKUP(D63&"*",个税上月累计情况!E:AN,35,0),0),0) -> 0 | BH63: =IFERROR(IF(F63="正常工资薪金",VLOOKUP(D63&"*",个税上月累计情况!E:AN,36,0),0),0) -> 0 | BI63: =IFERROR(IF(F63="正常工资薪金",VLOOKUP(D63&"*",个税上月累计情况!D:AW,46,0),0),0) -> 270.52 | BJ63: =IFERROR(IF(F63="正常工资薪金",VLOOKUP(D63&"*",个税上月累计情况!D:AX,47,0),0),0) -> 169.35 | BK63: =VLOOKUP(B63,花名册!C:N,12,0) -> #N/A
B64: 周昕 | C64: 居民身份证 | D64: 350504200012191529 | E64: 否 | F64: 正常工资薪金 | G64: {=_xlfn.IFS(F64="正常工资薪金",VLOOKUP(D64&"*",工资表明细!D:BL,61,0),F64="一般劳务报酬所得",VLOOKUP(D64&"*",工资表明细!D:BJ,59,0),F64="全年一次性奖金收入",VLOOKUP(D64&"*",工资表明细!D:BI,58,0),F64="解除劳动合同一次性补偿金",VLOOKUP(D64&"*",工资表明细!D:BH,57,0))} -> #N/A | H64: =IF(F64="一般劳务报酬所得",800,0) -> 0 | I64: 0 | J64: =IF(F64="正常工资薪金",5000,0) -> 5000 | K64: =IF(F64="正常工资薪金",VLOOKUP(D64&"*",工资表明细!D:AP,39,0),0) -> #N/A | L64: =IF(F64="正常工资薪金",VLOOKUP(D64&"*",工资表明细!D:AQ,40,0),0) -> #N/A | M64: =IF(F64="正常工资薪金",VLOOKUP(D64&"*",工资表明细!D:AR,41,0),0) -> #N/A | N64: =IF(F64="正常工资薪金",VLOOKUP(D64&"*",工资表明细!D:AT,43,0),0) -> #N/A | O64: 59 | P64: 59 | Q64: 59 | R64: 59 | S64: 59 | T64: 59 | U64: 59 | V64: 59 | W64: - | X64: 59 | Y64: - | Z64: - | AA64: - | AB64: 59 | AC64: =IF(F64="正常工资薪金",G64+AX64,"-") -> #N/A | AD64: =IF(F64="正常工资薪金",J64+AY64,"-") -> 25000 | AE64: =IF(F64="正常工资薪金",K64+L64+M64+N64+AZ64,"-") -> #N/A | AF64: =IFERROR(IF($F$5="正常工资薪金",IF(YEAR(BK64)<YEAR($BK$1),BA64/($D$1-1)*$D$1,BA64/DATEDIF(BK64,$BK$1,"M")*DATEDIF(BK64,$BK$1,"M")),"-"),0) -> 0 | AG64: =IFERROR(IF($F$5="正常工资薪金",IF(YEAR(BK64)<YEAR($BK$1),BB64/($D$1-1)*$D$1,BB64/DATEDIF(BK64,$BK$1,"M")*DATEDIF(BK64,$BK$1,"M")),"-"),0) -> 0 | AH64: =IFERROR(IF($F$5="正常工资薪金",IF(YEAR(BK64)<YEAR($BK$1),BC64/($D$1-1)*$D$1,BC64/(MONTH($BK$1)-MONTH(BK64))*(MONTH($BK$1)-MONTH(BK64)+1)),"-"),0) -> 0 | AI64: =IFERROR(IF($F$5="正常工资薪金",IF(YEAR(BK64)<YEAR($BK$1),BD64/($D$1-1)*$D$1,BD64/(MONTH($BK$1)-MONTH(BK64))*(MONTH($BK$1)-MONTH(BK64)+1)),"-"),0) -> 0 | AJ64: =IFERROR(IF($F$5="正常工资薪金",IF(YEAR(BK64)<YEAR($BK$1),BE64/($D$1-1)*$D$1,BE64/(MONTH($BK$1)-MONTH(BK64))*(MONTH($BK$1)-MONTH(BK64)+1)),"-"),0) -> 0 | AK64: =IFERROR(IF($F$5="正常工资薪金",IF(YEAR(BK64)<YEAR($BK$1),BF64/($D$1-1)*$D$1,BF64/(MONTH($BK$1)-MONTH(BK64))*(MONTH($BK$1)-MONTH(BK64)+1)),"-"),0) -> 0 | AL64: 0 | AM64: 0 | AN64: 100% | AO64: 0 | AP64: =IF(IF(F64="正常工资薪金",AC64-AD64-AE64-AF64-AG64-AH64-AI64-AJ64-AK64-AL64-AM64,G64-H64-I64)<0,0,IF(F64="正常工资薪金",AC64-AD64-AE64-AF64-AG64-AH64-AI64-AJ64-AK64-AL64-AM64,G64-H64-I64)) -> #N/A | AQ64: {=_xlfn.IFS(F64="正常工资薪金",VLOOKUP(AP64,{0,0.03;36000,0.1;144000,0.2;300000,0.25;420000,0.3;660000,0.35;960000,0.45},2,1),F64="一般劳务报酬所得",IF(AP64<=20000,0.2,IF(AP64<=50000,0.3,0.4)),F64="全年一次性奖金收入",VLOOKUP(AP64/12,{0,0.03;3000,0.1;12000,0.2;25000,0.25;35000,0.3;55000,0.35;80000,0.45},2,1),F64="解除劳动合同一次性补偿金",VLOOKUP(AP64,{0,0.03;36000,0.1;144000,0.2;300000,0.25;420000,0.3;660000,0.35;960000,0.45},2,1))} -> #N/A | AR64: {=_xlfn.IFS(F64="正常工资薪金",VLOOKUP(AP64,{0,0;36000,2520;144000,16920;300000,31920;420000,52920;660000,85920;960000,181920},2,1),F64="一般劳务报酬所得",IF(AP64<=20000,0,IF(AS<=50000,2000,7000)),F64="全年一次性奖金收入",VLOOKUP(AP64/12,{0,0;3000,210;12000,1410;25000,2660;35000,4410;55000,7160;80000,15160},2,1),F64="解除劳动合同一次性补偿金",VLOOKUP(AP64,{0,0;36000,2520;144000,16920;300000,31920;420000,52920;660000,85920;960000,181920},2,1))} -> #N/A | AS64: =AP64*AQ64-AR64 -> #N/A | AT64: 0 | AU64: =BI64+BJ64 -> 0 | AV64: =IF(AS64-AT64-AU64>0,AS64-AT64-AU64,0) -> #N/A | AX64: =IFERROR(IF(F64="正常工资薪金",VLOOKUP(D64&"*",个税上月累计情况!E:AL,26,0),0),0) -> 17591.09 | AY64: =IFERROR(IF(F64="正常工资薪金",VLOOKUP(D64&"*",个税上月累计情况!E:AL,27,0),0),0) -> 20000 | AZ64: =IFERROR(IF(F64="正常工资薪金",VLOOKUP(D64&"*",个税上月累计情况!E:AL,28,0),0),0) -> 2076.96 | BA64: =IFERROR(IF(F64="正常工资薪金",VLOOKUP(D64&"*",个税上月累计情况!E:AL,29,0),0),0) -> 0 | BB64: =IFERROR(IF(F64="正常工资薪金",VLOOKUP(D64&"*",个税上月累计情况!E:AL,30,0),0),0) -> 0 | BC64: =IFERROR(IF(F64="正常工资薪金",VLOOKUP(D64&"*",个税上月累计情况!E:AL,31,0),0),0) -> 0 | BD64: =IFERROR(IF(F64="正常工资薪金",VLOOKUP(D64&"*",个税上月累计情况!E:AL,32,0),0),0) -> 0 | BE64: =IFERROR(IF(F64="正常工资薪金",VLOOKUP(D64&"*",个税上月累计情况!E:AL,33,0),0),0) -> 0 | BF64: =IFERROR(IF(F64="正常工资薪金",VLOOKUP(D64&"*",个税上月累计情况!E:AL,34,0),0),0) -> 0 | BG64: =IFERROR(IF(F64="正常工资薪金",VLOOKUP(D64&"*",个税上月累计情况!E:AN,35,0),0),0) -> 0 | BH64: =IFERROR(IF(F64="正常工资薪金",VLOOKUP(D64&"*",个税上月累计情况!E:AN,36,0),0),0) -> 0 | BI64: =IFERROR(IF(F64="正常工资薪金",VLOOKUP(D64&"*",个税上月累计情况!D:AW,46,0),0),0) -> 0 | BJ64: =IFERROR(IF(F64="正常工资薪金",VLOOKUP(D64&"*",个税上月累计情况!D:AX,47,0),0),0) -> 0 | BK64: =VLOOKUP(B64,花名册!C:N,12,0) -> #N/A
B65: 许紫怡 | C65: 居民身份证 | D65: 362323200208062528 | E65: 否 | F65: 正常工资薪金 | G65: {=_xlfn.IFS(F65="正常工资薪金",VLOOKUP(D65&"*",工资表明细!D:BL,61,0),F65="一般劳务报酬所得",VLOOKUP(D65&"*",工资表明细!D:BJ,59,0),F65="全年一次性奖金收入",VLOOKUP(D65&"*",工资表明细!D:BI,58,0),F65="解除劳动合同一次性补偿金",VLOOKUP(D65&"*",工资表明细!D:BH,57,0))} -> #N/A | H65: =IF(F65="一般劳务报酬所得",800,0) -> 0 | I65: 0 | J65: =IF(F65="正常工资薪金",5000,0) -> 5000 | K65: =IF(F65="正常工资薪金",VLOOKUP(D65&"*",工资表明细!D:AP,39,0),0) -> #N/A | L65: =IF(F65="正常工资薪金",VLOOKUP(D65&"*",工资表明细!D:AQ,40,0),0) -> #N/A | M65: =IF(F65="正常工资薪金",VLOOKUP(D65&"*",工资表明细!D:AR,41,0),0) -> #N/A | N65: =IF(F65="正常工资薪金",VLOOKUP(D65&"*",工资表明细!D:AT,43,0),0) -> #N/A | O65: 60 | P65: 60 | Q65: 60 | R65: 60 | S65: 60 | T65: 60 | U65: 60 | V65: 60 | W65: - | X65: 60 | Y65: - | Z65: - | AA65: - | AB65: 60 | AC65: =IF(F65="正常工资薪金",G65+AX65,"-") -> #N/A | AD65: =IF(F65="正常工资薪金",J65+AY65,"-") -> 25000 | AE65: =IF(F65="正常工资薪金",K65+L65+M65+N65+AZ65,"-") -> #N/A | AF65: =IFERROR(IF($F$5="正常工资薪金",IF(YEAR(BK65)<YEAR($BK$1),BA65/($D$1-1)*$D$1,BA65/DATEDIF(BK65,$BK$1,"M")*DATEDIF(BK65,$BK$1,"M")),"-"),0) -> 0 | AG65: =IFERROR(IF($F$5="正常工资薪金",IF(YEAR(BK65)<YEAR($BK$1),BB65/($D$1-1)*$D$1,BB65/DATEDIF(BK65,$BK$1,"M")*DATEDIF(BK65,$BK$1,"M")),"-"),0) -> 0 | AH65: =IFERROR(IF($F$5="正常工资薪金",IF(YEAR(BK65)<YEAR($BK$1),BC65/($D$1-1)*$D$1,BC65/(MONTH($BK$1)-MONTH(BK65))*(MONTH($BK$1)-MONTH(BK65)+1)),"-"),0) -> 0 | AI65: =IFERROR(IF($F$5="正常工资薪金",IF(YEAR(BK65)<YEAR($BK$1),BD65/($D$1-1)*$D$1,BD65/(MONTH($BK$1)-MONTH(BK65))*(MONTH($BK$1)-MONTH(BK65)+1)),"-"),0) -> 0 | AJ65: =IFERROR(IF($F$5="正常工资薪金",IF(YEAR(BK65)<YEAR($BK$1),BE65/($D$1-1)*$D$1,BE65/(MONTH($BK$1)-MONTH(BK65))*(MONTH($BK$1)-MONTH(BK65)+1)),"-"),0) -> 0 | AK65: =IFERROR(IF($F$5="正常工资薪金",IF(YEAR(BK65)<YEAR($BK$1),BF65/($D$1-1)*$D$1,BF65/(MONTH($BK$1)-MONTH(BK65))*(MONTH($BK$1)-MONTH(BK65)+1)),"-"),0) -> 0 | AL65: 0 | AM65: 0 | AN65: 100% | AO65: 0 | AP65: =IF(IF(F65="正常工资薪金",AC65-AD65-AE65-AF65-AG65-AH65-AI65-AJ65-AK65-AL65-AM65,G65-H65-I65)<0,0,IF(F65="正常工资薪金",AC65-AD65-AE65-AF65-AG65-AH65-AI65-AJ65-AK65-AL65-AM65,G65-H65-I65)) -> #N/A | AQ65: {=_xlfn.IFS(F65="正常工资薪金",VLOOKUP(AP65,{0,0.03;36000,0.1;144000,0.2;300000,0.25;420000,0.3;660000,0.35;960000,0.45},2,1),F65="一般劳务报酬所得",IF(AP65<=20000,0.2,IF(AP65<=50000,0.3,0.4)),F65="全年一次性奖金收入",VLOOKUP(AP65/12,{0,0.03;3000,0.1;12000,0.2;25000,0.25;35000,0.3;55000,0.35;80000,0.45},2,1),F65="解除劳动合同一次性补偿金",VLOOKUP(AP65,{0,0.03;36000,0.1;144000,0.2;300000,0.25;420000,0.3;660000,0.35;960000,0.45},2,1))} -> #N/A | AR65: {=_xlfn.IFS(F65="正常工资薪金",VLOOKUP(AP65,{0,0;36000,2520;144000,16920;300000,31920;420000,52920;660000,85920;960000,181920},2,1),F65="一般劳务报酬所得",IF(AP65<=20000,0,IF(AS<=50000,2000,7000)),F65="全年一次性奖金收入",VLOOKUP(AP65/12,{0,0;3000,210;12000,1410;25000,2660;35000,4410;55000,7160;80000,15160},2,1),F65="解除劳动合同一次性补偿金",VLOOKUP(AP65,{0,0;36000,2520;144000,16920;300000,31920;420000,52920;660000,85920;960000,181920},2,1))} -> #N/A | AS65: =AP65*AQ65-AR65 -> #N/A | AT65: 0 | AU65: =BI65+BJ65 -> 0 | AV65: =IF(AS65-AT65-AU65>0,AS65-AT65-AU65,0) -> #N/A | AX65: =IFERROR(IF(F65="正常工资薪金",VLOOKUP(D65&"*",个税上月累计情况!E:AL,26,0),0),0) -> 17548.55 | AY65: =IFERROR(IF(F65="正常工资薪金",VLOOKUP(D65&"*",个税上月累计情况!E:AL,27,0),0),0) -> 20000 | AZ65: =IFERROR(IF(F65="正常工资薪金",VLOOKUP(D65&"*",个税上月累计情况!E:AL,28,0),0),0) -> 2076.96 | BA65: =IFERROR(IF(F65="正常工资薪金",VLOOKUP(D65&"*",个税上月累计情况!E:AL,29,0),0),0) -> 0 | BB65: =IFERROR(IF(F65="正常工资薪金",VLOOKUP(D65&"*",个税上月累计情况!E:AL,30,0),0),0) -> 0 | BC65: =IFERROR(IF(F65="正常工资薪金",VLOOKUP(D65&"*",个税上月累计情况!E:AL,31,0),0),0) -> 0 | BD65: =IFERROR(IF(F65="正常工资薪金",VLOOKUP(D65&"*",个税上月累计情况!E:AL,32,0),0),0) -> 0 | BE65: =IFERROR(IF(F65="正常工资薪金",VLOOKUP(D65&"*",个税上月累计情况!E:AL,33,0),0),0) -> 0 | BF65: =IFERROR(IF(F65="正常工资薪金",VLOOKUP(D65&"*",个税上月累计情况!E:AL,34,0),0),0) -> 0 | BG65: =IFERROR(IF(F65="正常工资薪金",VLOOKUP(D65&"*",个税上月累计情况!E:AN,35,0),0),0) -> 0 | BH65: =IFERROR(IF(F65="正常工资薪金",VLOOKUP(D65&"*",个税上月累计情况!E:AN,36,0),0),0) -> 0 | BI65: =IFERROR(IF(F65="正常工资薪金",VLOOKUP(D65&"*",个税上月累计情况!D:AW,46,0),0),0) -> 0 | BJ65: =IFERROR(IF(F65="正常工资薪金",VLOOKUP(D65&"*",个税上月累计情况!D:AX,47,0),0),0) -> 0 | BK65: =VLOOKUP(B65,花名册!C:N,12,0) -> #N/A
B66: 李一蒙 | C66: 居民身份证 | D66: 372928200010010016 | E66: 否 | F66: 正常工资薪金 | G66: {=_xlfn.IFS(F66="正常工资薪金",VLOOKUP(D66&"*",工资表明细!D:BL,61,0),F66="一般劳务报酬所得",VLOOKUP(D66&"*",工资表明细!D:BJ,59,0),F66="全年一次性奖金收入",VLOOKUP(D66&"*",工资表明细!D:BI,58,0),F66="解除劳动合同一次性补偿金",VLOOKUP(D66&"*",工资表明细!D:BH,57,0))} -> #N/A | H66: =IF(F66="一般劳务报酬所得",800,0) -> 0 | I66: 0 | J66: =IF(F66="正常工资薪金",5000,0) -> 5000 | K66: =IF(F66="正常工资薪金",VLOOKUP(D66&"*",工资表明细!D:AP,39,0),0) -> #N/A | L66: =IF(F66="正常工资薪金",VLOOKUP(D66&"*",工资表明细!D:AQ,40,0),0) -> #N/A | M66: =IF(F66="正常工资薪金",VLOOKUP(D66&"*",工资表明细!D:AR,41,0),0) -> #N/A | N66: =IF(F66="正常工资薪金",VLOOKUP(D66&"*",工资表明细!D:AT,43,0),0) -> #N/A | O66: 61 | P66: 61 | Q66: 61 | R66: 61 | S66: 61 | T66: 61 | U66: 61 | V66: 61 | W66: - | X66: 61 | Y66: - | Z66: - | AA66: - | AB66: 61 | AC66: =IF(F66="正常工资薪金",G66+AX66,"-") -> #N/A | AD66: =IF(F66="正常工资薪金",J66+AY66,"-") -> 20000 | AE66: =IF(F66="正常工资薪金",K66+L66+M66+N66+AZ66,"-") -> #N/A | AF66: =IFERROR(IF($F$5="正常工资薪金",IF(YEAR(BK66)<YEAR($BK$1),BA66/($D$1-1)*$D$1,BA66/DATEDIF(BK66,$BK$1,"M")*DATEDIF(BK66,$BK$1,"M")),"-"),0) -> 0 | AG66: =IFERROR(IF($F$5="正常工资薪金",IF(YEAR(BK66)<YEAR($BK$1),BB66/($D$1-1)*$D$1,BB66/DATEDIF(BK66,$BK$1,"M")*DATEDIF(BK66,$BK$1,"M")),"-"),0) -> 0 | AH66: =IFERROR(IF($F$5="正常工资薪金",IF(YEAR(BK66)<YEAR($BK$1),BC66/($D$1-1)*$D$1,BC66/(MONTH($BK$1)-MONTH(BK66))*(MONTH($BK$1)-MONTH(BK66)+1)),"-"),0) -> 0 | AI66: =IFERROR(IF($F$5="正常工资薪金",IF(YEAR(BK66)<YEAR($BK$1),BD66/($D$1-1)*$D$1,BD66/(MONTH($BK$1)-MONTH(BK66))*(MONTH($BK$1)-MONTH(BK66)+1)),"-"),0) -> 0 | AJ66: =IFERROR(IF($F$5="正常工资薪金",IF(YEAR(BK66)<YEAR($BK$1),BE66/($D$1-1)*$D$1,BE66/(MONTH($BK$1)-MONTH(BK66))*(MONTH($BK$1)-MONTH(BK66)+1)),"-"),0) -> 0 | AK66: =IFERROR(IF($F$5="正常工资薪金",IF(YEAR(BK66)<YEAR($BK$1),BF66/($D$1-1)*$D$1,BF66/(MONTH($BK$1)-MONTH(BK66))*(MONTH($BK$1)-MONTH(BK66)+1)),"-"),0) -> 0 | AL66: 0 | AM66: 0 | AN66: 100% | AO66: 0 | AP66: =IF(IF(F66="正常工资薪金",AC66-AD66-AE66-AF66-AG66-AH66-AI66-AJ66-AK66-AL66-AM66,G66-H66-I66)<0,0,IF(F66="正常工资薪金",AC66-AD66-AE66-AF66-AG66-AH66-AI66-AJ66-AK66-AL66-AM66,G66-H66-I66)) -> #N/A | AQ66: {=_xlfn.IFS(F66="正常工资薪金",VLOOKUP(AP66,{0,0.03;36000,0.1;144000,0.2;300000,0.25;420000,0.3;660000,0.35;960000,0.45},2,1),F66="一般劳务报酬所得",IF(AP66<=20000,0.2,IF(AP66<=50000,0.3,0.4)),F66="全年一次性奖金收入",VLOOKUP(AP66/12,{0,0.03;3000,0.1;12000,0.2;25000,0.25;35000,0.3;55000,0.35;80000,0.45},2,1),F66="解除劳动合同一次性补偿金",VLOOKUP(AP66,{0,0.03;36000,0.1;144000,0.2;300000,0.25;420000,0.3;660000,0.35;960000,0.45},2,1))} -> #N/A | AR66: {=_xlfn.IFS(F66="正常工资薪金",VLOOKUP(AP66,{0,0;36000,2520;144000,16920;300000,31920;420000,52920;660000,85920;960000,181920},2,1),F66="一般劳务报酬所得",IF(AP66<=20000,0,IF(AS<=50000,2000,7000)),F66="全年一次性奖金收入",VLOOKUP(AP66/12,{0,0;3000,210;12000,1410;25000,2660;35000,4410;55000,7160;80000,15160},2,1),F66="解除劳动合同一次性补偿金",VLOOKUP(AP66,{0,0;36000,2520;144000,16920;300000,31920;420000,52920;660000,85920;960000,181920},2,1))} -> #N/A | AS66: =AP66*AQ66-AR66 -> #N/A | AT66: 0 | AU66: =BI66+BJ66 -> 566.23 | AV66: =IF(AS66-AT66-AU66>0,AS66-AT66-AU66,0) -> #N/A | AX66: =IFERROR(IF(F66="正常工资薪金",VLOOKUP(D66&"*",个税上月累计情况!E:AL,26,0),0),0) -> 38179.52 | AY66: =IFERROR(IF(F66="正常工资薪金",VLOOKUP(D66&"*",个税上月累计情况!E:AL,27,0),0),0) -> 15000 | AZ66: =IFERROR(IF(F66="正常工资薪金",VLOOKUP(D66&"*",个税上月累计情况!E:AL,28,0),0),0) -> 4305.03 | BA66: =IFERROR(IF(F66="正常工资薪金",VLOOKUP(D66&"*",个税上月累计情况!E:AL,29,0),0),0) -> 0 | BB66: =IFERROR(IF(F66="正常工资薪金",VLOOKUP(D66&"*",个税上月累计情况!E:AL,30,0),0),0) -> 0 | BC66: =IFERROR(IF(F66="正常工资薪金",VLOOKUP(D66&"*",个税上月累计情况!E:AL,31,0),0),0) -> 0 | BD66: =IFERROR(IF(F66="正常工资薪金",VLOOKUP(D66&"*",个税上月累计情况!E:AL,32,0),0),0) -> 0 | BE66: =IFERROR(IF(F66="正常工资薪金",VLOOKUP(D66&"*",个税上月累计情况!E:AL,33,0),0),0) -> 0 | BF66: =IFERROR(IF(F66="正常工资薪金",VLOOKUP(D66&"*",个税上月累计情况!E:AL,34,0),0),0) -> 0 | BG66: =IFERROR(IF(F66="正常工资薪金",VLOOKUP(D66&"*",个税上月累计情况!E:AN,35,0),0),0) -> 0 | BH66: =IFERROR(IF(F66="正常工资薪金",VLOOKUP(D66&"*",个税上月累计情况!E:AN,36,0),0),0) -> 0 | BI66: =IFERROR(IF(F66="正常工资薪金",VLOOKUP(D66&"*",个税上月累计情况!D:AW,46,0),0),0) -> 352.19 | BJ66: =IFERROR(IF(F66="正常工资薪金",VLOOKUP(D66&"*",个税上月累计情况!D:AX,47,0),0),0) -> 214.04 | BK66: =VLOOKUP(B66,花名册!C:N,12,0) -> #N/A
B67: 冯俊磊 | C67: 居民身份证 | D67: 412825199805203017 | E67: 否 | F67: 正常工资薪金 | G67: {=_xlfn.IFS(F67="正常工资薪金",VLOOKUP(D67&"*",工资表明细!D:BL,61,0),F67="一般劳务报酬所得",VLOOKUP(D67&"*",工资表明细!D:BJ,59,0),F67="全年一次性奖金收入",VLOOKUP(D67&"*",工资表明细!D:BI,58,0),F67="解除劳动合同一次性补偿金",VLOOKUP(D67&"*",工资表明细!D:BH,57,0))} -> #N/A | H67: =IF(F67="一般劳务报酬所得",800,0) -> 0 | I67: 0 | J67: =IF(F67="正常工资薪金",5000,0) -> 5000 | K67: =IF(F67="正常工资薪金",VLOOKUP(D67&"*",工资表明细!D:AP,39,0),0) -> #N/A | L67: =IF(F67="正常工资薪金",VLOOKUP(D67&"*",工资表明细!D:AQ,40,0),0) -> #N/A | M67: =IF(F67="正常工资薪金",VLOOKUP(D67&"*",工资表明细!D:AR,41,0),0) -> #N/A | N67: =IF(F67="正常工资薪金",VLOOKUP(D67&"*",工资表明细!D:AT,43,0),0) -> #N/A | O67: 62 | P67: 62 | Q67: 62 | R67: 62 | S67: 62 | T67: 62 | U67: 62 | V67: 62 | W67: - | X67: 62 | Y67: - | Z67: - | AA67: - | AB67: 62 | AC67: =IF(F67="正常工资薪金",G67+AX67,"-") -> #N/A | AD67: =IF(F67="正常工资薪金",J67+AY67,"-") -> 20000 | AE67: =IF(F67="正常工资薪金",K67+L67+M67+N67+AZ67,"-") -> #N/A | AF67: =IFERROR(IF($F$5="正常工资薪金",IF(YEAR(BK67)<YEAR($BK$1),BA67/($D$1-1)*$D$1,BA67/DATEDIF(BK67,$BK$1,"M")*DATEDIF(BK67,$BK$1,"M")),"-"),0) -> 0 | AG67: =IFERROR(IF($F$5="正常工资薪金",IF(YEAR(BK67)<YEAR($BK$1),BB67/($D$1-1)*$D$1,BB67/DATEDIF(BK67,$BK$1,"M")*DATEDIF(BK67,$BK$1,"M")),"-"),0) -> 0 | AH67: =IFERROR(IF($F$5="正常工资薪金",IF(YEAR(BK67)<YEAR($BK$1),BC67/($D$1-1)*$D$1,BC67/(MONTH($BK$1)-MONTH(BK67))*(MONTH($BK$1)-MONTH(BK67)+1)),"-"),0) -> 0 | AI67: =IFERROR(IF($F$5="正常工资薪金",IF(YEAR(BK67)<YEAR($BK$1),BD67/($D$1-1)*$D$1,BD67/(MONTH($BK$1)-MONTH(BK67))*(MONTH($BK$1)-MONTH(BK67)+1)),"-"),0) -> 0 | AJ67: =IFERROR(IF($F$5="正常工资薪金",IF(YEAR(BK67)<YEAR($BK$1),BE67/($D$1-1)*$D$1,BE67/(MONTH($BK$1)-MONTH(BK67))*(MONTH($BK$1)-MONTH(BK67)+1)),"-"),0) -> 0 | AK67: =IFERROR(IF($F$5="正常工资薪金",IF(YEAR(BK67)<YEAR($BK$1),BF67/($D$1-1)*$D$1,BF67/(MONTH($BK$1)-MONTH(BK67))*(MONTH($BK$1)-MONTH(BK67)+1)),"-"),0) -> 0 | AL67: 0 | AM67: 0 | AN67: 100% | AO67: 0 | AP67: =IF(IF(F67="正常工资薪金",AC67-AD67-AE67-AF67-AG67-AH67-AI67-AJ67-AK67-AL67-AM67,G67-H67-I67)<0,0,IF(F67="正常工资薪金",AC67-AD67-AE67-AF67-AG67-AH67-AI67-AJ67-AK67-AL67-AM67,G67-H67-I67)) -> #N/A | AQ67: {=_xlfn.IFS(F67="正常工资薪金",VLOOKUP(AP67,{0,0.03;36000,0.1;144000,0.2;300000,0.25;420000,0.3;660000,0.35;960000,0.45},2,1),F67="一般劳务报酬所得",IF(AP67<=20000,0.2,IF(AP67<=50000,0.3,0.4)),F67="全年一次性奖金收入",VLOOKUP(AP67/12,{0,0.03;3000,0.1;12000,0.2;25000,0.25;35000,0.3;55000,0.35;80000,0.45},2,1),F67="解除劳动合同一次性补偿金",VLOOKUP(AP67,{0,0.03;36000,0.1;144000,0.2;300000,0.25;420000,0.3;660000,0.35;960000,0.45},2,1))} -> #N/A | AR67: {=_xlfn.IFS(F67="正常工资薪金",VLOOKUP(AP67,{0,0;36000,2520;144000,16920;300000,31920;420000,52920;660000,85920;960000,181920},2,1),F67="一般劳务报酬所得",IF(AP67<=20000,0,IF(AS<=50000,2000,7000)),F67="全年一次性奖金收入",VLOOKUP(AP67/12,{0,0;3000,210;12000,1410;25000,2660;35000,4410;55000,7160;80000,15160},2,1),F67="解除劳动合同一次性补偿金",VLOOKUP(AP67,{0,0;36000,2520;144000,16920;300000,31920;420000,52920;660000,85920;960000,181920},2,1))} -> #N/A | AS67: =AP67*AQ67-AR67 -> #N/A | AT67: 0 | AU67: =BI67+BJ67 -> 108.91 | AV67: =IF(AS67-AT67-AU67>0,AS67-AT67-AU67,0) -> #N/A | AX67: =IFERROR(IF(F67="正常工资薪金",VLOOKUP(D67&"*",个税上月累计情况!E:AL,26,0),0),0) -> 22095.24 | AY67: =IFERROR(IF(F67="正常工资薪金",VLOOKUP(D67&"*",个税上月累计情况!E:AL,27,0),0),0) -> 15000 | AZ67: =IFERROR(IF(F67="正常工资薪金",VLOOKUP(D67&"*",个税上月累计情况!E:AL,28,0),0),0) -> 3465.03 | BA67: =IFERROR(IF(F67="正常工资薪金",VLOOKUP(D67&"*",个税上月累计情况!E:AL,29,0),0),0) -> 0 | BB67: =IFERROR(IF(F67="正常工资薪金",VLOOKUP(D67&"*",个税上月累计情况!E:AL,30,0),0),0) -> 0 | BC67: =IFERROR(IF(F67="正常工资薪金",VLOOKUP(D67&"*",个税上月累计情况!E:AL,31,0),0),0) -> 0 | BD67: =IFERROR(IF(F67="正常工资薪金",VLOOKUP(D67&"*",个税上月累计情况!E:AL,32,0),0),0) -> 0 | BE67: =IFERROR(IF(F67="正常工资薪金",VLOOKUP(D67&"*",个税上月累计情况!E:AL,33,0),0),0) -> 0 | BF67: =IFERROR(IF(F67="正常工资薪金",VLOOKUP(D67&"*",个税上月累计情况!E:AL,34,0),0),0) -> 0 | BG67: =IFERROR(IF(F67="正常工资薪金",VLOOKUP(D67&"*",个税上月累计情况!E:AN,35,0),0),0) -> 0 | BH67: =IFERROR(IF(F67="正常工资薪金",VLOOKUP(D67&"*",个税上月累计情况!E:AN,36,0),0),0) -> 0 | BI67: =IFERROR(IF(F67="正常工资薪金",VLOOKUP(D67&"*",个税上月累计情况!D:AW,46,0),0),0) -> 53.56 | BJ67: =IFERROR(IF(F67="正常工资薪金",VLOOKUP(D67&"*",个税上月累计情况!D:AX,47,0),0),0) -> 55.35 | BK67: =VLOOKUP(B67,花名册!C:N,12,0) -> #N/A
B68: 陈龙 | C68: 居民身份证 | D68: 131127198602104395 | E68: 否 | F68: 正常工资薪金 | G68: {=_xlfn.IFS(F68="正常工资薪金",VLOOKUP(D68&"*",工资表明细!D:BL,61,0),F68="一般劳务报酬所得",VLOOKUP(D68&"*",工资表明细!D:BJ,59,0),F68="全年一次性奖金收入",VLOOKUP(D68&"*",工资表明细!D:BI,58,0),F68="解除劳动合同一次性补偿金",VLOOKUP(D68&"*",工资表明细!D:BH,57,0))} -> #N/A | H68: =IF(F68="一般劳务报酬所得",800,0) -> 0 | I68: 0 | J68: =IF(F68="正常工资薪金",5000,0) -> 5000 | K68: =IF(F68="正常工资薪金",VLOOKUP(D68&"*",工资表明细!D:AP,39,0),0) -> #N/A | L68: =IF(F68="正常工资薪金",VLOOKUP(D68&"*",工资表明细!D:AQ,40,0),0) -> #N/A | M68: =IF(F68="正常工资薪金",VLOOKUP(D68&"*",工资表明细!D:AR,41,0),0) -> #N/A | N68: =IF(F68="正常工资薪金",VLOOKUP(D68&"*",工资表明细!D:AT,43,0),0) -> #N/A | O68: 63 | P68: 63 | Q68: 63 | R68: 63 | S68: 63 | T68: 63 | U68: 63 | V68: 63 | W68: - | X68: 63 | Y68: - | Z68: - | AA68: - | AB68: 63 | AC68: =IF(F68="正常工资薪金",G68+AX68,"-") -> #N/A | AD68: =IF(F68="正常工资薪金",J68+AY68,"-") -> 20000 | AE68: =IF(F68="正常工资薪金",K68+L68+M68+N68+AZ68,"-") -> #N/A | AF68: =IFERROR(IF($F$5="正常工资薪金",IF(YEAR(BK68)<YEAR($BK$1),BA68/($D$1-1)*$D$1,BA68/DATEDIF(BK68,$BK$1,"M")*DATEDIF(BK68,$BK$1,"M")),"-"),0) -> 0 | AG68: =IFERROR(IF($F$5="正常工资薪金",IF(YEAR(BK68)<YEAR($BK$1),BB68/($D$1-1)*$D$1,BB68/DATEDIF(BK68,$BK$1,"M")*DATEDIF(BK68,$BK$1,"M")),"-"),0) -> 0 | AH68: =IFERROR(IF($F$5="正常工资薪金",IF(YEAR(BK68)<YEAR($BK$1),BC68/($D$1-1)*$D$1,BC68/(MONTH($BK$1)-MONTH(BK68))*(MONTH($BK$1)-MONTH(BK68)+1)),"-"),0) -> 0 | AI68: =IFERROR(IF($F$5="正常工资薪金",IF(YEAR(BK68)<YEAR($BK$1),BD68/($D$1-1)*$D$1,BD68/(MONTH($BK$1)-MONTH(BK68))*(MONTH($BK$1)-MONTH(BK68)+1)),"-"),0) -> 0 | AJ68: =IFERROR(IF($F$5="正常工资薪金",IF(YEAR(BK68)<YEAR($BK$1),BE68/($D$1-1)*$D$1,BE68/(MONTH($BK$1)-MONTH(BK68))*(MONTH($BK$1)-MONTH(BK68)+1)),"-"),0) -> 0 | AK68: =IFERROR(IF($F$5="正常工资薪金",IF(YEAR(BK68)<YEAR($BK$1),BF68/($D$1-1)*$D$1,BF68/(MONTH($BK$1)-MONTH(BK68))*(MONTH($BK$1)-MONTH(BK68)+1)),"-"),0) -> 0 | AL68: 0 | AM68: 0 | AN68: 100% | AO68: 0 | AP68: =IF(IF(F68="正常工资薪金",AC68-AD68-AE68-AF68-AG68-AH68-AI68-AJ68-AK68-AL68-AM68,G68-H68-I68)<0,0,IF(F68="正常工资薪金",AC68-AD68-AE68-AF68-AG68-AH68-AI68-AJ68-AK68-AL68-AM68,G68-H68-I68)) -> #N/A | AQ68: {=_xlfn.IFS(F68="正常工资薪金",VLOOKUP(AP68,{0,0.03;36000,0.1;144000,0.2;300000,0.25;420000,0.3;660000,0.35;960000,0.45},2,1),F68="一般劳务报酬所得",IF(AP68<=20000,0.2,IF(AP68<=50000,0.3,0.4)),F68="全年一次性奖金收入",VLOOKUP(AP68/12,{0,0.03;3000,0.1;12000,0.2;25000,0.25;35000,0.3;55000,0.35;80000,0.45},2,1),F68="解除劳动合同一次性补偿金",VLOOKUP(AP68,{0,0.03;36000,0.1;144000,0.2;300000,0.25;420000,0.3;660000,0.35;960000,0.45},2,1))} -> #N/A | AR68: {=_xlfn.IFS(F68="正常工资薪金",VLOOKUP(AP68,{0,0;36000,2520;144000,16920;300000,31920;420000,52920;660000,85920;960000,181920},2,1),F68="一般劳务报酬所得",IF(AP68<=20000,0,IF(AS<=50000,2000,7000)),F68="全年一次性奖金收入",VLOOKUP(AP68/12,{0,0;3000,210;12000,1410;25000,2660;35000,4410;55000,7160;80000,15160},2,1),F68="解除劳动合同一次性补偿金",VLOOKUP(AP68,{0,0;36000,2520;144000,16920;300000,31920;420000,52920;660000,85920;960000,181920},2,1))} -> #N/A | AS68: =AP68*AQ68-AR68 -> #N/A | AT68: 0 | AU68: =BI68+BJ68 -> 923.82 | AV68: =IF(AS68-AT68-AU68>0,AS68-AT68-AU68,0) -> #N/A | AX68: =IFERROR(IF(F68="正常工资薪金",VLOOKUP(D68&"*",个税上月累计情况!E:AL,26,0),0),0) -> 50819.05 | AY68: =IFERROR(IF(F68="正常工资薪金",VLOOKUP(D68&"*",个税上月累计情况!E:AL,27,0),0),0) -> 15000 | AZ68: =IFERROR(IF(F68="正常工资薪金",VLOOKUP(D68&"*",个税上月累计情况!E:AL,28,0),0),0) -> 5025.03 | BA68: =IFERROR(IF(F68="正常工资薪金",VLOOKUP(D68&"*",个税上月累计情况!E:AL,29,0),0),0) -> 0 | BB68: =IFERROR(IF(F68="正常工资薪金",VLOOKUP(D68&"*",个税上月累计情况!E:AL,30,0),0),0) -> 0 | BC68: =IFERROR(IF(F68="正常工资薪金",VLOOKUP(D68&"*",个税上月累计情况!E:AL,31,0),0),0) -> 0 | BD68: =IFERROR(IF(F68="正常工资薪金",VLOOKUP(D68&"*",个税上月累计情况!E:AL,32,0),0),0) -> 0 | BE68: =IFERROR(IF(F68="正常工资薪金",VLOOKUP(D68&"*",个税上月累计情况!E:AL,33,0),0),0) -> 0 | BF68: =IFERROR(IF(F68="正常工资薪金",VLOOKUP(D68&"*",个税上月累计情况!E:AL,34,0),0),0) -> 0 | BG68: =IFERROR(IF(F68="正常工资薪金",VLOOKUP(D68&"*",个税上月累计情况!E:AN,35,0),0),0) -> 0 | BH68: =IFERROR(IF(F68="正常工资薪金",VLOOKUP(D68&"*",个税上月累计情况!E:AN,36,0),0),0) -> 0 | BI68: =IFERROR(IF(F68="正常工资薪金",VLOOKUP(D68&"*",个税上月累计情况!D:AW,46,0),0),0) -> 572.07 | BJ68: =IFERROR(IF(F68="正常工资薪金",VLOOKUP(D68&"*",个税上月累计情况!D:AX,47,0),0),0) -> 351.75 | BK68: =VLOOKUP(B68,花名册!C:N,12,0) -> #N/A
B69: 龙江慧 | C69: 居民身份证 | D69: 430224200004226866 | E69: 否 | F69: 正常工资薪金 | G69: {=_xlfn.IFS(F69="正常工资薪金",VLOOKUP(D69&"*",工资表明细!D:BL,61,0),F69="一般劳务报酬所得",VLOOKUP(D69&"*",工资表明细!D:BJ,59,0),F69="全年一次性奖金收入",VLOOKUP(D69&"*",工资表明细!D:BI,58,0),F69="解除劳动合同一次性补偿金",VLOOKUP(D69&"*",工资表明细!D:BH,57,0))} -> #N/A | H69: =IF(F69="一般劳务报酬所得",800,0) -> 0 | I69: 0 | J69: =IF(F69="正常工资薪金",5000,0) -> 5000 | K69: =IF(F69="正常工资薪金",VLOOKUP(D69&"*",工资表明细!D:AP,39,0),0) -> #N/A | L69: =IF(F69="正常工资薪金",VLOOKUP(D69&"*",工资表明细!D:AQ,40,0),0) -> #N/A | M69: =IF(F69="正常工资薪金",VLOOKUP(D69&"*",工资表明细!D:AR,41,0),0) -> #N/A | N69: =IF(F69="正常工资薪金",VLOOKUP(D69&"*",工资表明细!D:AT,43,0),0) -> #N/A | O69: 64 | P69: 64 | Q69: 64 | R69: 64 | S69: 64 | T69: 64 | U69: 64 | V69: 64 | W69: - | X69: 64 | Y69: - | Z69: - | AA69: - | AB69: 64 | AC69: =IF(F69="正常工资薪金",G69+AX69,"-") -> #N/A | AD69: =IF(F69="正常工资薪金",J69+AY69,"-") -> 20000 | AE69: =IF(F69="正常工资薪金",K69+L69+M69+N69+AZ69,"-") -> #N/A | AF69: =IFERROR(IF($F$5="正常工资薪金",IF(YEAR(BK69)<YEAR($BK$1),BA69/($D$1-1)*$D$1,BA69/DATEDIF(BK69,$BK$1,"M")*DATEDIF(BK69,$BK$1,"M")),"-"),0) -> 0 | AG69: =IFERROR(IF($F$5="正常工资薪金",IF(YEAR(BK69)<YEAR($BK$1),BB69/($D$1-1)*$D$1,BB69/DATEDIF(BK69,$BK$1,"M")*DATEDIF(BK69,$BK$1,"M")),"-"),0) -> 0 | AH69: =IFERROR(IF($F$5="正常工资薪金",IF(YEAR(BK69)<YEAR($BK$1),BC69/($D$1-1)*$D$1,BC69/(MONTH($BK$1)-MONTH(BK69))*(MONTH($BK$1)-MONTH(BK69)+1)),"-"),0) -> 0 | AI69: =IFERROR(IF($F$5="正常工资薪金",IF(YEAR(BK69)<YEAR($BK$1),BD69/($D$1-1)*$D$1,BD69/(MONTH($BK$1)-MONTH(BK69))*(MONTH($BK$1)-MONTH(BK69)+1)),"-"),0) -> 0 | AJ69: =IFERROR(IF($F$5="正常工资薪金",IF(YEAR(BK69)<YEAR($BK$1),BE69/($D$1-1)*$D$1,BE69/(MONTH($BK$1)-MONTH(BK69))*(MONTH($BK$1)-MONTH(BK69)+1)),"-"),0) -> 0 | AK69: =IFERROR(IF($F$5="正常工资薪金",IF(YEAR(BK69)<YEAR($BK$1),BF69/($D$1-1)*$D$1,BF69/(MONTH($BK$1)-MONTH(BK69))*(MONTH($BK$1)-MONTH(BK69)+1)),"-"),0) -> 0 | AL69: 0 | AM69: 0 | AN69: 100% | AO69: 0 | AP69: =IF(IF(F69="正常工资薪金",AC69-AD69-AE69-AF69-AG69-AH69-AI69-AJ69-AK69-AL69-AM69,G69-H69-I69)<0,0,IF(F69="正常工资薪金",AC69-AD69-AE69-AF69-AG69-AH69-AI69-AJ69-AK69-AL69-AM69,G69-H69-I69)) -> #N/A | AQ69: {=_xlfn.IFS(F69="正常工资薪金",VLOOKUP(AP69,{0,0.03;36000,0.1;144000,0.2;300000,0.25;420000,0.3;660000,0.35;960000,0.45},2,1),F69="一般劳务报酬所得",IF(AP69<=20000,0.2,IF(AP69<=50000,0.3,0.4)),F69="全年一次性奖金收入",VLOOKUP(AP69/12,{0,0.03;3000,0.1;12000,0.2;25000,0.25;35000,0.3;55000,0.35;80000,0.45},2,1),F69="解除劳动合同一次性补偿金",VLOOKUP(AP69,{0,0.03;36000,0.1;144000,0.2;300000,0.25;420000,0.3;660000,0.35;960000,0.45},2,1))} -> #N/A | AR69: {=_xlfn.IFS(F69="正常工资薪金",VLOOKUP(AP69,{0,0;36000,2520;144000,16920;300000,31920;420000,52920;660000,85920;960000,181920},2,1),F69="一般劳务报酬所得",IF(AP69<=20000,0,IF(AS<=50000,2000,7000)),F69="全年一次性奖金收入",VLOOKUP(AP69/12,{0,0;3000,210;12000,1410;25000,2660;35000,4410;55000,7160;80000,15160},2,1),F69="解除劳动合同一次性补偿金",VLOOKUP(AP69,{0,0;36000,2520;144000,16920;300000,31920;420000,52920;660000,85920;960000,181920},2,1))} -> #N/A | AS69: =AP69*AQ69-AR69 -> #N/A | AT69: 0 | AU69: =BI69+BJ69 -> 82.21 | AV69: =IF(AS69-AT69-AU69>0,AS69-AT69-AU69,0) -> #N/A | AX69: =IFERROR(IF(F69="正常工资薪金",VLOOKUP(D69&"*",个税上月累计情况!E:AL,26,0),0),0) -> 21205.26 | AY69: =IFERROR(IF(F69="正常工资薪金",VLOOKUP(D69&"*",个税上月累计情况!E:AL,27,0),0),0) -> 15000 | AZ69: =IFERROR(IF(F69="正常工资薪金",VLOOKUP(D69&"*",个税上月累计情况!E:AL,28,0),0),0) -> 3465.03 | BA69: =IFERROR(IF(F69="正常工资薪金",VLOOKUP(D69&"*",个税上月累计情况!E:AL,29,0),0),0) -> 0 | BB69: =IFERROR(IF(F69="正常工资薪金",VLOOKUP(D69&"*",个税上月累计情况!E:AL,30,0),0),0) -> 0 | BC69: =IFERROR(IF(F69="正常工资薪金",VLOOKUP(D69&"*",个税上月累计情况!E:AL,31,0),0),0) -> 0 | BD69: =IFERROR(IF(F69="正常工资薪金",VLOOKUP(D69&"*",个税上月累计情况!E:AL,32,0),0),0) -> 0 | BE69: =IFERROR(IF(F69="正常工资薪金",VLOOKUP(D69&"*",个税上月累计情况!E:AL,33,0),0),0) -> 0 | BF69: =IFERROR(IF(F69="正常工资薪金",VLOOKUP(D69&"*",个税上月累计情况!E:AL,34,0),0),0) -> 0 | BG69: =IFERROR(IF(F69="正常工资薪金",VLOOKUP(D69&"*",个税上月累计情况!E:AN,35,0),0),0) -> 0 | BH69: =IFERROR(IF(F69="正常工资薪金",VLOOKUP(D69&"*",个税上月累计情况!E:AN,36,0),0),0) -> 0 | BI69: =IFERROR(IF(F69="正常工资薪金",VLOOKUP(D69&"*",个税上月累计情况!D:AW,46,0),0),0) -> 26.86 | BJ69: =IFERROR(IF(F69="正常工资薪金",VLOOKUP(D69&"*",个税上月累计情况!D:AX,47,0),0),0) -> 55.35 | BK69: =VLOOKUP(B69,花名册!C:N,12,0) -> #N/A
B70: 邢佳齐 | C70: 居民身份证 | D70: 410721200206190528 | E70: 否 | F70: 正常工资薪金 | G70: {=_xlfn.IFS(F70="正常工资薪金",VLOOKUP(D70&"*",工资表明细!D:BL,61,0),F70="一般劳务报酬所得",VLOOKUP(D70&"*",工资表明细!D:BJ,59,0),F70="全年一次性奖金收入",VLOOKUP(D70&"*",工资表明细!D:BI,58,0),F70="解除劳动合同一次性补偿金",VLOOKUP(D70&"*",工资表明细!D:BH,57,0))} -> #N/A | H70: =IF(F70="一般劳务报酬所得",800,0) -> 0 | I70: 0 | J70: =IF(F70="正常工资薪金",5000,0) -> 5000 | K70: =IF(F70="正常工资薪金",VLOOKUP(D70&"*",工资表明细!D:AP,39,0),0) -> #N/A | L70: =IF(F70="正常工资薪金",VLOOKUP(D70&"*",工资表明细!D:AQ,40,0),0) -> #N/A | M70: =IF(F70="正常工资薪金",VLOOKUP(D70&"*",工资表明细!D:AR,41,0),0) -> #N/A | N70: =IF(F70="正常工资薪金",VLOOKUP(D70&"*",工资表明细!D:AT,43,0),0) -> #N/A | O70: 65 | P70: 65 | Q70: 65 | R70: 65 | S70: 65 | T70: 65 | U70: 65 | V70: 65 | W70: - | X70: 65 | Y70: - | Z70: - | AA70: - | AB70: 65 | AC70: =IF(F70="正常工资薪金",G70+AX70,"-") -> #N/A | AD70: =IF(F70="正常工资薪金",J70+AY70,"-") -> 20000 | AE70: =IF(F70="正常工资薪金",K70+L70+M70+N70+AZ70,"-") -> #N/A | AF70: =IFERROR(IF($F$5="正常工资薪金",IF(YEAR(BK70)<YEAR($BK$1),BA70/($D$1-1)*$D$1,BA70/DATEDIF(BK70,$BK$1,"M")*DATEDIF(BK70,$BK$1,"M")),"-"),0) -> 0 | AG70: =IFERROR(IF($F$5="正常工资薪金",IF(YEAR(BK70)<YEAR($BK$1),BB70/($D$1-1)*$D$1,BB70/DATEDIF(BK70,$BK$1,"M")*DATEDIF(BK70,$BK$1,"M")),"-"),0) -> 0 | AH70: =IFERROR(IF($F$5="正常工资薪金",IF(YEAR(BK70)<YEAR($BK$1),BC70/($D$1-1)*$D$1,BC70/(MONTH($BK$1)-MONTH(BK70))*(MONTH($BK$1)-MONTH(BK70)+1)),"-"),0) -> 0 | AI70: =IFERROR(IF($F$5="正常工资薪金",IF(YEAR(BK70)<YEAR($BK$1),BD70/($D$1-1)*$D$1,BD70/(MONTH($BK$1)-MONTH(BK70))*(MONTH($BK$1)-MONTH(BK70)+1)),"-"),0) -> 0 | AJ70: =IFERROR(IF($F$5="正常工资薪金",IF(YEAR(BK70)<YEAR($BK$1),BE70/($D$1-1)*$D$1,BE70/(MONTH($BK$1)-MONTH(BK70))*(MONTH($BK$1)-MONTH(BK70)+1)),"-"),0) -> 0 | AK70: =IFERROR(IF($F$5="正常工资薪金",IF(YEAR(BK70)<YEAR($BK$1),BF70/($D$1-1)*$D$1,BF70/(MONTH($BK$1)-MONTH(BK70))*(MONTH($BK$1)-MONTH(BK70)+1)),"-"),0) -> 0 | AL70: 0 | AM70: 0 | AN70: 100% | AO70: 0 | AP70: =IF(IF(F70="正常工资薪金",AC70-AD70-AE70-AF70-AG70-AH70-AI70-AJ70-AK70-AL70-AM70,G70-H70-I70)<0,0,IF(F70="正常工资薪金",AC70-AD70-AE70-AF70-AG70-AH70-AI70-AJ70-AK70-AL70-AM70,G70-H70-I70)) -> #N/A | AQ70: {=_xlfn.IFS(F70="正常工资薪金",VLOOKUP(AP70,{0,0.03;36000,0.1;144000,0.2;300000,0.25;420000,0.3;660000,0.35;960000,0.45},2,1),F70="一般劳务报酬所得",IF(AP70<=20000,0.2,IF(AP70<=50000,0.3,0.4)),F70="全年一次性奖金收入",VLOOKUP(AP70/12,{0,0.03;3000,0.1;12000,0.2;25000,0.25;35000,0.3;55000,0.35;80000,0.45},2,1),F70="解除劳动合同一次性补偿金",VLOOKUP(AP70,{0,0.03;36000,0.1;144000,0.2;300000,0.25;420000,0.3;660000,0.35;960000,0.45},2,1))} -> #N/A | AR70: {=_xlfn.IFS(F70="正常工资薪金",VLOOKUP(AP70,{0,0;36000,2520;144000,16920;300000,31920;420000,52920;660000,85920;960000,181920},2,1),F70="一般劳务报酬所得",IF(AP70<=20000,0,IF(AS<=50000,2000,7000)),F70="全年一次性奖金收入",VLOOKUP(AP70/12,{0,0;3000,210;12000,1410;25000,2660;35000,4410;55000,7160;80000,15160},2,1),F70="解除劳动合同一次性补偿金",VLOOKUP(AP70,{0,0;36000,2520;144000,16920;300000,31920;420000,52920;660000,85920;960000,181920},2,1))} -> #N/A | AS70: =AP70*AQ70-AR70 -> #N/A | AT70: 0 | AU70: =BI70+BJ70 -> 0 | AV70: =IF(AS70-AT70-AU70>0,AS70-AT70-AU70,0) -> #N/A | AX70: =IFERROR(IF(F70="正常工资薪金",VLOOKUP(D70&"*",个税上月累计情况!E:AL,26,0),0),0) -> 16457.14 | AY70: =IFERROR(IF(F70="正常工资薪金",VLOOKUP(D70&"*",个税上月累计情况!E:AL,27,0),0),0) -> 15000 | AZ70: =IFERROR(IF(F70="正常工资薪金",VLOOKUP(D70&"*",个税上月累计情况!E:AL,28,0),0),0) -> 2230.02 | BA70: =IFERROR(IF(F70="正常工资薪金",VLOOKUP(D70&"*",个税上月累计情况!E:AL,29,0),0),0) -> 0 | BB70: =IFERROR(IF(F70="正常工资薪金",VLOOKUP(D70&"*",个税上月累计情况!E:AL,30,0),0),0) -> 0 | BC70: =IFERROR(IF(F70="正常工资薪金",VLOOKUP(D70&"*",个税上月累计情况!E:AL,31,0),0),0) -> 0 | BD70: =IFERROR(IF(F70="正常工资薪金",VLOOKUP(D70&"*",个税上月累计情况!E:AL,32,0),0),0) -> 0 | BE70: =IFERROR(IF(F70="正常工资薪金",VLOOKUP(D70&"*",个税上月累计情况!E:AL,33,0),0),0) -> 0 | BF70: =IFERROR(IF(F70="正常工资薪金",VLOOKUP(D70&"*",个税上月累计情况!E:AL,34,0),0),0) -> 0 | BG70: =IFERROR(IF(F70="正常工资薪金",VLOOKUP(D70&"*",个税上月累计情况!E:AN,35,0),0),0) -> 0 | BH70: =IFERROR(IF(F70="正常工资薪金",VLOOKUP(D70&"*",个税上月累计情况!E:AN,36,0),0),0) -> 0 | BI70: =IFERROR(IF(F70="正常工资薪金",VLOOKUP(D70&"*",个税上月累计情况!D:AW,46,0),0),0) -> 0 | BJ70: =IFERROR(IF(F70="正常工资薪金",VLOOKUP(D70&"*",个税上月累计情况!D:AX,47,0),0),0) -> 0 | BK70: =VLOOKUP(B70,花名册!C:N,12,0) -> #N/A
B71: 吴松 | C71: 居民身份证 | D71: 131082199312094137 | E71: 否 | F71: 正常工资薪金 | G71: {=_xlfn.IFS(F71="正常工资薪金",VLOOKUP(D71&"*",工资表明细!D:BL,61,0),F71="一般劳务报酬所得",VLOOKUP(D71&"*",工资表明细!D:BJ,59,0),F71="全年一次性奖金收入",VLOOKUP(D71&"*",工资表明细!D:BI,58,0),F71="解除劳动合同一次性补偿金",VLOOKUP(D71&"*",工资表明细!D:BH,57,0))} -> #N/A | H71: =IF(F71="一般劳务报酬所得",800,0) -> 0 | I71: 0 | J71: =IF(F71="正常工资薪金",5000,0) -> 5000 | K71: =IF(F71="正常工资薪金",VLOOKUP(D71&"*",工资表明细!D:AP,39,0),0) -> #N/A | L71: =IF(F71="正常工资薪金",VLOOKUP(D71&"*",工资表明细!D:AQ,40,0),0) -> #N/A | M71: =IF(F71="正常工资薪金",VLOOKUP(D71&"*",工资表明细!D:AR,41,0),0) -> #N/A | N71: =IF(F71="正常工资薪金",VLOOKUP(D71&"*",工资表明细!D:AT,43,0),0) -> #N/A | O71: 66 | P71: 66 | Q71: 66 | R71: 66 | S71: 66 | T71: 66 | U71: 66 | V71: 66 | W71: - | X71: 66 | Y71: - | Z71: - | AA71: - | AB71: 66 | AC71: =IF(F71="正常工资薪金",G71+AX71,"-") -> #N/A | AD71: =IF(F71="正常工资薪金",J71+AY71,"-") -> 20000 | AE71: =IF(F71="正常工资薪金",K71+L71+M71+N71+AZ71,"-") -> #N/A | AF71: =IFERROR(IF($F$5="正常工资薪金",IF(YEAR(BK71)<YEAR($BK$1),BA71/($D$1-1)*$D$1,BA71/DATEDIF(BK71,$BK$1,"M")*DATEDIF(BK71,$BK$1,"M")),"-"),0) -> 0 | AG71: =IFERROR(IF($F$5="正常工资薪金",IF(YEAR(BK71)<YEAR($BK$1),BB71/($D$1-1)*$D$1,BB71/DATEDIF(BK71,$BK$1,"M")*DATEDIF(BK71,$BK$1,"M")),"-"),0) -> 0 | AH71: =IFERROR(IF($F$5="正常工资薪金",IF(YEAR(BK71)<YEAR($BK$1),BC71/($D$1-1)*$D$1,BC71/(MONTH($BK$1)-MONTH(BK71))*(MONTH($BK$1)-MONTH(BK71)+1)),"-"),0) -> 0 | AI71: =IFERROR(IF($F$5="正常工资薪金",IF(YEAR(BK71)<YEAR($BK$1),BD71/($D$1-1)*$D$1,BD71/(MONTH($BK$1)-MONTH(BK71))*(MONTH($BK$1)-MONTH(BK71)+1)),"-"),0) -> 0 | AJ71: =IFERROR(IF($F$5="正常工资薪金",IF(YEAR(BK71)<YEAR($BK$1),BE71/($D$1-1)*$D$1,BE71/(MONTH($BK$1)-MONTH(BK71))*(MONTH($BK$1)-MONTH(BK71)+1)),"-"),0) -> 0 | AK71: =IFERROR(IF($F$5="正常工资薪金",IF(YEAR(BK71)<YEAR($BK$1),BF71/($D$1-1)*$D$1,BF71/(MONTH($BK$1)-MONTH(BK71))*(MONTH($BK$1)-MONTH(BK71)+1)),"-"),0) -> 0 | AL71: 0 | AM71: 0 | AN71: 100% | AO71: 0 | AP71: =IF(IF(F71="正常工资薪金",AC71-AD71-AE71-AF71-AG71-AH71-AI71-AJ71-AK71-AL71-AM71,G71-H71-I71)<0,0,IF(F71="正常工资薪金",AC71-AD71-AE71-AF71-AG71-AH71-AI71-AJ71-AK71-AL71-AM71,G71-H71-I71)) -> #N/A | AQ71: {=_xlfn.IFS(F71="正常工资薪金",VLOOKUP(AP71,{0,0.03;36000,0.1;144000,0.2;300000,0.25;420000,0.3;660000,0.35;960000,0.45},2,1),F71="一般劳务报酬所得",IF(AP71<=20000,0.2,IF(AP71<=50000,0.3,0.4)),F71="全年一次性奖金收入",VLOOKUP(AP71/12,{0,0.03;3000,0.1;12000,0.2;25000,0.25;35000,0.3;55000,0.35;80000,0.45},2,1),F71="解除劳动合同一次性补偿金",VLOOKUP(AP71,{0,0.03;36000,0.1;144000,0.2;300000,0.25;420000,0.3;660000,0.35;960000,0.45},2,1))} -> #N/A | AR71: {=_xlfn.IFS(F71="正常工资薪金",VLOOKUP(AP71,{0,0;36000,2520;144000,16920;300000,31920;420000,52920;660000,85920;960000,181920},2,1),F71="一般劳务报酬所得",IF(AP71<=20000,0,IF(AS<=50000,2000,7000)),F71="全年一次性奖金收入",VLOOKUP(AP71/12,{0,0;3000,210;12000,1410;25000,2660;35000,4410;55000,7160;80000,15160},2,1),F71="解除劳动合同一次性补偿金",VLOOKUP(AP71,{0,0;36000,2520;144000,16920;300000,31920;420000,52920;660000,85920;960000,181920},2,1))} -> #N/A | AS71: =AP71*AQ71-AR71 -> #N/A | AT71: 0 | AU71: =BI71+BJ71 -> 105.86 | AV71: =IF(AS71-AT71-AU71>0,AS71-AT71-AU71,0) -> #N/A | AX71: =IFERROR(IF(F71="正常工资薪金",VLOOKUP(D71&"*",个税上月累计情况!E:AL,26,0),0),0) -> 20998.57 | AY71: =IFERROR(IF(F71="正常工资薪金",VLOOKUP(D71&"*",个税上月累计情况!E:AL,27,0),0),0) -> 15000 | AZ71: =IFERROR(IF(F71="正常工资薪金",VLOOKUP(D71&"*",个税上月累计情况!E:AL,28,0),0),0) -> 2470.02 | BA71: =IFERROR(IF(F71="正常工资薪金",VLOOKUP(D71&"*",个税上月累计情况!E:AL,29,0),0),0) -> 0 | BB71: =IFERROR(IF(F71="正常工资薪金",VLOOKUP(D71&"*",个税上月累计情况!E:AL,30,0),0),0) -> 0 | BC71: =IFERROR(IF(F71="正常工资薪金",VLOOKUP(D71&"*",个税上月累计情况!E:AL,31,0),0),0) -> 0 | BD71: =IFERROR(IF(F71="正常工资薪金",VLOOKUP(D71&"*",个税上月累计情况!E:AL,32,0),0),0) -> 0 | BE71: =IFERROR(IF(F71="正常工资薪金",VLOOKUP(D71&"*",个税上月累计情况!E:AL,33,0),0),0) -> 0 | BF71: =IFERROR(IF(F71="正常工资薪金",VLOOKUP(D71&"*",个税上月累计情况!E:AL,34,0),0),0) -> 0 | BG71: =IFERROR(IF(F71="正常工资薪金",VLOOKUP(D71&"*",个税上月累计情况!E:AN,35,0),0),0) -> 0 | BH71: =IFERROR(IF(F71="正常工资薪金",VLOOKUP(D71&"*",个税上月累计情况!E:AN,36,0),0),0) -> 0 | BI71: =IFERROR(IF(F71="正常工资薪金",VLOOKUP(D71&"*",个税上月累计情况!D:AW,46,0),0),0) -> 4.91 | BJ71: =IFERROR(IF(F71="正常工资薪金",VLOOKUP(D71&"*",个税上月累计情况!D:AX,47,0),0),0) -> 100.95 | BK71: =VLOOKUP(B71,花名册!C:N,12,0) -> #N/A
... B78: 王丽花 | C78: 居民身份证 | D78: 350500197206142522 | E78: 否 | F78: 一般劳务报酬所得 | G78: {=_xlfn.IFS(F78="正常工资薪金",VLOOKUP(D78&"*",工资表明细!D:BL,61,0),F78="一般劳务报酬所得",VLOOKUP(D78&"*",工资表明细!D:BJ,59,0),F78="全年一次性奖金收入",VLOOKUP(D78&"*",工资表明细!D:BI,58,0),F78="解除劳动合同一次性补偿金",VLOOKUP(D78&"*",工资表明细!D:BH,57,0))} -> #N/A | H78: =IF(F78="一般劳务报酬所得",800,0) -> 800 | I78: 0 | J78: =IF(F78="正常工资薪金",5000,0) -> 0 | K78: =IF(F78="正常工资薪金",VLOOKUP(D78&"*",工资表明细!D:AP,39,0),0) -> 0 | L78: =IF(F78="正常工资薪金",VLOOKUP(D78&"*",工资表明细!D:AQ,40,0),0) -> 0 | M78: =IF(F78="正常工资薪金",VLOOKUP(D78&"*",工资表明细!D:AR,41,0),0) -> 0 | N78: =IF(F78="正常工资薪金",VLOOKUP(D78&"*",工资表明细!D:AT,43,0),0) -> 0 | O78: 73 | P78: 73 | Q78: 73 | R78: 73 | S78: 73 | T78: 73 | U78: 73 | V78: 73 | W78: - | X78: 73 | Y78: - | Z78: - | AA78: - | AB78: 73 | AC78: =IF(F78="正常工资薪金",G78+AX78,"-") -> - | AD78: =IF(F78="正常工资薪金",J78+AY78,"-") -> - | AE78: =IF(F78="正常工资薪金",K78+L78+M78+N78+AZ78,"-") -> - | AF78: =IFERROR(IF($F$5="正常工资薪金",IF(YEAR(BK78)<YEAR($BK$1),BA78/($D$1-1)*$D$1,BA78/DATEDIF(BK78,$BK$1,"M")*DATEDIF(BK78,$BK$1,"M")),"-"),0) -> 0 | AG78: =IFERROR(IF($F$5="正常工资薪金",IF(YEAR(BK78)<YEAR($BK$1),BB78/($D$1-1)*$D$1,BB78/DATEDIF(BK78,$BK$1,"M")*DATEDIF(BK78,$BK$1,"M")),"-"),0) -> 0 | AH78: =IFERROR(IF($F$5="正常工资薪金",IF(YEAR(BK78)<YEAR($BK$1),BC78/($D$1-1)*$D$1,BC78/(MONTH($BK$1)-MONTH(BK78))*(MONTH($BK$1)-MONTH(BK78)+1)),"-"),0) -> 0 | AI78: =IFERROR(IF($F$5="正常工资薪金",IF(YEAR(BK78)<YEAR($BK$1),BD78/($D$1-1)*$D$1,BD78/(MONTH($BK$1)-MONTH(BK78))*(MONTH($BK$1)-MONTH(BK78)+1)),"-"),0) -> 0 | AJ78: =IFERROR(IF($F$5="正常工资薪金",IF(YEAR(BK78)<YEAR($BK$1),BE78/($D$1-1)*$D$1,BE78/(MONTH($BK$1)-MONTH(BK78))*(MONTH($BK$1)-MONTH(BK78)+1)),"-"),0) -> 0 | AK78: =IFERROR(IF($F$5="正常工资薪金",IF(YEAR(BK78)<YEAR($BK$1),BF78/($D$1-1)*$D$1,BF78/(MONTH($BK$1)-MONTH(BK78))*(MONTH($BK$1)-MONTH(BK78)+1)),"-"),0) -> 0 | AL78: 0 | AM78: 0 | AN78: 100% | AO78: 0 | AP78: =IF(IF(F78="正常工资薪金",AC78-AD78-AE78-AF78-AG78-AH78-AI78-AJ78-AK78-AL78-AM78,G78-H78-I78)<0,0,IF(F78="正常工资薪金",AC78-AD78-AE78-AF78-AG78-AH78-AI78-AJ78-AK78-AL78-AM78,G78-H78-I78)) -> #N/A | AQ78: {=_xlfn.IFS(F78="正常工资薪金",VLOOKUP(AP78,{0,0.03;36000,0.1;144000,0.2;300000,0.25;420000,0.3;660000,0.35;960000,0.45},2,1),F78="一般劳务报酬所得",IF(AP78<=20000,0.2,IF(AP78<=50000,0.3,0.4)),F78="全年一次性奖金收入",VLOOKUP(AP78/12,{0,0.03;3000,0.1;12000,0.2;25000,0.25;35000,0.3;55000,0.35;80000,0.45},2,1),F78="解除劳动合同一次性补偿金",VLOOKUP(AP78,{0,0.03;36000,0.1;144000,0.2;300000,0.25;420000,0.3;660000,0.35;960000,0.45},2,1))} -> #N/A | AR78: {=_xlfn.IFS(F78="正常工资薪金",VLOOKUP(AP78,{0,0;36000,2520;144000,16920;300000,31920;420000,52920;660000,85920;960000,181920},2,1),F78="一般劳务报酬所得",IF(AP78<=20000,0,IF(AS<=50000,2000,7000)),F78="全年一次性奖金收入",VLOOKUP(AP78/12,{0,0;3000,210;12000,1410;25000,2660;35000,4410;55000,7160;80000,15160},2,1),F78="解除劳动合同一次性补偿金",VLOOKUP(AP78,{0,0;36000,2520;144000,16920;300000,31920;420000,52920;660000,85920;960000,181920},2,1))} -> #N/A | AS78: =AP78*AQ78-AR78 -> #N/A | AT78: 0 | AU78: =BI78+BJ78 -> 0 | AV78: =IF(AS78-AT78-AU78>0,AS78-AT78-AU78,0) -> #N/A | AX78: =IFERROR(IF(F78="正常工资薪金",VLOOKUP(D78&"*",个税上月累计情况!E:AL,26,0),0),0) -> 0 | AY78: =IFERROR(IF(F78="正常工资薪金",VLOOKUP(D78&"*",个税上月累计情况!E:AL,27,0),0),0) -> 0 | AZ78: =IFERROR(IF(F78="正常工资薪金",VLOOKUP(D78&"*",个税上月累计情况!E:AL,28,0),0),0) -> 0 | BA78: =IFERROR(IF(F78="正常工资薪金",VLOOKUP(D78&"*",个税上月累计情况!E:AL,29,0),0),0) -> 0 | BB78: =IFERROR(IF(F78="正常工资薪金",VLOOKUP(D78&"*",个税上月累计情况!E:AL,30,0),0),0) -> 0 | BC78: =IFERROR(IF(F78="正常工资薪金",VLOOKUP(D78&"*",个税上月累计情况!E:AL,31,0),0),0) -> 0 | BD78: =IFERROR(IF(F78="正常工资薪金",VLOOKUP(D78&"*",个税上月累计情况!E:AL,32,0),0),0) -> 0 | BE78: =IFERROR(IF(F78="正常工资薪金",VLOOKUP(D78&"*",个税上月累计情况!E:AL,33,0),0),0) -> 0 | BF78: =IFERROR(IF(F78="正常工资薪金",VLOOKUP(D78&"*",个税上月累计情况!E:AL,34,0),0),0) -> 0 | BG78: =IFERROR(IF(F78="正常工资薪金",VLOOKUP(D78&"*",个税上月累计情况!E:AN,35,0),0),0) -> 0 | BH78: =IFERROR(IF(F78="正常工资薪金",VLOOKUP(D78&"*",个税上月累计情况!E:AN,36,0),0),0) -> 0 | BI78: =IFERROR(IF(F78="正常工资薪金",VLOOKUP(D78&"*",个税上月累计情况!D:AW,46,0),0),0) -> 0 | BJ78: =IFERROR(IF(F78="正常工资薪金",VLOOKUP(D78&"*",个税上月累计情况!D:AX,47,0),0),0) -> 0 | BK78: =VLOOKUP(B78,花名册!C:N,12,0) -> #N/A

Sheet 研发工时表
A1: 主体 | B1: 类型 | C1: 项目名称 | D1: 完成月份 | E1: 项目参与人员 | F1: 月工作日总天数 （天） | G1: 月工作总工时 （按8小时/天） | H1: 工时单价 （元） | I1: 项目投入工时 （小时） | J1: 项目人员经费合计 | K1: 项目工时占比 （%） | L1: 一级部门 | M1: 二级部门 | N1: 三级部门 | O1: 大数据挖掘工时 | P1: 大数据挖掘人力成本 | Q1: 其他人力成本
A2: 杭州 | E2: 耿德强 | F2: =VLOOKUP(E2,工资表明细!C:AF,30,0) -> #N/A | G2: =F2*8 -> #N/A | H2: =ROUND(J2/G2,2) -> #N/A | J2: =VLOOKUP(E2,工资表明细!C:BF,56,0) -> #N/A | L2: =VLOOKUP(E2,工资表明细!C:J,6,0) -> #N/A | M2: =VLOOKUP(E2,工资表明细!C:J,7,0) -> #N/A | N2: =VLOOKUP(E2,工资表明细!C:J,8,0) -> #N/A | P2: =O2*H2 -> #N/A | Q2: =J2-P2 -> #N/A
A3: 北分 | E3: 牛飞芸 | F3: =VLOOKUP(E3,工资表明细!C:AF,30,0) -> #N/A | G3: =F3*8 -> #N/A | H3: =ROUND(J3/G3,2) -> #N/A | J3: =VLOOKUP(E3,工资表明细!C:BF,56,0) -> #N/A | L3: =VLOOKUP(E3,工资表明细!C:J,6,0) -> #N/A | M3: =VLOOKUP(E3,工资表明细!C:J,7,0) -> #N/A | N3: =VLOOKUP(E3,工资表明细!C:J,8,0) -> #N/A | P3: =O3*H3 -> #N/A | Q3: =J3-P3 -> #N/A
A4: 杭州 | E4: 刘洋 | F4: =VLOOKUP(E4,工资表明细!C:AF,30,0) -> #N/A | G4: =F4*8 -> #N/A | H4: =ROUND(J4/G4,2) -> #N/A | J4: =VLOOKUP(E4,工资表明细!C:BF,56,0) -> #N/A | L4: =VLOOKUP(E4,工资表明细!C:J,6,0) -> #N/A | M4: =VLOOKUP(E4,工资表明细!C:J,7,0) -> #N/A | N4: =VLOOKUP(E4,工资表明细!C:J,8,0) -> #N/A | P4: =O4*H4 -> #N/A | Q4: =J4-P4 -> #N/A
A5: 北分 | E5: 杨娟 | F5: =VLOOKUP(E5,工资表明细!C:AF,30,0) -> #N/A | G5: =F5*8 -> #N/A | H5: =ROUND(J5/G5,2) -> #N/A | J5: =VLOOKUP(E5,工资表明细!C:BF,56,0) -> #N/A | L5: =VLOOKUP(E5,工资表明细!C:J,6,0) -> #N/A | M5: =VLOOKUP(E5,工资表明细!C:J,7,0) -> #N/A | N5: =VLOOKUP(E5,工资表明细!C:J,8,0) -> #N/A | P5: =O5*H5 -> #N/A | Q5: =J5-P5 -> #N/A
A6: 北分 | E6: 杨金雪 | F6: =VLOOKUP(E6,工资表明细!C:AF,30,0) -> #N/A | G6: =F6*8 -> #N/A | H6: =ROUND(J6/G6,2) -> #N/A | J6: =VLOOKUP(E6,工资表明细!C:BF,56,0) -> #N/A | L6: =VLOOKUP(E6,工资表明细!C:J,6,0) -> #N/A | M6: =VLOOKUP(E6,工资表明细!C:J,7,0) -> #N/A | N6: =VLOOKUP(E6,工资表明细!C:J,8,0) -> #N/A | P6: =O6*H6 -> #N/A | Q6: =J6-P6 -> #N/A
A7: 杭州 | E7: 马顺华 | F7: =VLOOKUP(E7,工资表明细!C:AF,30,0) -> #N/A | G7: =F7*8 -> #N/A | H7: =ROUND(J7/G7,2) -> #N/A | J7: =VLOOKUP(E7,工资表明细!C:BF,56,0) -> #N/A | L7: =VLOOKUP(E7,工资表明细!C:J,6,0) -> #N/A | M7: =VLOOKUP(E7,工资表明细!C:J,7,0) -> #N/A | N7: =VLOOKUP(E7,工资表明细!C:J,8,0) -> #N/A | P7: =O7*H7 -> #N/A | Q7: =J7-P7 -> #N/A
A8: 杭州 | E8: 耿惠欣 | F8: =VLOOKUP(E8,工资表明细!C:AF,30,0) -> #N/A | G8: =F8*8 -> #N/A | H8: =ROUND(J8/G8,2) -> #N/A | J8: =VLOOKUP(E8,工资表明细!C:BF,56,0) -> #N/A | L8: =VLOOKUP(E8,工资表明细!C:J,6,0) -> #N/A | M8: =VLOOKUP(E8,工资表明细!C:J,7,0) -> #N/A | N8: =VLOOKUP(E8,工资表明细!C:J,8,0) -> #N/A | P8: =O8*H8 -> #N/A | Q8: =J8-P8 -> #N/A
A9: 武汉 | E9: 王鹏辉 | F9: =VLOOKUP(E9,工资表明细!C:AF,30,0) -> #N/A | G9: =F9*8 -> #N/A | H9: =ROUND(J9/G9,2) -> #N/A | J9: =VLOOKUP(E9,工资表明细!C:BF,56,0) -> #N/A | L9: =VLOOKUP(E9,工资表明细!C:J,6,0) -> #N/A | M9: =VLOOKUP(E9,工资表明细!C:J,7,0) -> #N/A | N9: =VLOOKUP(E9,工资表明细!C:J,8,0) -> #N/A | P9: =O9*H9 -> #N/A | Q9: =J9-P9 -> #N/A
A10: 北分 | E10: 郭子轶 | F10: =VLOOKUP(E10,工资表明细!C:AF,30,0) -> #N/A | G10: =F10*8 -> #N/A | H10: =ROUND(J10/G10,2) -> #N/A | J10: =VLOOKUP(E10,工资表明细!C:BF,56,0) -> #N/A | L10: =VLOOKUP(E10,工资表明细!C:J,6,0) -> #N/A | M10: =VLOOKUP(E10,工资表明细!C:J,7,0) -> #N/A | N10: =VLOOKUP(E10,工资表明细!C:J,8,0) -> #N/A | P10: =O10*H10 -> #N/A | Q10: =J10-P10 -> #N/A
A11: 北分 | E11: 陈昱光 | F11: =VLOOKUP(E11,工资表明细!C:AF,30,0) -> #N/A | G11: =F11*8 -> #N/A | H11: =ROUND(J11/G11,2) -> #N/A | J11: =VLOOKUP(E11,工资表明细!C:BF,56,0) -> #N/A | L11: =VLOOKUP(E11,工资表明细!C:J,6,0) -> #N/A | M11: =VLOOKUP(E11,工资表明细!C:J,7,0) -> #N/A | N11: =VLOOKUP(E11,工资表明细!C:J,8,0) -> #N/A | P11: =O11*H11 -> #N/A | Q11: =J11-P11 -> #N/A
A12: 北分 | E12: 姜文超 | F12: =VLOOKUP(E12,工资表明细!C:AF,30,0) -> #N/A | G12: =F12*8 -> #N/A | H12: =ROUND(J12/G12,2) -> #N/A | J12: =VLOOKUP(E12,工资表明细!C:BF,56,0) -> #N/A | L12: =VLOOKUP(E12,工资表明细!C:J,6,0) -> #N/A | M12: =VLOOKUP(E12,工资表明细!C:J,7,0) -> #N/A | N12: =VLOOKUP(E12,工资表明细!C:J,8,0) -> #N/A | P12: =O12*H12 -> #N/A | Q12: =J12-P12 -> #N/A
A13: 北分 | E13: 周海明 | F13: =VLOOKUP(E13,工资表明细!C:AF,30,0) -> #N/A | G13: =F13*8 -> #N/A | H13: =ROUND(J13/G13,2) -> #N/A | J13: =VLOOKUP(E13,工资表明细!C:BF,56,0) -> #N/A | L13: =VLOOKUP(E13,工资表明细!C:J,6,0) -> #N/A | M13: =VLOOKUP(E13,工资表明细!C:J,7,0) -> #N/A | N13: =VLOOKUP(E13,工资表明细!C:J,8,0) -> #N/A | P13: =O13*H13 -> #N/A | Q13: =J13-P13 -> #N/A
... A32: 北分 | E32: 彭勇 | F32: =VLOOKUP(E32,工资表明细!C:AF,30,0) -> #N/A | G32: =F32*8 -> #N/A | H32: =ROUND(J32/G32,2) -> #N/A | J32: =VLOOKUP(E32,工资表明细!C:BF,56,0) -> #N/A | L32: =VLOOKUP(E32,工资表明细!C:J,6,0) -> #N/A | M32: =VLOOKUP(E32,工资表明细!C:J,7,0) -> #N/A | N32: =VLOOKUP(E32,工资表明细!C:J,8,0) -> #N/A | P32: =O32*H32 -> #N/A | Q32: =J32-P32 -> #N/A
A33: 北分 | E33: 温丽敏 | F33: =VLOOKUP(E33,工资表明细!C:AF,30,0) -> #N/A | G33: =F33*8 -> #N/A | H33: =ROUND(J33/G33,2) -> #N/A | J33: =VLOOKUP(E33,工资表明细!C:BF,56,0) -> #N/A | L33: =VLOOKUP(E33,工资表明细!C:J,6,0) -> #N/A | M33: =VLOOKUP(E33,工资表明细!C:J,7,0) -> #N/A | N33: =VLOOKUP(E33,工资表明细!C:J,8,0) -> #N/A | O33: =2*8 -> 16 | P33: =O33*H33 -> #N/A | Q33: =J33-P33 -> #N/A
A34: 杭州 | E34: 唐艳景 | F34: =VLOOKUP(E34,工资表明细!C:AF,30,0) -> #N/A | G34: =F34*8 -> #N/A | H34: =ROUND(J34/G34,2) -> #N/A | J34: =VLOOKUP(E34,工资表明细!C:BF,56,0) -> #N/A | L34: =VLOOKUP(E34,工资表明细!C:J,6,0) -> #N/A | M34: =VLOOKUP(E34,工资表明细!C:J,7,0) -> #N/A | N34: =VLOOKUP(E34,工资表明细!C:J,8,0) -> #N/A | P34: =O34*H34 -> #N/A | Q34: =J34-P34 -> #N/A
A35: 北分 | E35: 朱瑞丽 | F35: =VLOOKUP(E35,工资表明细!C:AF,30,0) -> #N/A | G35: =F35*8 -> #N/A | H35: =ROUND(J35/G35,2) -> #N/A | J35: =VLOOKUP(E35,工资表明细!C:BF,56,0) -> #N/A | L35: =VLOOKUP(E35,工资表明细!C:J,6,0) -> #N/A | M35: =VLOOKUP(E35,工资表明细!C:J,7,0) -> #N/A | N35: =VLOOKUP(E35,工资表明细!C:J,8,0) -> #N/A | O35: =4.5*8 -> 36 | P35: =O35*H35 -> #N/A | Q35: =J35-P35 -> #N/A
A36: 杭州 | E36: 陈楚冰 | F36: =VLOOKUP(E36,工资表明细!C:AF,30,0) -> #N/A | G36: =F36*8 -> #N/A | H36: =ROUND(J36/G36,2) -> #N/A | J36: =VLOOKUP(E36,工资表明细!C:BF,56,0) -> #N/A | L36: =VLOOKUP(E36,工资表明细!C:J,6,0) -> #N/A | M36: =VLOOKUP(E36,工资表明细!C:J,7,0) -> #N/A | N36: =VLOOKUP(E36,工资表明细!C:J,8,0) -> #N/A | P36: =O36*H36 -> #N/A | Q36: =J36-P36 -> #N/A
A37: 深圳 | E37: 陈丽娟 | F37: =VLOOKUP(E37,工资表明细!C:AF,30,0) -> #N/A | G37: =F37*8 -> #N/A | H37: =ROUND(J37/G37,2) -> #N/A | J37: =VLOOKUP(E37,工资表明细!C:BF,56,0) -> #N/A | L37: =VLOOKUP(E37,工资表明细!C:J,6,0) -> #N/A | M37: =VLOOKUP(E37,工资表明细!C:J,7,0) -> #N/A | N37: =VLOOKUP(E37,工资表明细!C:J,8,0) -> #N/A | P37: =O37*H37 -> #N/A | Q37: =J37-P37 -> #N/A
A38: 成都 | E38: 陈泓佳 | F38: =VLOOKUP(E38,工资表明细!C:AF,30,0) -> #N/A | G38: =F38*8 -> #N/A | H38: =ROUND(J38/G38,2) -> #N/A | J38: =VLOOKUP(E38,工资表明细!C:BF,56,0) -> #N/A | L38: =VLOOKUP(E38,工资表明细!C:J,6,0) -> #N/A | M38: =VLOOKUP(E38,工资表明细!C:J,7,0) -> #N/A | N38: =VLOOKUP(E38,工资表明细!C:J,8,0) -> #N/A | P38: =O38*H38 -> #N/A | Q38: =J38-P38 -> #N/A
A39: 深圳 | E39: 宁源双 | F39: =VLOOKUP(E39,工资表明细!C:AF,30,0) -> #N/A | G39: =F39*8 -> #N/A | H39: =ROUND(J39/G39,2) -> #N/A | J39: =VLOOKUP(E39,工资表明细!C:BF,56,0) -> #N/A | L39: =VLOOKUP(E39,工资表明细!C:J,6,0) -> #N/A | M39: =VLOOKUP(E39,工资表明细!C:J,7,0) -> #N/A | N39: =VLOOKUP(E39,工资表明细!C:J,8,0) -> #N/A | P39: =O39*H39 -> #N/A | Q39: =J39-P39 -> #N/A
A40: 北分 | E40: 陈思坪 | F40: =VLOOKUP(E40,工资表明细!C:AF,30,0) -> #N/A | G40: =F40*8 -> #N/A | H40: =ROUND(J40/G40,2) -> #N/A | J40: =VLOOKUP(E40,工资表明细!C:BF,56,0) -> #N/A | L40: =VLOOKUP(E40,工资表明细!C:J,6,0) -> #N/A | M40: =VLOOKUP(E40,工资表明细!C:J,7,0) -> #N/A | N40: =VLOOKUP(E40,工资表明细!C:J,8,0) -> #N/A | P40: =O40*H40 -> #N/A | Q40: =J40-P40 -> #N/A
A41: 北分 | E41: 夏昕 | F41: =VLOOKUP(E41,工资表明细!C:AF,30,0) -> #N/A | G41: =F41*8 -> #N/A | H41: =ROUND(J41/G41,2) -> #N/A | J41: =VLOOKUP(E41,工资表明细!C:BF,56,0) -> #N/A | L41: =VLOOKUP(E41,工资表明细!C:J,6,0) -> #N/A | M41: =VLOOKUP(E41,工资表明细!C:J,7,0) -> #N/A | N41: =VLOOKUP(E41,工资表明细!C:J,8,0) -> #N/A | P41: =O41*H41 -> #N/A | Q41: =J41-P41 -> #N/A
A42: 北分 | E42: 刘柏良 | F42: =VLOOKUP(E42,工资表明细!C:AF,30,0) -> #N/A | G42: =F42*8 -> #N/A | H42: =ROUND(J42/G42,2) -> #N/A | J42: =VLOOKUP(E42,工资表明细!C:BF,56,0) -> #N/A | L42: =VLOOKUP(E42,工资表明细!C:J,6,0) -> #N/A | M42: =VLOOKUP(E42,工资表明细!C:J,7,0) -> #N/A | N42: =VLOOKUP(E42,工资表明细!C:J,8,0) -> #N/A | O42: =0.5*8 -> 4 | P42: =O42*H42 -> #N/A | Q42: =J42-P42 -> #N/A
A43: 北分 | E43: 靳长明 | F43: =VLOOKUP(E43,工资表明细!C:AF,30,0) -> #N/A | G43: =F43*8 -> #N/A | H43: =ROUND(J43/G43,2) -> #N/A | J43: =VLOOKUP(E43,工资表明细!C:BF,56,0) -> #N/A | L43: =VLOOKUP(E43,工资表明细!C:J,6,0) -> #N/A | M43: =VLOOKUP(E43,工资表明细!C:J,7,0) -> #N/A | N43: =VLOOKUP(E43,工资表明细!C:J,8,0) -> #N/A | P43: =O43*H43 -> #N/A | Q43: =J43-P43 -> #N/A
A44: 北分 | E44: 窦晴 | F44: =VLOOKUP(E44,工资表明细!C:AF,30,0) -> #N/A | G44: =F44*8 -> #N/A | H44: =ROUND(J44/G44,2) -> #N/A | J44: =VLOOKUP(E44,工资表明细!C:BF,56,0) -> #N/A | L44: =VLOOKUP(E44,工资表明细!C:J,6,0) -> #N/A | M44: =VLOOKUP(E44,工资表明细!C:J,7,0) -> #N/A | N44: =VLOOKUP(E44,工资表明细!C:J,8,0) -> #N/A | P44: =O44*H44 -> #N/A | Q44: =J44-P44 -> #N/A
A45: 北分 | E45: 曹爱华 | F45: =VLOOKUP(E45,工资表明细!C:AF,30,0) -> #N/A | G45: =F45*8 -> #N/A | H45: =ROUND(J45/G45,2) -> #N/A | J45: =VLOOKUP(E45,工资表明细!C:BF,56,0) -> #N/A | L45: =VLOOKUP(E45,工资表明细!C:J,6,0) -> #N/A | M45: =VLOOKUP(E45,工资表明细!C:J,7,0) -> #N/A | N45: =VLOOKUP(E45,工资表明细!C:J,8,0) -> #N/A | P45: =O45*H45 -> #N/A | Q45: =J45-P45 -> #N/A
A46: 北分 | E46: 吴松遥 | F46: =VLOOKUP(E46,工资表明细!C:AF,30,0) -> #N/A | G46: =F46*8 -> #N/A | H46: =ROUND(J46/G46,2) -> #N/A | J46: =VLOOKUP(E46,工资表明细!C:BF,56,0) -> #N/A | L46: =VLOOKUP(E46,工资表明细!C:J,6,0) -> #N/A | M46: =VLOOKUP(E46,工资表明细!C:J,7,0) -> #N/A | N46: =VLOOKUP(E46,工资表明细!C:J,8,0) -> #N/A | P46: =O46*H46 -> #N/A | Q46: =J46-P46 -> #N/A
A47: 北分 | E47: 张泽祥 | F47: =VLOOKUP(E47,工资表明细!C:AF,30,0) -> #N/A | G47: =F47*8 -> #N/A | H47: =ROUND(J47/G47,2) -> #N/A | J47: =VLOOKUP(E47,工资表明细!C:BF,56,0) -> #N/A | L47: =VLOOKUP(E47,工资表明细!C:J,6,0) -> #N/A | M47: =VLOOKUP(E47,工资表明细!C:J,7,0) -> #N/A | N47: =VLOOKUP(E47,工资表明细!C:J,8,0) -> #N/A | P47: =O47*H47 -> #N/A | Q47: =J47-P47 -> #N/A
A48: 杭州 | E48: 来桑桑 | F48: =VLOOKUP(E48,工资表明细!C:AF,30,0) -> #N/A | G48: =F48*8 -> #N/A | H48: =ROUND(J48/G48,2) -> #N/A | J48: =VLOOKUP(E48,工资表明细!C:BF,56,0) -> #N/A | L48: =VLOOKUP(E48,工资表明细!C:J,6,0) -> #N/A | M48: =VLOOKUP(E48,工资表明细!C:J,7,0) -> #N/A | N48: =VLOOKUP(E48,工资表明细!C:J,8,0) -> #N/A | P48: =O48*H48 -> #N/A | Q48: =J48-P48 -> #N/A
A49: 北分 | E49: 董向毫 | F49: =VLOOKUP(E49,工资表明细!C:AF,30,0) -> #N/A | G49: =F49*8 -> #N/A | H49: =ROUND(J49/G49,2) -> #N/A | J49: =VLOOKUP(E49,工资表明细!C:BF,56,0) -> #N/A | L49: =VLOOKUP(E49,工资表明细!C:J,6,0) -> #N/A | M49: =VLOOKUP(E49,工资表明细!C:J,7,0) -> #N/A | N49: =VLOOKUP(E49,工资表明细!C:J,8,0) -> #N/A | P49: =O49*H49 -> #N/A | Q49: =J49-P49 -> #N/A
A50: 杭州 | E50: 王雨佳 | F50: =VLOOKUP(E50,工资表明细!C:AF,30,0) -> #N/A | G50: =F50*8 -> #N/A | H50: =ROUND(J50/G50,2) -> #N/A | J50: =VLOOKUP(E50,工资表明细!C:BF,56,0) -> #N/A | L50: =VLOOKUP(E50,工资表明细!C:J,6,0) -> #N/A | M50: =VLOOKUP(E50,工资表明细!C:J,7,0) -> #N/A | N50: =VLOOKUP(E50,工资表明细!C:J,8,0) -> #N/A | P50: =O50*H50 -> #N/A | Q50: =J50-P50 -> #N/A
A51: 北分 | E51: 闵梦妮 | F51: =VLOOKUP(E51,工资表明细!C:AF,30,0) -> #N/A | G51: =F51*8 -> #N/A | H51: =ROUND(J51/G51,2) -> #N/A | J51: =VLOOKUP(E51,工资表明细!C:BF,56,0) -> #N/A | L51: =VLOOKUP(E51,工资表明细!C:J,6,0) -> #N/A | M51: =VLOOKUP(E51,工资表明细!C:J,7,0) -> #N/A | N51: =VLOOKUP(E51,工资表明细!C:J,8,0) -> #N/A | P51: =O51*H51 -> #N/A | Q51: =J51-P51 -> #N/A
A52: 北分 | E52: 刘鹏 | F52: =VLOOKUP(E52,工资表明细!C:AF,30,0) -> #N/A | G52: =F52*8 -> #N/A | H52: =ROUND(J52/G52,2) -> #N/A | J52: =VLOOKUP(E52,工资表明细!C:BF,56,0) -> #N/A | L52: =VLOOKUP(E52,工资表明细!C:J,6,0) -> #N/A | M52: =VLOOKUP(E52,工资表明细!C:J,7,0) -> #N/A | N52: =VLOOKUP(E52,工资表明细!C:J,8,0) -> #N/A | P52: =O52*H52 -> #N/A | Q52: =J52-P52 -> #N/A
A53: 北分 | E53: 何鑫 | F53: =VLOOKUP(E53,工资表明细!C:AF,30,0) -> #N/A | G53: =F53*8 -> #N/A | H53: =ROUND(J53/G53,2) -> #N/A | J53: =VLOOKUP(E53,工资表明细!C:BF,56,0) -> #N/A | L53: =VLOOKUP(E53,工资表明细!C:J,6,0) -> #N/A | M53: =VLOOKUP(E53,工资表明细!C:J,7,0) -> #N/A | N53: =VLOOKUP(E53,工资表明细!C:J,8,0) -> #N/A | P53: =O53*H53 -> #N/A | Q53: =J53-P53 -> #N/A
A54: 北分 | E54: 陈鑫鑫 | F54: =VLOOKUP(E54,工资表明细!C:AF,30,0) -> #N/A | G54: =F54*8 -> #N/A | H54: =ROUND(J54/G54,2) -> #N/A | J54: =VLOOKUP(E54,工资表明细!C:BF,56,0) -> #N/A | L54: =VLOOKUP(E54,工资表明细!C:J,6,0) -> #N/A | M54: =VLOOKUP(E54,工资表明细!C:J,7,0) -> #N/A | N54: =VLOOKUP(E54,工资表明细!C:J,8,0) -> #N/A | P54: =O54*H54 -> #N/A | Q54: =J54-P54 -> #N/A
... A75: 杭州 | E75: 王丽花 | F75: =VLOOKUP(E75,工资表明细!C:AF,30,0) -> #N/A | G75: =F75*8 -> #N/A | H75: =ROUND(J75/G75,2) -> #N/A | J75: =VLOOKUP(E75,工资表明细!C:BF,56,0) -> #N/A | L75: =VLOOKUP(E75,工资表明细!C:J,6,0) -> #N/A | M75: =VLOOKUP(E75,工资表明细!C:J,7,0) -> #N/A | N75: =VLOOKUP(E75,工资表明细!C:J,8,0) -> #N/A | P75: =O75*H75 -> #N/A | Q75: =J75-P75 -> #N/A

Sheet 个税上月累计情况
A1: 序号 | B1: 姓名 | C1: 身份证件类型 | D1: 身份证件号码 | E1: 纳税人识别号 | F1: 是否为非居民个人 | G1: 所得项目 | H1: 本月（次）情况 | AD1: 累计情况 | AO1: 减按计税比例 | AP1: 准予扣除的捐赠额 | AQ1: 税款计算 | AY1: 备注
H2: 收入额计算 | K2: 减除费用 | L2: 专项扣除 | P2: 其他扣除 | AD2: 累计收入额 | AE2: 累计减除费用 | AF2: 累计专项扣除 | AG2: 累计专项附加扣除 | AM2: 累计个人养老金 | AN2: 累计其他扣除 | AQ2: 应纳税所得额 | AR2: 税率/预扣率 | AS2: 速算扣除数 | AT2: 应纳税额 | AU2: 减免税额 | AV2: 协定减免 | AW2: 已缴税额 | AX2: 应补/退税额
H3: 收入 | I3: 费用 | J3: 免税收入 | L3: 基本养老保险费 | M3: 基本医疗保险费 | N3: 失业保险费 | O3: 住房公积金 | P3: 年金 | Q3: 商业健康保险 | R3: 税延养老保险 | S3: 财产原值 | T3: 允许扣除的税费 | U3: 公务交通费用 | V3: 通讯费用 | W3: 律师办案费用 | X3: 展业成本 | Y3: 西藏附加减除费用 | Z3: 修缮费用 | AA3: 有关合理费用 | AB3: 向出租方支付的租金 | AC3: 其他 | AG3: 子女教育 | AH3: 赡养老人 | AI3: 住房贷款利息 | AJ3: 住房租金 | AK3: 继续教育 | AL3: 3岁以下婴幼儿照护
A4: 1 | B4: 2 | C4: 3 | D4: 4 | E4: 5 | F4: 6 | G4: 7 | H4: 8 | I4: 9 | J4: 10 | K4: 11 | L4: 12 | M4: 13 | N4: 14 | O4: 15 | P4: 16 | Q4: 17 | R4: 18 | S4: 19 | T4: 20 | U4: 21 | V4: 22 | W4: 23 | X4: 24 | Y4: 25 | Z4: 26 | AA4: 27 | AB4: 28 | AC4: 29 | AD4: 30 | AE4: 31 | AF4: 32 | AG4: 33 | AH4: 34 | AI4: 35 | AJ4: 36 | AK4: 37 | AL4: 38 | AM4: 39 | AN4: 40 | AO4: 41 | AP4: 42 | AQ4: 43 | AR4: 44 | AS4: 45 | AT4: 46 | AU4: 47 | AV4: 48 | AW4: 49 | AX4: 50 | AY4: 51
A5: 1 | B5: 姜文肖 | C5: 居民身份证 | D5: 410922199312131347 | E5: 410922199312131347 | F5: 否 | G5: 正常工资薪金 | H5: 6300 | I5: 0 | J5: 0 | K5: 5000 | L5: 572.96 | M5: 146.24 | N5: 35.81 | O5: 315 | P5: 0 | Q5: 0 | R5: 0 | S5: 0 | T5: 0 | U5: 0 | V5: 0 | W5: 0 | X5: - | Y5: 0 | Z5: - | AA5: - | AB5: - | AC5: 0 | AD5: 44469.82 | AE5: 35000 | AF5: 7490.07 | AG5: 0 | AH5: 0 | AI5: 0 | AJ5: 0 | AK5: 0 | AL5: 0 | AM5: 0 | AN5: 0 | AO5: 100% | AP5: 0 | AQ5: 1979.75 | AR5: 0.03 | AS5: 0 | AT5: 59.39 | AU5: 0 | AV5: 0 | AW5: 52.49 | AX5: 6.9
A6: 2 | B6: 刘海星 | C6: 居民身份证 | D6: 130724198912104414 | E6: 130724198912104414 | F6: 否 | G6: 正常工资薪金 | H6: 15200 | I6: 0 | J6: 0 | K6: 5000 | L6: 572.96 | M6: 146.24 | N6: 35.81 | O6: 760 | P6: 0 | Q6: 0 | R6: 0 | S6: 0 | T6: 0 | U6: 0 | V6: 0 | W6: 0 | X6: - | Y6: 0 | Z6: - | AA6: - | AB6: - | AC6: 0 | AD6: 106163.86 | AE6: 35000 | AF6: 10605.07 | AG6: 0 | AH6: 0 | AI6: 0 | AJ6: 0 | AK6: 0 | AL6: 0 | AM6: 0 | AN6: 0 | AO6: 100% | AP6: 0 | AQ6: 60558.79 | AR6: 0.1 | AS6: 2520 | AT6: 3535.88 | AU6: 0 | AV6: 0 | AW6: 2667.38 | AX6: 868.5
A7: 3 | B7: 周海明 | C7: 居民身份证 | D7: 130427198606116938 | E7: 130427198606116938 | F7: 否 | G7: 正常工资薪金 | H7: 14374.29 | I7: 0 | J7: 0 | K7: 5000 | L7: 572.96 | M7: 146.24 | N7: 35.81 | O7: 900 | P7: 0 | Q7: 0 | R7: 0 | S7: 0 | T7: 0 | U7: 0 | V7: 0 | W7: 0 | X7: - | Y7: 0 | Z7: - | AA7: - | AB7: - | AC7: 0 | AD7: 100605.4 | AE7: 35000 | AF7: 11585.07 | AG7: 0 | AH7: 0 | AI7: 0 | AJ7: 10500 | AK7: 0 | AL7: 0 | AM7: 0 | AN7: 0 | AO7: 100% | AP7: 0 | AQ7: 43520.33 | AR7: 0.1 | AS7: 2520 | AT7: 1832.03 | AU7: 0 | AV7: 0 | AW7: 2110.11 | AX7: 0
A8: 4 | B8: 闵梦妮 | C8: 居民身份证 | D8: 411521199904044629 | E8: 411521199904044629 | F8: 否 | G8: 正常工资薪金 | H8: 8495.45 | I8: 0 | J8: 0 | K8: 5000 | L8: 572.96 | M8: 146.24 | N8: 35.81 | O8: 127 | P8: 0 | Q8: 0 | R8: 0 | S8: 0 | T8: 0 | U8: 0 | V8: 0 | W8: 0 | X8: - | Y8: 0 | Z8: - | AA8: - | AB8: - | AC8: 0 | AD8: 33897.03 | AE8: 25000 | AF8: 4410.05 | AG8: 0 | AH8: 0 | AI8: 0 | AJ8: 0 | AK8: 0 | AL8: 0 | AM8: 0 | AN8: 0 | AO8: 100% | AP8: 0 | AQ8: 4486.98 | AR8: 0.03 | AS8: 0 | AT8: 134.61 | AU8: 0 | AV8: 0 | AW8: 56.21 | AX8: 78.4
A9: 5 | B9: 牛飞芸 | C9: 居民身份证 | D9: 620402199105092732 | E9: 620402199105092732 | F9: 否 | G9: 正常工资薪金 | H9: 15882.12 | I9: 0 | J9: 0 | K9: 5000 | L9: 572.96 | M9: 146.24 | N9: 35.81 | O9: 1079 | P9: 0 | Q9: 0 | R9: 0 | S9: 0 | T9: 0 | U9: 0 | V9: 0 | W9: 0 | X9: - | Y9: 0 | Z9: - | AA9: - | AB9: - | AC9: 0 | AD9: 109505.3 | AE9: 35000 | AF9: 12838.07 | AG9: 0 | AH9: 0 | AI9: 0 | AJ9: 10500 | AK9: 0 | AL9: 0 | AM9: 0 | AN9: 0 | AO9: 100% | AP9: 0 | AQ9: 51167.23 | AR9: 0.1 | AS9: 2520 | AT9: 2596.72 | AU9: 0 | AV9: 0 | AW9: 1841.91 | AX9: 754.81
A10: 6 | B10: 陈洁 | C10: 居民身份证 | D10: 110106199508180621 | E10: 110106199508180621 | F10: 否 | G10: 正常工资薪金 | H10: 16000 | I10: 0 | J10: 0 | K10: 5000 | L10: 572.96 | M10: 146.24 | N10: 35.81 | O10: 1000 | P10: 0 | Q10: 0 | R10: 0 | S10: 0 | T10: 0 | U10: 0 | V10: 0 | W10: 0 | X10: - | Y10: 0 | Z10: - | AA10: - | AB10: - | AC10: 0 | AD10: 111843.38 | AE10: 35000 | AF10: 12285.07 | AG10: 0 | AH10: 0 | AI10: 0 | AJ10: 0 | AK10: 0 | AL10: 0 | AM10: 0 | AN10: 0 | AO10: 100% | AP10: 0 | AQ10: 64558.31 | AR10: 0.1 | AS10: 2520 | AT10: 3935.83 | AU10: 0 | AV10: 0 | AW10: 3011.33 | AX10: 924.5
A11: 7 | B11: 李一蒙 | C11: 居民身份证 | D11: 372928200010010016 | E11: 372928200010010016 | F11: 否 | G11: 正常工资薪金 | H11: 13570 | I11: 0 | J11: 0 | K11: 5000 | L11: 572.96 | M11: 146.24 | N11: 35.81 | O11: 680 | P11: 0 | Q11: 0 | R11: 0 | S11: 0 | T11: 0 | U11: 0 | V11: 0 | W11: 0 | X11: - | Y11: 0 | Z11: - | AA11: - | AB11: - | AC11: 0 | AD11: 38179.52 | AE11: 15000 | AF11: 4305.03 | AG11: 0 | AH11: 0 | AI11: 0 | AJ11: 0 | AK11: 0 | AL11: 0 | AM11: 0 | AN11: 0 | AO11: 100% | AP11: 0 | AQ11: 18874.49 | AR11: 0.03 | AS11: 0 | AT11: 566.23 | AU11: 0 | AV11: 0 | AW11: 352.19 | AX11: 214.04
A12: 8 | B12: 陈鑫鑫 | C12: 居民身份证 | D12: 230121199808271040 | E12: 230121199808271040 | F12: 否 | G12: 正常工资薪金 | H12: 8800 | I12: 0 | J12: 0 | K12: 5000 | L12: 572.96 | M12: 146.24 | N12: 35.81 | O12: 400 | P12: 0 | Q12: 0 | R12: 0 | S12: 0 | T12: 0 | U12: 0 | V12: 0 | W12: 0 | X12: - | Y12: 0 | Z12: - | AA12: - | AB12: - | AC12: 0 | AD12: 32187.98 | AE12: 20000 | AF12: 4620.04 | AG12: 0 | AH12: 0 | AI12: 0 | AJ12: 7500 | AK12: 0 | AL12: 0 | AM12: 0 | AN12: 0 | AO12: 100% | AP12: 0 | AQ12: 67.94 | AR12: 0.03 | AS12: 0 | AT12: 2.04 | AU12: 0 | AV12: 0 | AW12: 0 | AX12: 2.04
A13: 9 | B13: 郭轶 | C13: 居民身份证 | D13: 510106197603021421 | E13: 510106197603021421 | F13: 否 | G13: 正常工资薪金 | H13: 32408.01 | I13: 0 | J13: 0 | K13: 5000 | L13: 2864.88 | M13: 719.22 | N13: 179.06 | O13: 1695 | P13: 0 | Q13: 0 | R13: 0 | S13: 0 | T13: 0 | U13: 0 | V13: 0 | W13: 0 | X13: - | Y13: 0 | Z13: - | AA13: - | AB13: - | AC13: 0 | AD13: 226856.07 | AE13: 35000 | AF13: 38207.12 | AG13: 0 | AH13: 0 | AI13: 0 | AJ13: 0 | AK13: 0 | AL13: 0 | AM13: 0 | AN13: 0 | AO13: 100% | AP13: 0 | AQ13: 153648.95 | AR13: 0.2 | AS13: 16920 | AT13: 13809.79 | AU13: 0 | AV13: 0 | AW13: 10649.91 | AX13: 3159.88
A14: 10 | B14: 靳长明 | C14: 居民身份证 | D14: 371421199906236319 | E14: 371421199906236319 | F14: 否 | G14: 正常工资薪金 | H14: 13600 | I14: 0 | J14: 0 | K14: 5000 | L14: 572.96 | M14: 146.24 | N14: 35.81 | O14: 680 | P14: 0 | Q14: 0 | R14: 0 | S14: 0 | T14: 0 | U14: 0 | V14: 0 | W14: 0 | X14: - | Y14: 0 | Z14: - | AA14: - | AB14: - | AC14: 0 | AD14: 94599.2 | AE14: 35000 | AF14: 10045.07 | AG14: 0 | AH14: 0 | AI14: 0 | AJ14: 0 | AK14: 0 | AL14: 0 | AM14: 0 | AN14: 0 | AO14: 100% | AP14: 0 | AQ14: 49554.13 | AR14: 0.1 | AS14: 2520 | AT14: 2435.41 | AU14: 0 | AV14: 0 | AW14: 1718.91 | AX14: 716.5
A15: 11 | B15: 许文艳 | C15: 居民身份证 | D15: 130921198810150243 | E15: 130921198810150243 | F15: 否 | G15: 正常工资薪金 | H15: 26986.87 | I15: 0 | J15: 0 | K15: 5000 | L15: 572.96 | M15: 146.24 | N15: 35.81 | O15: 1350 | P15: 0 | Q15: 0 | R15: 0 | S15: 0 | T15: 0 | U15: 0 | V15: 0 | W15: 0 | X15: - | Y15: 0 | Z15: - | AA15: - | AB15: - | AC15: 0 | AD15: 192033.75 | AE15: 35000 | AF15: 14735.07 | AG15: 0 | AH15: 0 | AI15: 0 | AJ15: 0 | AK15: 0 | AL15: 0 | AM15: 0 | AN15: 0 | AO15: 100% | AP15: 0 | AQ15: 142298.68 | AR15: 0.1 | AS15: 2520 | AT15: 11709.87 | AU15: 0 | AV15: 0 | AW15: 9721.68 | AX15: 1988.19
A16: 12 | B16: 刘柏良 | C16: 居民身份证 | D16: 131182200104083813 | E16: 131182200104083813 | F16: 否 | G16: 正常工资薪金 | H16: 14970 | I16: 0 | J16: 0 | K16: 5000 | L16: 572.96 | M16: 146.24 | N16: 35.81 | O16: 520 | P16: 0 | Q16: 0 | R16: 0 | S16: 0 | T16: 0 | U16: 0 | V16: 0 | W16: 0 | X16: - | Y16: 0 | Z16: - | AA16: - | AB16: - | AC16: 0 | AD16: 104377.77 | AE16: 35000 | AF16: 8925.07 | AG16: 0 | AH16: 0 | AI16: 0 | AJ16: 0 | AK16: 0 | AL16: 0 | AM16: 0 | AN16: 0 | AO16: 100% | AP16: 0 | AQ16: 60452.7 | AR16: 0.1 | AS16: 2520 | AT16: 3525.27 | AU16: 0 | AV16: 0 | AW16: 2655.77 | AX16: 869.5
... A54: 50 | B54: 邢佳齐 | C54: 居民身份证 | D54: 410721200206190528 | E54: 410721200206190528 | F54: 否 | G54: 正常工资薪金 | H54: 7200 | I54: 0 | J54: 0 | K54: 5000 | L54: 572.96 | M54: 146.24 | N54: 35.81 | O54: 360 | P54: 0 | Q54: 0 | R54: 0 | S54: 0 | T54: 0 | U54: 0 | V54: 0 | W54: 0 | X54: - | Y54: 0 | Z54: - | AA54: - | AB54: - | AC54: 0 | AD54: 16457.14 | AE54: 15000 | AF54: 2230.02 | AG54: 0 | AH54: 0 | AI54: 0 | AJ54: 0 | AK54: 0 | AL54: 0 | AM54: 0 | AN54: 0 | AO54: 100% | AP54: 0 | AQ54: 0 | AR54: 0.03 | AS54: 0 | AT54: 0 | AU54: 0 | AV54: 0 | AW54: 0 | AX54: 0
A55: 51 | B55: 王涛 | C55: 居民身份证 | D55: 110103198904200037 | E55: 110103198904200037 | F55: 否 | G55: 正常工资薪金 | H55: 3803.01 | I55: 0 | J55: 0 | K55: 5000 | L55: 572.96 | M55: 146.24 | N55: 35.81 | O55: 0 | P55: 0 | Q55: 0 | R55: 0 | S55: 0 | T55: 0 | U55: 0 | V55: 0 | W55: 0 | X55: - | Y55: 0 | Z55: - | AA55: - | AB55: - | AC55: 0 | AD55: 26585.27 | AE55: 60000 | AF55: 5285.07 | AG55: 0 | AH55: 0 | AI55: 0 | AJ55: 0 | AK55: 0 | AL55: 0 | AM55: 0 | AN55: 0 | AO55: 100% | AP55: 0 | AQ55: 0 | AR55: 0.03 | AS55: 0 | AT55: 0 | AU55: 0 | AV55: 0 | AW55: 0 | AX55: 0 | AY55: 上年各月均有申报且全年收入不超过6万元
A56: 52 | B56: 曹爱华 | C56: 居民身份证 | D56: 131124199306212223 | E56: 131124199306212223 | F56: 否 | G56: 正常工资薪金 | H56: 11250.02 | I56: 0 | J56: 0 | K56: 5000 | L56: 572.96 | M56: 146.24 | N56: 35.81 | O56: 560 | P56: 0 | Q56: 0 | R56: 0 | S56: 0 | T56: 0 | U56: 0 | V56: 0 | W56: 0 | X56: - | Y56: 0 | Z56: - | AA56: - | AB56: - | AC56: 0 | AD56: 77869.83 | AE56: 35000 | AF56: 9205.07 | AG56: 0 | AH56: 0 | AI56: 0 | AJ56: 0 | AK56: 0 | AL56: 0 | AM56: 0 | AN56: 0 | AO56: 100% | AP56: 0 | AQ56: 33664.76 | AR56: 0.03 | AS56: 0 | AT56: 1009.94 | AU56: 0 | AV56: 0 | AW56: 861.89 | AX56: 148.05
A57: 53 | B57: 汪和艺 | C57: 居民身份证 | D57: 340881197110130626 | E57: 340881197110130626 | F57: 否 | G57: 一般劳务报酬所得 | H57: 1800 | I57: 800 | J57: 0 | K57: 0 | L57: 0 | M57: 0 | N57: 0 | O57: 0 | P57: 0 | Q57: 0 | R57: 0 | S57: 0 | T57: 0 | U57: - | V57: - | W57: - | X57: - | Y57: - | Z57: - | AA57: - | AB57: - | AC57: 0 | AD57: - | AE57: - | AF57: - | AG57: - | AH57: - | AI57: - | AJ57: - | AK57: - | AL57: - | AM57: - | AN57: - | AO57: 100% | AP57: 0 | AQ57: 1000 | AR57: 0.2 | AS57: 0 | AT57: 200 | AU57: 0 | AV57: 0 | AW57: 0 | AX57: 200
A58: 1 | B58: 陈泓佳 | C58: 居民身份证 | D58: 510802198811120026 | E58: 510802198811120026 | F58: 否 | G58: 正常工资薪金 | H58: 8000 | I58: 0 | J58: 0 | K58: 5000 | L58: 367.04 | M58: 91.76 | N58: 18.35 | O58: 400 | P58: 0 | Q58: 0 | R58: 0 | S58: 0 | T58: 0 | U58: 0 | V58: 0 | W58: 0 | X58: - | Y58: 0 | Z58: - | AA58: - | AB58: - | AC58: 0 | AD58: 56000 | AE58: 35000 | AF58: 6140.05 | AG58: 0 | AH58: 0 | AI58: 0 | AJ58: 0 | AK58: 0 | AL58: 0 | AM58: 0 | AN58: 0 | AO58: 100% | AP58: 0 | AQ58: 14859.95 | AR58: 0.03 | AS58: 0 | AT58: 445.8 | AU58: 0 | AV58: 0 | AW58: 382.11 | AX58: 63.69
A59: 1 | B59: 许紫怡 | C59: 居民身份证 | D59: 362323200208062528 | E59: 362323200208062528 | F59: 否 | G59: 正常工资薪金 | H59: 5708 | I59: 0 | J59: 0 | K59: 5000 | L59: 323.44 | M59: 88.66 | N59: 20.22 | O59: 260 | P59: 0 | Q59: 0 | R59: 0 | S59: 0 | T59: 0 | U59: 0 | V59: 0 | W59: 0 | X59: - | Y59: 0 | Z59: - | AA59: - | AB59: - | AC59: 0 | AD59: 17548.55 | AE59: 20000 | AF59: 2076.96 | AG59: 0 | AH59: 0 | AI59: 0 | AJ59: 0 | AK59: 0 | AL59: 0 | AM59: 0 | AN59: 0 | AO59: 100% | AP59: 0 | AQ59: 0 | AR59: 0.03 | AS59: 0 | AT59: 0 | AU59: 0 | AV59: 0 | AW59: 0 | AX59: 0
A60: 2 | B60: 陈楚冰 | C60: 居民身份证 | D60: 330681200010251588 | E60: 330681200010251588 | F60: 否 | G60: 正常工资薪金 | H60: 7200 | I60: 0 | J60: 0 | K60: 5000 | L60: 398.88 | M60: 99.72 | N60: 24.93 | O60: 320 | P60: 0 | Q60: 0 | R60: 0 | S60: 0 | T60: 0 | U60: 0 | V60: 0 | W60: 0 | X60: - | Y60: 0 | Z60: - | AA60: - | AB60: - | AC60: 0 | AD60: 51115.17 | AE60: 35000 | AF60: 5904.71 | AG60: 0 | AH60: 0 | AI60: 0 | AJ60: 0 | AK60: 0 | AL60: 0 | AM60: 0 | AN60: 0 | AO60: 100% | AP60: 0 | AQ60: 10210.46 | AR60: 0.03 | AS60: 0 | AT60: 306.31 | AU60: 0 | AV60: 0 | AW60: 265.62 | AX60: 40.69
A61: 3 | B61: 耿惠欣 | C61: 居民身份证 | D61: 37028519940425172X | E61: 37028519940425172X | F61: 否 | G61: 正常工资薪金 | H61: 3906.53 | I61: 0 | J61: 3906.53 | K61: 5000 | L61: 398.88 | M61: 99.72 | N61: 24.93 | O61: 723 | P61: 0 | Q61: 0 | R61: 0 | S61: 0 | T61: 0 | U61: 0 | V61: 0 | W61: 0 | X61: - | Y61: 0 | Z61: - | AA61: - | AB61: - | AC61: 0 | AD61: 48198.57 | AE61: 35000 | AF61: 9719.43 | AG61: 0 | AH61: 0 | AI61: 0 | AJ61: 10500 | AK61: 0 | AL61: 0 | AM61: 0 | AN61: 0 | AO61: 100% | AP61: 0 | AQ61: 0 | AR61: 0.03 | AS61: 0 | AT61: 0 | AU61: 0 | AV61: 0 | AW61: 436.85 | AX61: 0
A62: 4 | B62: 马顺华 | C62: 居民身份证 | D62: 429006198803300316 | E62: 429006198803300316 | F62: 否 | G62: 正常工资薪金 | H62: 10450.02 | I62: 0 | J62: 0 | K62: 5000 | L62: 398.88 | M62: 99.72 | N62: 24.93 | O62: 600 | P62: 0 | Q62: 0 | R62: 0 | S62: 0 | T62: 0 | U62: 0 | V62: 0 | W62: 0 | X62: - | Y62: 0 | Z62: - | AA62: - | AB62: - | AC62: 0 | AD62: 72991.45 | AE62: 35000 | AF62: 8600.34 | AG62: 0 | AH62: 10500 | AI62: 0 | AJ62: 0 | AK62: 0 | AL62: 0 | AM62: 0 | AN62: 0 | AO62: 100% | AP62: 0 | AQ62: 18891.11 | AR62: 0.03 | AS62: 0 | AT62: 566.73 | AU62: 0 | AV62: 0 | AW62: 481.94 | AX62: 84.79
A63: 5 | B63: 耿德强 | C63: 居民身份证 | D63: 37028519831217171X | E63: 37028519831217171X | F63: 否 | G63: 正常工资薪金 | H63: 40000 | I63: 0 | J63: 0 | K63: 5000 | L63: 398.88 | M63: 99.72 | N63: 24.93 | O63: 1977 | P63: 0 | Q63: 0 | R63: 0 | S63: 0 | T63: 0 | U63: 0 | V63: 0 | W63: 0 | X63: - | Y63: 0 | Z63: - | AA63: - | AB63: - | AC63: 0 | AD63: 280000 | AE63: 35000 | AF63: 19597.83 | AG63: 0 | AH63: 0 | AI63: 0 | AJ63: 0 | AK63: 0 | AL63: 0 | AM63: 0 | AN63: 0 | AO63: 100% | AP63: 0 | AQ63: 225402.17 | AR63: 0.2 | AS63: 16920 | AT63: 28160.43 | AU63: 0 | AV63: 0 | AW63: 21660.54 | AX63: 6499.89
A64: 6 | B64: 孙帆 | C64: 居民身份证 | D64: 140824199509230041 | E64: 140824199509230041 | F64: 否 | G64: 正常工资薪金 | H64: 14400 | I64: 0 | J64: 0 | K64: 5000 | L64: 398.88 | M64: 99.72 | N64: 24.93 | O64: 900 | P64: 0 | Q64: 0 | R64: 0 | S64: 0 | T64: 0 | U64: 0 | V64: 0 | W64: 0 | X64: - | Y64: 0 | Z64: - | AA64: - | AB64: - | AC64: 0 | AD64: 101078.25 | AE64: 35000 | AF64: 11331.18 | AG64: 0 | AH64: 0 | AI64: 0 | AJ64: 0 | AK64: 0 | AL64: 0 | AM64: 0 | AN64: 0 | AO64: 100% | AP64: 0 | AQ64: 54747.07 | AR64: 0.1 | AS64: 2520 | AT64: 2954.71 | AU64: 0 | AV64: 0 | AW64: 2157.06 | AX64: 797.65
A65: 7 | B65: 刘宇轩 | C65: 居民身份证 | D65: 232332199912051824 | E65: 232332199912051824 | F65: 否 | G65: 正常工资薪金 | H65: 6095.24 | I65: 0 | J65: 0 | K65: 5000 | L65: 398.88 | M65: 99.72 | N65: 24.93 | O65: 400 | P65: 0 | Q65: 0 | R65: 0 | S65: 0 | T65: 0 | U65: 0 | V65: 0 | W65: 0 | X65: - | Y65: 0 | Z65: - | AA65: - | AB65: - | AC65: 0 | AD65: 6095.24 | AE65: 5000 | AF65: 923.53 | AG65: 0 | AH65: 0 | AI65: 0 | AJ65: 0 | AK65: 0 | AL65: 0 | AM65: 0 | AN65: 0 | AO65: 100% | AP65: 0 | AQ65: 171.71 | AR65: 0.03 | AS65: 0 | AT65: 5.15 | AU65: 0 | AV65: 0 | AW65: 0 | AX65: 5.15
A66: 8 | B66: 王雨佳 | C66: 居民身份证 | D66: 339005199412138426 | E66: 339005199412138426 | F66: 否 | G66: 正常工资薪金 | H66: 11953.33 | I66: 0 | J66: 0 | K66: 5000 | L66: 398.88 | M66: 99.72 | N66: 24.93 | O66: 133 | P66: 0 | Q66: 0 | R66: 0 | S66: 0 | T66: 0 | U66: 0 | V66: 0 | W66: 0 | X66: - | Y66: 0 | Z66: - | AA66: - | AB66: - | AC66: 0 | AD66: 59856.92 | AE66: 25000 | AF66: 2626.12 | AG66: 0 | AH66: 0 | AI66: 0 | AJ66: 0 | AK66: 0 | AL66: 0 | AM66: 0 | AN66: 0 | AO66: 100% | AP66: 0 | AQ66: 32230.8 | AR66: 0.03 | AS66: 0 | AT66: 966.92 | AU66: 0 | AV66: 0 | AW66: 778.02 | AX66: 188.9
A67: 9 | B67: 段佳攀 | C67: 居民身份证 | D67: 421223199511130022 | E67: 421223199511130022 | F67: 否 | G67: 正常工资薪金 | H67: 6400 | I67: 0 | J67: 0 | K67: 5000 | L67: 398.88 | M67: 99.72 | N67: 24.93 | O67: 320 | P67: 0 | Q67: 0 | R67: 0 | S67: 0 | T67: 0 | U67: 0 | V67: 0 | W67: 0 | X67: - | Y67: 0 | Z67: - | AA67: - | AB67: - | AC67: 0 | AD67: 21236.36 | AE67: 20000 | AF67: 2530.59 | AG67: 0 | AH67: 0 | AI67: 0 | AJ67: 0 | AK67: 0 | AL67: 0 | AM67: 0 | AN67: 0 | AO67: 100% | AP67: 0 | AQ67: 0 | AR67: 0.03 | AS67: 0 | AT67: 0 | AU67: 0 | AV67: 0 | AW67: 0 | AX67: 0
A68: 10 | B68: 唐艳景 | C68: 居民身份证 | D68: 411324199508133468 | E68: 411324199508133468 | F68: 否 | G68: 正常工资薪金 | H68: 21050.02 | I68: 0 | J68: 0 | K68: 5000 | L68: 398.88 | M68: 99.72 | N68: 24.93 | O68: 1050 | P68: 0 | Q68: 0 | R68: 0 | S68: 0 | T68: 0 | U68: 0 | V68: 0 | W68: 0 | X68: - | Y68: 0 | Z68: - | AA68: - | AB68: - | AC68: 0 | AD68: 146960.02 | AE68: 35000 | AF68: 12696.18 | AG68: 0 | AH68: 0 | AI68: 0 | AJ68: 0 | AK68: 0 | AL68: 0 | AM68: 0 | AN68: 0 | AO68: 100% | AP68: 0 | AQ68: 99263.84 | AR68: 0.1 | AS68: 2520 | AT68: 7406.38 | AU68: 0 | AV68: 0 | AW68: 5958.74 | AX68: 1447.64
A69: 11 | B69: 刘洋 | C69: 居民身份证 | D69: 411102198406050051 | E69: 411102198406050051 | F69: 否 | G69: 正常工资薪金 | H69: 40000 | I69: 0 | J69: 0 | K69: 5000 | L69: 398.88 | M69: 99.72 | N69: 24.93 | O69: 1977 | P69: 0 | Q69: 0 | R69: 0 | S69: 0 | T69: 0 | U69: 0 | V69: 0 | W69: 0 | X69: - | Y69: 0 | Z69: - | AA69: - | AB69: - | AC69: 0 | AD69: 280000 | AE69: 35000 | AF69: 19597.83 | AG69: 0 | AH69: 21000 | AI69: 0 | AJ69: 0 | AK69: 0 | AL69: 0 | AM69: 0 | AN69: 0 | AO69: 100% | AP69: 0 | AQ69: 204402.17 | AR69: 0.2 | AS69: 16920 | AT69: 23960.43 | AU69: 0 | AV69: 0 | AW69: 18060.54 | AX69: 5899.89
... A72: 14 | B72: 田楠 | C72: 居民身份证 | D72: 342221199203231524 | E72: 342221199203231524 | F72: 否 | G72: 正常工资薪金 | H72: 11200 | I72: 0 | J72: 0 | K72: 5000 | L72: 398.88 | M72: 99.72 | N72: 24.93 | O72: 694 | P72: 0 | Q72: 0 | R72: 0 | S72: 0 | T72: 0 | U72: 0 | V72: 0 | W72: 0 | X72: - | Y72: 0 | Z72: - | AA72: - | AB72: - | AC72: 0 | AD72: 78400 | AE72: 35000 | AF72: 9456.06 | AG72: 0 | AH72: 0 | AI72: 0 | AJ72: 0 | AK72: 0 | AL72: 0 | AM72: 0 | AN72: 0 | AO72: 100% | AP72: 0 | AQ72: 33943.94 | AR72: 0.03 | AS72: 0 | AT72: 1018.32 | AU72: 0 | AV72: 0 | AW72: 868.84 | AX72: 149.48
A73: 15 | B73: 陈柏强 | C73: 居民身份证 | D73: 430321198203253513 | E73: 430321198203253513 | F73: 否 | G73: 一般劳务报酬所得 | H73: 800 | I73: 800 | J73: 0 | K73: 0 | L73: 0 | M73: 0 | N73: 0 | O73: 0 | P73: 0 | Q73: 0 | R73: 0 | S73: 0 | T73: 0 | U73: - | V73: - | W73: - | X73: - | Y73: - | Z73: - | AA73: - | AB73: - | AC73: 0 | AD73: - | AE73: - | AF73: - | AG73: - | AH73: - | AI73: - | AJ73: - | AK73: - | AL73: - | AM73: - | AN73: - | AO73: 100% | AP73: 0 | AQ73: 0 | AR73: 0.2 | AS73: 0 | AT73: 0 | AU73: 0 | AV73: 0 | AW73: 0 | AX73: 0
A74: 16 | B74: 宋琪 | C74: 居民身份证 | D74: 372928198901100293 | E74: 372928198901100293 | F74: 否 | G74: 一般劳务报酬所得 | H74: 800 | I74: 800 | J74: 0 | K74: 0 | L74: 0 | M74: 0 | N74: 0 | O74: 0 | P74: 0 | Q74: 0 | R74: 0 | S74: 0 | T74: 0 | U74: - | V74: - | W74: - | X74: - | Y74: - | Z74: - | AA74: - | AB74: - | AC74: 0 | AD74: - | AE74: - | AF74: - | AG74: - | AH74: - | AI74: - | AJ74: - | AK74: - | AL74: - | AM74: - | AN74: - | AO74: 100% | AP74: 0 | AQ74: 0 | AR74: 0.2 | AS74: 0 | AT74: 0 | AU74: 0 | AV74: 0 | AW74: 0 | AX74: 0
A75: 17 | B75: 汤修兰 | C75: 居民身份证 | D75: 512224197105265300 | E75: 512224197105265300 | F75: 否 | G75: 一般劳务报酬所得 | H75: 600 | I75: 800 | J75: 0 | K75: 0 | L75: 0 | M75: 0 | N75: 0 | O75: 0 | P75: 0 | Q75: 0 | R75: 0 | S75: 0 | T75: 0 | U75: - | V75: - | W75: - | X75: - | Y75: - | Z75: - | AA75: - | AB75: - | AC75: 0 | AD75: - | AE75: - | AF75: - | AG75: - | AH75: - | AI75: - | AJ75: - | AK75: - | AL75: - | AM75: - | AN75: - | AO75: 100% | AP75: 0 | AQ75: 0 | AR75: 0.2 | AS75: 0 | AT75: 0 | AU75: 0 | AV75: 0 | AW75: 0 | AX75: 0
A76: 18 | B76: 李诚 | C76: 居民身份证 | D76: 110108198206225730 | E76: 110108198206225730 | F76: 否 | G76: 一般劳务报酬所得 | H76: 800 | I76: 800 | J76: 0 | K76: 0 | L76: 0 | M76: 0 | N76: 0 | O76: 0 | P76: 0 | Q76: 0 | R76: 0 | S76: 0 | T76: 0 | U76: - | V76: - | W76: - | X76: - | Y76: - | Z76: - | AA76: - | AB76: - | AC76: 0 | AD76: - | AE76: - | AF76: - | AG76: - | AH76: - | AI76: - | AJ76: - | AK76: - | AL76: - | AM76: - | AN76: - | AO76: 100% | AP76: 0 | AQ76: 0 | AR76: 0.2 | AS76: 0 | AT76: 0 | AU76: 0 | AV76: 0 | AW76: 0 | AX76: 0
A77: 19 | B77: 王丽花 | C77: 居民身份证 | D77: 350500197206142522 | E77: 350500197206142522 | F77: 否 | G77: 一般劳务报酬所得 | H77: 150 | I77: 800 | J77: 0 | K77: 0 | L77: 0 | M77: 0 | N77: 0 | O77: 0 | P77: 0 | Q77: 0 | R77: 0 | S77: 0 | T77: 0 | U77: - | V77: - | W77: - | X77: - | Y77: - | Z77: - | AA77: - | AB77: - | AC77: 0 | AD77: - | AE77: - | AF77: - | AG77: - | AH77: - | AI77: - | AJ77: - | AK77: - | AL77: - | AM77: - | AN77: - | AO77: 100% | AP77: 0 | AQ77: 0 | AR77: 0.2 | AS77: 0 | AT77: 0 | AU77: 0 | AV77: 0 | AW77: 0 | AX77: 0
A78: 20 | B78: 阮敬 | C78: 居民身份证 | D78: 452330197910110017 | E78: 452330197910110017 | F78: 否 | G78: 一般劳务报酬所得 | H78: 800 | I78: 800 | J78: 0 | K78: 0 | L78: 0 | M78: 0 | N78: 0 | O78: 0 | P78: 0 | Q78: 0 | R78: 0 | S78: 0 | T78: 0 | U78: - | V78: - | W78: - | X78: - | Y78: - | Z78: - | AA78: - | AB78: - | AC78: 0 | AD78: - | AE78: - | AF78: - | AG78: - | AH78: - | AI78: - | AJ78: - | AK78: - | AL78: - | AM78: - | AN78: - | AO78: 100% | AP78: 0 | AQ78: 0 | AR78: 0.2 | AS78: 0 | AT78: 0 | AU78: 0 | AV78: 0 | AW78: 0 | AX78: 0
A79: 21 | B79: 刘毅婷 | C79: 居民身份证 | D79: 362502198303250446 | E79: 362502198303250446 | F79: 否 | G79: 一般劳务报酬所得 | H79: 800 | I79: 800 | J79: 0 | K79: 0 | L79: 0 | M79: 0 | N79: 0 | O79: 0 | P79: 0 | Q79: 0 | R79: 0 | S79: 0 | T79: 0 | U79: - | V79: - | W79: - | X79: - | Y79: - | Z79: - | AA79: - | AB79: - | AC79: 0 | AD79: - | AE79: - | AF79: - | AG79: - | AH79: - | AI79: - | AJ79: - | AK79: - | AL79: - | AM79: - | AN79: - | AO79: 100% | AP79: 0 | AQ79: 0 | AR79: 0.2 | AS79: 0 | AT79: 0 | AU79: 0 | AV79: 0 | AW79: 0 | AX79: 0
A80: 1 | B80: 宁源双 | C80: 居民身份证 | D80: 450721200302232625 | E80: 450721200302232625 | F80: 否 | G80: 正常工资薪金 | H80: 7970.02 | I80: 0 | J80: 0 | K80: 5000 | L80: 382 | M80: 134.54 | N80: 5.04 | O80: 352 | P80: 0 | Q80: 0 | R80: 0 | S80: 0 | T80: 0 | U80: 0 | V80: 0 | W80: 0 | X80: - | Y80: 0 | Z80: - | AA80: - | AB80: - | AC80: 0 | AD80: 55391.21 | AE80: 35000 | AF80: 6115.18 | AG80: 0 | AH80: 0 | AI80: 0 | AJ80: 0 | AK80: 0 | AL80: 0 | AM80: 0 | AN80: 0 | AO80: 100% | AP80: 0 | AQ80: 14276.03 | AR80: 0.03 | AS80: 0 | AT80: 428.28 | AU80: 0 | AV80: 0 | AW80: 365.39 | AX80: 62.89
A81: 3 | B81: 陈丽娟 | C81: 居民身份证 | D81: 230103197203163221 | E81: 230103197203163221 | F81: 否 | G81: 正常工资薪金 | H81: 3145.06 | I81: 0 | J81: 0 | K81: 5000 | L81: 382 | M81: 134.54 | N81: 5.04 | O81: 126 | P81: 0 | Q81: 0 | R81: 0 | S81: 0 | T81: 0 | U81: 0 | V81: 0 | W81: 0 | X81: - | Y81: 0 | Z81: - | AA81: - | AB81: - | AC81: 0 | AD81: 22222.22 | AE81: 35000 | AF81: 4533.18 | AG81: 0 | AH81: 0 | AI81: 0 | AJ81: 0 | AK81: 0 | AL81: 0 | AM81: 0 | AN81: 0 | AO81: 100% | AP81: 0 | AQ81: 0 | AR81: 0.03 | AS81: 0 | AT81: 0 | AU81: 0 | AV81: 0 | AW81: 0 | AX81: 0
A82: 2 | B82: 王鹏辉 | C82: 居民身份证 | D82: 421181198909130413 | E82: 421181198909130413 | F82: 否 | G82: 正常工资薪金 | H82: 19494.69 | I82: 0 | J82: 0 | K82: 5000 | L82: 1799.04 | M82: 456.76 | N82: 67.46 | O82: 1191.65 | P82: 0 | Q82: 0 | R82: 0 | S82: 0 | T82: 0 | U82: 0 | V82: 0 | W82: 0 | X82: - | Y82: 0 | Z82: - | AA82: - | AB82: - | AC82: 0 | AD82: 147222.56 | AE82: 35000 | AF82: 25014.85 | AG82: 0 | AH82: 0 | AI82: 0 | AJ82: 10500 | AK82: 0 | AL82: 0 | AM82: 0 | AN82: 0 | AO82: 100% | AP82: 0 | AQ82: 76707.71 | AR82: 0.1 | AS82: 2520 | AT82: 5150.77 | AU82: 0 | AV82: 0 | AW82: 4202.79 | AX82: 947.98
A83: 3 | B83: 黄晶 | C83: 居民身份证 | D83: 420111199208023126 | E83: 420111199208023126 | F83: 否 | G83: 正常工资薪金 | H83: 12378 | I83: 0 | J83: 0 | K83: 5000 | L83: 1200 | M83: 307 | N83: 45 | O83: 750 | P83: 0 | Q83: 0 | R83: 0 | S83: 0 | T83: 0 | U83: 0 | V83: 0 | W83: 0 | X83: - | Y83: 0 | Z83: - | AA83: - | AB83: - | AC83: 0 | AD83: 86315.46 | AE83: 35000 | AF83: 16114 | AG83: 7000 | AH83: 21000 | AI83: 0 | AJ83: 0 | AK83: 0 | AL83: 0 | AM83: 0 | AN83: 0 | AO83: 100% | AP83: 0 | AQ83: 7201.46 | AR83: 0.03 | AS83: 0 | AT83: 216.04 | AU83: 0 | AV83: 0 | AW83: 422.82 | AX83: 0

Sheet 法定假日列表
A1: 节日 | B1: 日期 | C1: 说明 | F1: 补班日期 | G1: 说明
A2: 元旦 | B2: 46023 | C2: 放假 | F2: 46026 | G2: 元旦补班
A3: 元旦 | B3: 46024 | C3: 放假 | F3: 46067 | G3: 春节补班
A4: 元旦 | B4: 46025 | C4: 放假 | F4: 46081 | G4: 春节补班
A5: 春节 | B5: 46069 | C5: 放假（初一） | F5: 46151 | G5: 劳动节补班
A6: 春节 | B6: 46070 | C6: 放假（初二） | F6: 46285 | G6: 国庆节补班
A7: 春节 | B7: 46071 | C7: 放假（初三） | F7: 46305 | G7: 国庆节补班
A8: 春节 | B8: 46072 | C8: 放假（初四）
A9: 春节 | B9: 46073 | C9: 放假（初五）
A10: 春节 | B10: 46076 | C10: 放假（调休）
A11: 清明节 | B11: 46116 | C11: 放假
A12: 清明节 | B12: 46117 | C12: 放假
A13: 清明节 | B13: 46118 | C13: 放假
A14: 劳动节 | B14: 46143 | C14: 放假
A15: 劳动节 | B15: 46144 | C15: 放假
A16: 劳动节 | B16: 46145 | C16: 放假
A17: 劳动节 | B17: 46146 | C17: 放假
A18: 劳动节 | B18: 46147 | C18: 放假
A19: 端午节 | B19: 46192 | C19: 放假
... A31: 国庆节 | B31: 46302 | C31: 放假

Sheet 导入模版（北分）
A1: 身份证号 | B1: 编号 | C1: 员工账号 | D1: 员工账户开户行 | E1: 姓名 | F1: 金额 | G1: 备注
A2: 620402199105092732 | B2: =ROW()-1 -> 1 | C2: =VLOOKUP(A2&"*",花名册!B:S,17,0) -> #N/A | D2: =VLOOKUP(A2&"*",花名册!B:S,18,0) -> #N/A | E2: =IF(VLOOKUP(A2&"*",花名册!B:C,2,0)="郭子轶","郭轶",VLOOKUP(A2&"*",花名册!B:C,2,0)) -> #N/A | F2: =VLOOKUP(A2&"*",工资表明细!D:AX,47,0) -> #N/A
A3: 141034199511170105 | B3: =ROW()-1 -> 2 | C3: =VLOOKUP(A3&"*",花名册!B:S,17,0) -> #N/A | D3: =VLOOKUP(A3&"*",花名册!B:S,18,0) -> #N/A | E3: =IF(VLOOKUP(A3&"*",花名册!B:C,2,0)="郭子轶","郭轶",VLOOKUP(A3&"*",花名册!B:C,2,0)) -> #N/A | F3: =VLOOKUP(A3&"*",工资表明细!D:AX,47,0) -> #N/A
A4: 211382199701014125 | B4: =ROW()-1 -> 3 | C4: =VLOOKUP(A4&"*",花名册!B:S,17,0) -> #N/A | D4: =VLOOKUP(A4&"*",花名册!B:S,18,0) -> #N/A | E4: =IF(VLOOKUP(A4&"*",花名册!B:C,2,0)="郭子轶","郭轶",VLOOKUP(A4&"*",花名册!B:C,2,0)) -> #N/A | F4: =VLOOKUP(A4&"*",工资表明细!D:AX,47,0) -> #N/A
A5: 510106197603021421 | B5: =ROW()-1 -> 4 | C5: =VLOOKUP(A5&"*",花名册!B:S,17,0) -> #N/A | D5: =VLOOKUP(A5&"*",花名册!B:S,18,0) -> #N/A | E5: =IF(VLOOKUP(A5&"*",花名册!B:C,2,0)="郭子轶","郭轶",VLOOKUP(A5&"*",花名册!B:C,2,0)) -> #N/A | F5: =VLOOKUP(A5&"*",工资表明细!D:AX,47,0) -> #N/A
A6: 410881199208201514 | B6: =ROW()-1 -> 5 | C6: =VLOOKUP(A6&"*",花名册!B:S,17,0) -> #N/A | D6: =VLOOKUP(A6&"*",花名册!B:S,18,0) -> #N/A | E6: =IF(VLOOKUP(A6&"*",花名册!B:C,2,0)="郭子轶","郭轶",VLOOKUP(A6&"*",花名册!B:C,2,0)) -> #N/A | F6: =VLOOKUP(A6&"*",工资表明细!D:AX,47,0) -> #N/A
A7: 370831198704081514 | B7: =ROW()-1 -> 6 | C7: =VLOOKUP(A7&"*",花名册!B:S,17,0) -> #N/A | D7: =VLOOKUP(A7&"*",花名册!B:S,18,0) -> #N/A | E7: =IF(VLOOKUP(A7&"*",花名册!B:C,2,0)="郭子轶","郭轶",VLOOKUP(A7&"*",花名册!B:C,2,0)) -> #N/A | F7: =VLOOKUP(A7&"*",工资表明细!D:AX,47,0) -> #N/A
A8: 130427198606116938 | B8: =ROW()-1 -> 7 | C8: =VLOOKUP(A8&"*",花名册!B:S,17,0) -> #N/A | D8: =VLOOKUP(A8&"*",花名册!B:S,18,0) -> #N/A | E8: =IF(VLOOKUP(A8&"*",花名册!B:C,2,0)="郭子轶","郭轶",VLOOKUP(A8&"*",花名册!B:C,2,0)) -> #N/A | F8: =VLOOKUP(A8&"*",工资表明细!D:AX,47,0) -> #N/A
A9: 110111199310191641 | B9: =ROW()-1 -> 8 | C9: =VLOOKUP(A9&"*",花名册!B:S,17,0) -> #N/A | D9: =VLOOKUP(A9&"*",花名册!B:S,18,0) -> #N/A | E9: =IF(VLOOKUP(A9&"*",花名册!B:C,2,0)="郭子轶","郭轶",VLOOKUP(A9&"*",花名册!B:C,2,0)) -> #N/A | F9: =VLOOKUP(A9&"*",工资表明细!D:AX,47,0) -> #N/A
A10: 420528199505212854 | B10: =ROW()-1 -> 9 | C10: =VLOOKUP(A10&"*",花名册!B:S,17,0) -> #N/A | D10: =VLOOKUP(A10&"*",花名册!B:S,18,0) -> #N/A | E10: =IF(VLOOKUP(A10&"*",花名册!B:C,2,0)="郭子轶","郭轶",VLOOKUP(A10&"*",花名册!B:C,2,0)) -> #N/A | F10: =VLOOKUP(A10&"*",工资表明细!D:AX,47,0) -> #N/A
A11: 412726199110166812 | B11: =ROW()-1 -> 10 | C11: =VLOOKUP(A11&"*",花名册!B:S,17,0) -> #N/A | D11: =VLOOKUP(A11&"*",花名册!B:S,18,0) -> #N/A | E11: =IF(VLOOKUP(A11&"*",花名册!B:C,2,0)="郭子轶","郭轶",VLOOKUP(A11&"*",花名册!B:C,2,0)) -> #N/A | F11: =VLOOKUP(A11&"*",工资表明细!D:AX,47,0) -> #N/A
A12: 110106199508180621 | B12: =ROW()-1 -> 11 | C12: =VLOOKUP(A12&"*",花名册!B:S,17,0) -> #N/A | D12: =VLOOKUP(A12&"*",花名册!B:S,18,0) -> #N/A | E12: =IF(VLOOKUP(A12&"*",花名册!B:C,2,0)="郭子轶","郭轶",VLOOKUP(A12&"*",花名册!B:C,2,0)) -> #N/A | F12: =VLOOKUP(A12&"*",工资表明细!D:AX,47,0) -> #N/A
A13: 14273019951005291X | B13: =ROW()-1 -> 12 | C13: =VLOOKUP(A13&"*",花名册!B:S,17,0) -> #N/A | D13: =VLOOKUP(A13&"*",花名册!B:S,18,0) -> #N/A | E13: =IF(VLOOKUP(A13&"*",花名册!B:C,2,0)="郭子轶","郭轶",VLOOKUP(A13&"*",花名册!B:C,2,0)) -> #N/A | F13: =VLOOKUP(A13&"*",工资表明细!D:AX,47,0) -> #N/A
... A53: 340881197110130626 | B53: =ROW()-1 -> 52 | C53: =VLOOKUP(A53&"*",花名册!B:S,17,0) -> #N/A | D53: =VLOOKUP(A53&"*",花名册!B:S,18,0) -> #N/A | E53: =IF(VLOOKUP(A53&"*",花名册!B:C,2,0)="郭子轶","郭轶",VLOOKUP(A53&"*",花名册!B:C,2,0)) -> #N/A | F53: =VLOOKUP(A53&"*",工资表明细!D:AX,47,0) -> #N/A
A54: 413026199909013086 | B54: =ROW()-1 -> 53 | C54: =VLOOKUP(A54&"*",花名册!B:S,17,0) -> #N/A | D54: =VLOOKUP(A54&"*",花名册!B:S,18,0) -> #N/A | E54: 蒋艳林 | F54: =VLOOKUP(A54&"*",工资表明细!D:AX,47,0) -> #N/A
F55: =SUM(F2:F54) -> #N/A

Sheet 导入模版（北京）
A1: 身份证号 | B1: 编号 | C1: 员工账号 | D1: 员工账户开户行 | E1: 姓名 | F1: 金额 | G1: 备注
F4: =SUM(F2:F3) -> 0
F56: =SUM(F2:F55) -> 0

Sheet 导入模版（成都）
A1: 身份证号 | B1: 编号 | C1: 员工账号 | D1: 员工账户开户行 | E1: 姓名 | F1: 金额 | G1: 备注
A2: 510802198811120026 | B2: =ROW()-1 -> 1 | C2: =VLOOKUP(A2&"*",花名册!B:S,17,0) -> #N/A | D2: =VLOOKUP(A2&"*",花名册!B:S,18,0) -> #N/A | E2: =VLOOKUP(A2&"*",花名册!B:C,2,0) -> #N/A | F2: =VLOOKUP(A2&"*",工资表明细!D:AX,47,0) -> #N/A
F4: =SUM(F2:F3) -> #N/A
F56: =SUM(F2:F55) -> #N/A

Sheet 导入模版（杭州）
A1: 身份证号 | B1: 编号 | C1: 员工账号 | D1: 员工账户开户行 | E1: 姓名 | F1: 金额 | G1: 备注
A2: 37028519831217171X | B2: =ROW()-1 -> 1 | C2: =VLOOKUP(A2&"*",花名册!B:S,17,0) -> #N/A | D2: =VLOOKUP(A2&"*",花名册!B:S,18,0) -> #N/A | E2: =VLOOKUP(A2&"*",花名册!B:C,2,0) -> #N/A | F2: =VLOOKUP(A2&"*",工资表明细!D:AX,47,0) -> #N/A
A3: 411102198406050051 | B3: =ROW()-1 -> 2 | C3: =VLOOKUP(A3&"*",花名册!B:S,17,0) -> #N/A | D3: =VLOOKUP(A3&"*",花名册!B:S,18,0) -> #N/A | E3: =VLOOKUP(A3&"*",花名册!B:C,2,0) -> #N/A | F3: =VLOOKUP(A3&"*",工资表明细!D:AX,47,0) -> #N/A
A4: 429006198803300316 | B4: =ROW()-1 -> 3 | C4: =VLOOKUP(A4&"*",花名册!B:S,17,0) -> #N/A | D4: =VLOOKUP(A4&"*",花名册!B:S,18,0) -> #N/A | E4: =VLOOKUP(A4&"*",花名册!B:C,2,0) -> #N/A | F4: =VLOOKUP(A4&"*",工资表明细!D:AX,47,0) -> #N/A
A5: 37028519940425172X | B5: =ROW()-1 -> 4 | C5: =VLOOKUP(A5&"*",花名册!B:S,17,0) -> #N/A | D5: =VLOOKUP(A5&"*",花名册!B:S,18,0) -> #N/A | E5: =VLOOKUP(A5&"*",花名册!B:C,2,0) -> #N/A | F5: =VLOOKUP(A5&"*",工资表明细!D:AX,47,0) -> #N/A
A6: 342221199203231524 | B6: =ROW()-1 -> 5 | C6: =VLOOKUP(A6&"*",花名册!B:S,17,0) -> #N/A | D6: =VLOOKUP(A6&"*",花名册!B:S,18,0) -> #N/A | E6: =VLOOKUP(A6&"*",花名册!B:C,2,0) -> #N/A | F6: =VLOOKUP(A6&"*",工资表明细!D:AX,47,0) -> #N/A
A7: 140824199509230041 | B7: =ROW()-1 -> 6 | C7: =VLOOKUP(A7&"*",花名册!B:S,17,0) -> #N/A | D7: =VLOOKUP(A7&"*",花名册!B:S,18,0) -> #N/A | E7: =VLOOKUP(A7&"*",花名册!B:C,2,0) -> #N/A | F7: =VLOOKUP(A7&"*",工资表明细!D:AX,47,0) -> #N/A
A8: 411324199508133468 | B8: =ROW()-1 -> 7 | C8: =VLOOKUP(A8&"*",花名册!B:S,17,0) -> #N/A | D8: =VLOOKUP(A8&"*",花名册!B:S,18,0) -> #N/A | E8: =VLOOKUP(A8&"*",花名册!B:C,2,0) -> #N/A | F8: =VLOOKUP(A8&"*",工资表明细!D:AX,47,0) -> #N/A
A9: 330681200010251588 | B9: =ROW()-1 -> 8 | C9: =VLOOKUP(A9&"*",花名册!B:S,17,0) -> #N/A | D9: =VLOOKUP(A9&"*",花名册!B:S,18,0) -> #N/A | E9: =VLOOKUP(A9&"*",花名册!B:C,2,0) -> #N/A | F9: =VLOOKUP(A9&"*",工资表明细!D:AX,47,0) -> #N/A
A10: 330108198912080920 | B10: =ROW()-1 -> 9 | C10: =VLOOKUP(A10&"*",花名册!B:S,17,0) -> #N/A | D10: =VLOOKUP(A10&"*",花名册!B:S,18,0) -> #N/A | E10: =VLOOKUP(A10&"*",花名册!B:C,2,0) -> #N/A | F10: =VLOOKUP(A10&"*",工资表明细!D:AX,47,0) -> #N/A
A11: 339005199412138426 | B11: =ROW()-1 -> 10 | C11: =VLOOKUP(A11&"*",花名册!B:S,17,0) -> #N/A | D11: =VLOOKUP(A11&"*",花名册!B:S,18,0) -> #N/A | E11: =VLOOKUP(A11&"*",花名册!B:C,2,0) -> #N/A | F11: =VLOOKUP(A11&"*",工资表明细!D:AX,47,0) -> #N/A
A12: 421223199511130022 | B12: =ROW()-1 -> 11 | C12: =VLOOKUP(A12&"*",花名册!B:S,17,0) -> #N/A | D12: =VLOOKUP(A12&"*",花名册!B:S,18,0) -> #N/A | E12: =VLOOKUP(A12&"*",花名册!B:C,2,0) -> #N/A | F12: =VLOOKUP(A12&"*",工资表明细!D:AX,47,0) -> #N/A
A13: 350504200012191529 | B13: =ROW()-1 -> 12 | C13: =VLOOKUP(A13&"*",花名册!B:S,17,0) -> #N/A | D13: =VLOOKUP(A13&"*",花名册!B:S,18,0) -> #N/A | E13: =VLOOKUP(A13&"*",花名册!B:C,2,0) -> #N/A | F13: =VLOOKUP(A13&"*",工资表明细!D:AX,47,0) -> #N/A
... A17: 232332199912051824 | B17: =ROW()-1 -> 16 | C17: =VLOOKUP(A17&"*",花名册!B:S,17,0) -> #N/A | D17: =VLOOKUP(A17&"*",花名册!B:S,18,0) -> #N/A | E17: =VLOOKUP(A17&"*",花名册!B:C,2,0) -> #N/A | F17: =VLOOKUP(A17&"*",工资表明细!D:AX,47,0) -> #N/A
F18: =SUM(F2:F17) -> #N/A
F57: =SUM(F2:F56) -> #N/A

Sheet 导入模版（深圳）
A1: 身份证号 | B1: 编号 | C1: 员工账号 | D1: 员工账户开户行 | E1: 姓名 | F1: 金额 | G1: 备注
A2: 230103197203163221 | B2: =ROW()-1 -> 1 | C2: =VLOOKUP(A2&"*",花名册!B:S,17,0) -> #N/A | D2: =VLOOKUP(A2&"*",花名册!B:S,18,0) -> #N/A | E2: =VLOOKUP(A2&"*",花名册!B:C,2,0) -> #N/A | F2: =VLOOKUP(A2&"*",工资表明细!D:AX,47,0) -> #N/A
A3: 450721200302232625 | B3: =ROW()-1 -> 2 | C3: =VLOOKUP(A3&"*",花名册!B:S,17,0) -> #N/A | D3: =VLOOKUP(A3&"*",花名册!B:S,18,0) -> #N/A | E3: =VLOOKUP(A3&"*",花名册!B:C,2,0) -> #N/A | F3: =VLOOKUP(A3&"*",工资表明细!D:AX,47,0) -> #N/A
F4: =SUM(F2:F3) -> #N/A
F56: =SUM(F2:F55) -> #N/A

Sheet 导入模版（武汉）
A1: 身份证号 | B1: 编号 | C1: 员工账号 | D1: 员工账户开户行 | E1: 姓名 | F1: 金额 | G1: 备注
A2: 421181198909130413 | B2: =ROW()-1 -> 1 | C2: =VLOOKUP(A2&"*",花名册!B:S,17,0) -> #N/A | D2: =VLOOKUP(A2&"*",花名册!B:S,18,0) -> #N/A | E2: =VLOOKUP(A2&"*",花名册!B:C,2,0) -> #N/A | F2: =VLOOKUP(A2&"*",工资表明细!D:AX,47,0) -> #N/A
A3: 420111199208023126 | B3: =ROW()-1 -> 2 | C3: =VLOOKUP(A3&"*",花名册!B:S,17,0) -> #N/A | D3: =VLOOKUP(A3&"*",花名册!B:S,18,0) -> #N/A | E3: =VLOOKUP(A3&"*",花名册!B:C,2,0) -> #N/A | F3: =VLOOKUP(A3&"*",工资表明细!D:AX,47,0) -> #N/A
F4: =SUM(F2:F3) -> #N/A
F56: =SUM(F2:F55) -> #N/A

Sheet 导入模版（中汽）
A1: 序号 | B1: 姓名 | C1: 卡/折号 | D1: 证件类型 | E1: 证件号码 | F1: 工资金额 | G1: 明细1 | H1: 明细2
A12: 输入项 | B12: 填写说明
A13: 序号 | B13: 序号以阿拉伯数字按顺序填写即可。
A14: 姓名 | B14: 中文姓名请不要包含空格。
A15: 卡/折号 | B15: 收款人账号应为“6029”、“6210”等开头的北京银行账号。输入收款账号时应保证收款账号以文本形式输入，如果收款账号以科学计数法输入，将不能保证工资正确发放。
A16: 证件类型 | B16: 身份证件类型请参照以下对应关系录入，输入数字代码或中文名称均可。1-身份证、2-户口本、3-护照、4-军人证、5-港澳台居民身份证、6-武警身份证、7-边民出入境通行证。
A17: 证件号码 | B17: 身份证件号码身份证件号码应以文本格式输入。其中身份证件号码可以为15位或18位，护照证件号码中可输入英文，军人证号码中可输入中文。
A18: 工资金额 | B18: 工资金额请以阿拉伯数字填写，不要使用公式计算，如果从其他表格计算结果中粘贴，请保证小数点后最多只有两位。
A19: 工资明细 | B19: EXCEL工资文件从第七列开始为工资明细。请您依次在每列第一行输入名细名目，以下各行只需依次输入对应的工资金额即可。
A20: 特别说明： 1、系统将自动从上传的文件中第二行开始提取数值，第一行请不要录入工资信息；2、请确认输入的内容中不包含空格字符； 3、上传文件时如提示“输入的笔数与总笔数不符”，请使用“删除整行”删除最后一行后的若干行后重试；4、如提示输入的金额有误，请检查报销金额是否小数点后超过两位。

Sheet 报税-人员信息采集表
A1: 公司 | B1: *姓名 | C1: *证件类型 | D1: *证件号码 | E1: *国籍(地区) | F1: *性别 | G1: *出生日期 | H1: 是否高级专家 | I1: *任职受雇从业类型 | J1: 其他情况说明 | K1: 入职年度就业情形 | L1: 手机号码 | M1: 任职受雇从业日期 | N1: 离职日期 | O1: 是否离职后补发工资 | P1: 补发税款所属月份 | Q1: 是否残疾 | R1: 是否烈属 | S1: 是否孤老 | T1: 残疾证件类型 | U1: 残疾证号 | V1: 烈属证号 | W1: 是否扣除减除费用 | X1: 个人投资额 | Y1: 个人投资比例(%) | Z1: 备注 | AA1: 中文名 | AB1: 涉税事由 | AC1: 出生国家(地区) | AD1: 首次入境时间 | AE1: 预计离境时间 | AF1: 其他证件类型 | AG1: 其他证件号码 | AH1: 户籍所在地（省） | AI1: 户籍所在地（市） | AJ1: 户籍所在地（区县） | AK1: 户籍所在地（详细地址） | AL1: 经常居住地（省） | AM1: 经常居住地（市） | AN1: 经常居住地（区县） | AO1: 经常居住地（详细地址） | AP1: 联系地址（省） | AQ1: 联系地址（市） | AR1: 联系地址（区县） | AS1: 联系地址（详细地址） | AT1: 电子邮箱 | AU1: 学历 | AV1: 开户银行 | AW1: 银行账号 | AX1: 开户行省份 | AY1: 职务
A2: 北分 | B2: 蒋艳林 | C2: 居民身份证 | D2: 413026199909013086 | I2: 雇员 | L2: =VLOOKUP(D2&"*",花名册!B:Q,16,0) -> #N/A | M2: =VLOOKUP(D2&"*",花名册!B:N,13,0) -> #N/A

Sheet 报税-正常工资
A1: 公司 | B1: *姓名 | C1: *证件类型 | D1: *证件号码 | E1: 本期收入 | F1: 本期免税收入 | G1: 基本养老保险费 | H1: 基本医疗保险费 | I1: 失业保险费 | J1: 住房公积金 | K1: 累计子女教育 | L1: 累计继续教育 | M1: 累计住房贷款利息 | N1: 累计住房租金 | O1: 累计赡养老人 | P1: 累计3岁以下婴幼儿照护 | Q1: 累计个人养老金 | R1: 企业(职业)年金 | S1: 商业健康保险 | T1: 税延养老保险 | U1: 公务交通费用 | V1: 通讯费用 | W1: 律师办案费用 | X1: 西藏附加减除费用 | Y1: 其他 | Z1: 准予扣除的捐赠额 | AA1: 减免税额 | AB1: 备注 | AC1: 校验1 | AD1: 校验2 | AE1: 校验3
A2: 杭州 | B2: 耿德强 | C2: 居民身份证 | D2: 37028519831217171X | E2: =VLOOKUP(D2&"*",工资表明细!D:BL,61,0) -> #N/A | G2: =VLOOKUP(D2&"*",工资表明细!D:AP,39,0) -> #N/A | H2: =VLOOKUP(D2&"*",工资表明细!D:AQ,40,0) -> #N/A | I2: =VLOOKUP(D2&"*",工资表明细!D:AR,41,0) -> #N/A | J2: =VLOOKUP(D2&"*",工资表明细!D:AT,43,0) -> #N/A | AC2: =E2-G2-H2-I2-J2 -> #N/A | AD2: =VLOOKUP(B2,工资表明细!C:AX,48,0)+VLOOKUP(B2,工资表明细!C:AU,45,0) -> #N/A | AE2: =AC2-AD2 -> #N/A
A3: 北分 | B3: 牛飞芸 | C3: 居民身份证 | D3: 620402199105092732 | E3: =VLOOKUP(D3&"*",工资表明细!D:BL,61,0) -> #N/A | G3: =VLOOKUP(D3&"*",工资表明细!D:AP,39,0) -> #N/A | H3: =VLOOKUP(D3&"*",工资表明细!D:AQ,40,0) -> #N/A | I3: =VLOOKUP(D3&"*",工资表明细!D:AR,41,0) -> #N/A | J3: =VLOOKUP(D3&"*",工资表明细!D:AT,43,0) -> #N/A | AC3: =E3-G3-H3-I3-J3 -> #N/A | AD3: =VLOOKUP(B3,工资表明细!C:AX,48,0)+VLOOKUP(B3,工资表明细!C:AU,45,0) -> #N/A | AE3: =AC3-AD3 -> #N/A
A4: 杭州 | B4: 刘洋 | C4: 居民身份证 | D4: 411102198406050051 | E4: =VLOOKUP(D4&"*",工资表明细!D:BL,61,0) -> #N/A | G4: =VLOOKUP(D4&"*",工资表明细!D:AP,39,0) -> #N/A | H4: =VLOOKUP(D4&"*",工资表明细!D:AQ,40,0) -> #N/A | I4: =VLOOKUP(D4&"*",工资表明细!D:AR,41,0) -> #N/A | J4: =VLOOKUP(D4&"*",工资表明细!D:AT,43,0) -> #N/A | AC4: =E4-G4-H4-I4-J4 -> #N/A | AD4: =VLOOKUP(B4,工资表明细!C:AX,48,0)+VLOOKUP(B4,工资表明细!C:AU,45,0) -> #N/A | AE4: =AC4-AD4 -> #N/A
A5: 北分 | B5: 杨娟 | C5: 居民身份证 | D5: 141034199511170105 | E5: =VLOOKUP(D5&"*",工资表明细!D:BL,61,0) -> #N/A | F5: 3935.01 | G5: =VLOOKUP(D5&"*",工资表明细!D:AP,39,0) -> #N/A | H5: =VLOOKUP(D5&"*",工资表明细!D:AQ,40,0) -> #N/A | I5: =VLOOKUP(D5&"*",工资表明细!D:AR,41,0) -> #N/A | J5: =VLOOKUP(D5&"*",工资表明细!D:AT,43,0) -> #N/A | AC5: =E5-G5-H5-I5-J5 -> #N/A | AD5: =VLOOKUP(B5,工资表明细!C:AX,48,0)+VLOOKUP(B5,工资表明细!C:AU,45,0) -> #N/A | AE5: =AC5-AD5 -> #N/A
A6: 北分 | B6: 杨金雪 | C6: 居民身份证 | D6: 211382199701014125 | E6: =VLOOKUP(D6&"*",工资表明细!D:BL,61,0) -> #N/A | G6: =VLOOKUP(D6&"*",工资表明细!D:AP,39,0) -> #N/A | H6: =VLOOKUP(D6&"*",工资表明细!D:AQ,40,0) -> #N/A | I6: =VLOOKUP(D6&"*",工资表明细!D:AR,41,0) -> #N/A | J6: =VLOOKUP(D6&"*",工资表明细!D:AT,43,0) -> #N/A | AC6: =E6-G6-H6-I6-J6 -> #N/A | AD6: =VLOOKUP(B6,工资表明细!C:AX,48,0)+VLOOKUP(B6,工资表明细!C:AU,45,0) -> #N/A | AE6: =AC6-AD6 -> #N/A
A7: 杭州 | B7: 马顺华 | C7: 居民身份证 | D7: 429006198803300316 | E7: =VLOOKUP(D7&"*",工资表明细!D:BL,61,0) -> #N/A | G7: =VLOOKUP(D7&"*",工资表明细!D:AP,39,0) -> #N/A | H7: =VLOOKUP(D7&"*",工资表明细!D:AQ,40,0) -> #N/A | I7: =VLOOKUP(D7&"*",工资表明细!D:AR,41,0) -> #N/A | J7: =VLOOKUP(D7&"*",工资表明细!D:AT,43,0) -> #N/A | AC7: =E7-G7-H7-I7-J7 -> #N/A | AD7: =VLOOKUP(B7,工资表明细!C:AX,48,0)+VLOOKUP(B7,工资表明细!C:AU,45,0) -> #N/A | AE7: =AC7-AD7 -> #N/A
A8: 杭州 | B8: 耿惠欣 | C8: 居民身份证 | D8: 37028519940425172X | E8: =VLOOKUP(D8&"*",工资表明细!D:BL,61,0) -> #N/A | F8: 3763.53 | G8: =VLOOKUP(D8&"*",工资表明细!D:AP,39,0) -> #N/A | H8: =VLOOKUP(D8&"*",工资表明细!D:AQ,40,0) -> #N/A | I8: =VLOOKUP(D8&"*",工资表明细!D:AR,41,0) -> #N/A | J8: =VLOOKUP(D8&"*",工资表明细!D:AT,43,0) -> #N/A | AC8: =E8-G8-H8-I8-J8 -> #N/A | AD8: =VLOOKUP(B8,工资表明细!C:AX,48,0)+VLOOKUP(B8,工资表明细!C:AU,45,0) -> #N/A | AE8: =AC8-AD8 -> #N/A
A9: 武汉 | B9: 王鹏辉 | C9: 居民身份证 | D9: 421181198909130413 | E9: =VLOOKUP(D9&"*",工资表明细!D:BL,61,0) -> #N/A | G9: =VLOOKUP(D9&"*",工资表明细!D:AP,39,0) -> #N/A | H9: =VLOOKUP(D9&"*",工资表明细!D:AQ,40,0) -> #N/A | I9: =VLOOKUP(D9&"*",工资表明细!D:AR,41,0) -> #N/A | J9: =VLOOKUP(D9&"*",工资表明细!D:AT,43,0) -> #N/A | AC9: =E9-G9-H9-I9-J9 -> #N/A | AD9: =VLOOKUP(B9,工资表明细!C:AX,48,0)+VLOOKUP(B9,工资表明细!C:AU,45,0) -> #N/A | AE9: =AC9-AD9 -> #N/A
A10: 北分 | B10: 郭子轶 | C10: 居民身份证 | D10: 510106197603021421 | E10: =VLOOKUP(D10&"*",工资表明细!D:BL,61,0) -> #N/A | G10: =VLOOKUP(D10&"*",工资表明细!D:AP,39,0) -> #N/A | H10: =VLOOKUP(D10&"*",工资表明细!D:AQ,40,0) -> #N/A | I10: =VLOOKUP(D10&"*",工资表明细!D:AR,41,0) -> #N/A | J10: =VLOOKUP(D10&"*",工资表明细!D:AT,43,0) -> #N/A | AC10: =E10-G10-H10-I10-J10 -> #N/A | AD10: =VLOOKUP(B10,工资表明细!C:AX,48,0)+VLOOKUP(B10,工资表明细!C:AU,45,0) -> #N/A | AE10: =AC10-AD10 -> #N/A
A11: 北分 | B11: 陈昱光 | C11: 居民身份证 | D11: 410881199208201514 | E11: =VLOOKUP(D11&"*",工资表明细!D:BL,61,0) -> #N/A | G11: =VLOOKUP(D11&"*",工资表明细!D:AP,39,0) -> #N/A | H11: =VLOOKUP(D11&"*",工资表明细!D:AQ,40,0) -> #N/A | I11: =VLOOKUP(D11&"*",工资表明细!D:AR,41,0) -> #N/A | J11: =VLOOKUP(D11&"*",工资表明细!D:AT,43,0) -> #N/A | AC11: =E11-G11-H11-I11-J11 -> #N/A | AD11: =VLOOKUP(B11,工资表明细!C:AX,48,0)+VLOOKUP(B11,工资表明细!C:AU,45,0) -> #N/A | AE11: =AC11-AD11 -> #N/A
A12: 北分 | B12: 姜文超 | C12: 居民身份证 | D12: 370831198704081514 | E12: =VLOOKUP(D12&"*",工资表明细!D:BL,61,0) -> #N/A | G12: =VLOOKUP(D12&"*",工资表明细!D:AP,39,0) -> #N/A | H12: =VLOOKUP(D12&"*",工资表明细!D:AQ,40,0) -> #N/A | I12: =VLOOKUP(D12&"*",工资表明细!D:AR,41,0) -> #N/A | J12: =VLOOKUP(D12&"*",工资表明细!D:AT,43,0) -> #N/A | AC12: =E12-G12-H12-I12-J12 -> #N/A | AD12: =VLOOKUP(B12,工资表明细!C:AX,48,0)+VLOOKUP(B12,工资表明细!C:AU,45,0) -> #N/A | AE12: =AC12-AD12 -> #N/A
A13: 北分 | B13: 周海明 | C13: 居民身份证 | D13: 130427198606116938 | E13: =VLOOKUP(D13&"*",工资表明细!D:BL,61,0) -> #N/A | G13: =VLOOKUP(D13&"*",工资表明细!D:AP,39,0) -> #N/A | H13: =VLOOKUP(D13&"*",工资表明细!D:AQ,40,0) -> #N/A | I13: =VLOOKUP(D13&"*",工资表明细!D:AR,41,0) -> #N/A | J13: =VLOOKUP(D13&"*",工资表明细!D:AT,43,0) -> #N/A | AC13: =E13-G13-H13-I13-J13 -> #N/A | AD13: =VLOOKUP(B13,工资表明细!C:AX,48,0)+VLOOKUP(B13,工资表明细!C:AU,45,0) -> #N/A | AE13: =AC13-AD13 -> #N/A
A14: 北分 | B14: 高爽 | C14: 居民身份证 | D14: 110111199310191641 | E14: =VLOOKUP(D14&"*",工资表明细!D:BL,61,0) -> #N/A | G14: =VLOOKUP(D14&"*",工资表明细!D:AP,39,0) -> #N/A | H14: =VLOOKUP(D14&"*",工资表明细!D:AQ,40,0) -> #N/A | I14: =VLOOKUP(D14&"*",工资表明细!D:AR,41,0) -> #N/A | J14: =VLOOKUP(D14&"*",工资表明细!D:AT,43,0) -> #N/A | AC14: =E14-G14-H14-I14-J14 -> #N/A | AD14: =VLOOKUP(B14,工资表明细!C:AX,48,0)+VLOOKUP(B14,工资表明细!C:AU,45,0) -> #N/A | AE14: =AC14-AD14 -> #N/A
A15: 北分 | B15: 何泽栋 | C15: 居民身份证 | D15: 420528199505212854 | E15: =VLOOKUP(D15&"*",工资表明细!D:BL,61,0) -> #N/A | G15: =VLOOKUP(D15&"*",工资表明细!D:AP,39,0) -> #N/A | H15: =VLOOKUP(D15&"*",工资表明细!D:AQ,40,0) -> #N/A | I15: =VLOOKUP(D15&"*",工资表明细!D:AR,41,0) -> #N/A | J15: =VLOOKUP(D15&"*",工资表明细!D:AT,43,0) -> #N/A | AC15: =E15-G15-H15-I15-J15 -> #N/A | AD15: =VLOOKUP(B15,工资表明细!C:AX,48,0)+VLOOKUP(B15,工资表明细!C:AU,45,0) -> #N/A | AE15: =AC15-AD15 -> #N/A
A16: 杭州 | B16: 田楠 | C16: 居民身份证 | D16: 342221199203231524 | E16: =VLOOKUP(D16&"*",工资表明细!D:BL,61,0) -> #N/A | G16: =VLOOKUP(D16&"*",工资表明细!D:AP,39,0) -> #N/A | H16: =VLOOKUP(D16&"*",工资表明细!D:AQ,40,0) -> #N/A | I16: =VLOOKUP(D16&"*",工资表明细!D:AR,41,0) -> #N/A | J16: =VLOOKUP(D16&"*",工资表明细!D:AT,43,0) -> #N/A | AC16: =E16-G16-H16-I16-J16 -> #N/A | AD16: =VLOOKUP(B16,工资表明细!C:AX,48,0)+VLOOKUP(B16,工资表明细!C:AU,45,0) -> #N/A | AE16: =AC16-AD16 -> #N/A
A17: 北分 | B17: 郭高伟 | C17: 居民身份证 | D17: 412726199110166812 | E17: =VLOOKUP(D17&"*",工资表明细!D:BL,61,0) -> #N/A | G17: =VLOOKUP(D17&"*",工资表明细!D:AP,39,0) -> #N/A | H17: =VLOOKUP(D17&"*",工资表明细!D:AQ,40,0) -> #N/A | I17: =VLOOKUP(D17&"*",工资表明细!D:AR,41,0) -> #N/A | J17: =VLOOKUP(D17&"*",工资表明细!D:AT,43,0) -> #N/A | AC17: =E17-G17-H17-I17-J17 -> #N/A | AD17: =VLOOKUP(B17,工资表明细!C:AX,48,0)+VLOOKUP(B17,工资表明细!C:AU,45,0) -> #N/A | AE17: =AC17-AD17 -> #N/A
A18: 武汉 | B18: 黄晶 | C18: 居民身份证 | D18: 420111199208023126 | E18: =VLOOKUP(D18&"*",工资表明细!D:BL,61,0) -> #N/A | G18: =VLOOKUP(D18&"*",工资表明细!D:AP,39,0) -> #N/A | H18: =VLOOKUP(D18&"*",工资表明细!D:AQ,40,0) -> #N/A | I18: =VLOOKUP(D18&"*",工资表明细!D:AR,41,0) -> #N/A | J18: =VLOOKUP(D18&"*",工资表明细!D:AT,43,0) -> #N/A | AC18: =E18-G18-H18-I18-J18 -> #N/A | AD18: =VLOOKUP(B18,工资表明细!C:AX,48,0)+VLOOKUP(B18,工资表明细!C:AU,45,0) -> #N/A | AE18: =AC18-AD18 -> #N/A
A19: 北分 | B19: 陈洁 | C19: 居民身份证 | D19: 110106199508180621 | E19: =VLOOKUP(D19&"*",工资表明细!D:BL,61,0) -> #N/A | G19: =VLOOKUP(D19&"*",工资表明细!D:AP,39,0) -> #N/A | H19: =VLOOKUP(D19&"*",工资表明细!D:AQ,40,0) -> #N/A | I19: =VLOOKUP(D19&"*",工资表明细!D:AR,41,0) -> #N/A | J19: =VLOOKUP(D19&"*",工资表明细!D:AT,43,0) -> #N/A | AC19: =E19-G19-H19-I19-J19 -> #N/A | AD19: =VLOOKUP(B19,工资表明细!C:AX,48,0)+VLOOKUP(B19,工资表明细!C:AU,45,0) -> #N/A | AE19: =AC19-AD19 -> #N/A
A20: 北分 | B20: 王琪 | C20: 居民身份证 | D20: 14273019951005291X | E20: =VLOOKUP(D20&"*",工资表明细!D:BL,61,0) -> #N/A | G20: =VLOOKUP(D20&"*",工资表明细!D:AP,39,0) -> #N/A | H20: =VLOOKUP(D20&"*",工资表明细!D:AQ,40,0) -> #N/A | I20: =VLOOKUP(D20&"*",工资表明细!D:AR,41,0) -> #N/A | J20: =VLOOKUP(D20&"*",工资表明细!D:AT,43,0) -> #N/A | AC20: =E20-G20-H20-I20-J20 -> #N/A | AD20: =VLOOKUP(B20,工资表明细!C:AX,48,0)+VLOOKUP(B20,工资表明细!C:AU,45,0) -> #N/A | AE20: =AC20-AD20 -> #N/A
... A25: 杭州 | B25: 孙帆 | C25: 居民身份证 | D25: 140824199509230041 | E25: =VLOOKUP(D25&"*",工资表明细!D:BL,61,0) -> #N/A | G25: =VLOOKUP(D25&"*",工资表明细!D:AP,39,0) -> #N/A | H25: =VLOOKUP(D25&"*",工资表明细!D:AQ,40,0) -> #N/A | I25: =VLOOKUP(D25&"*",工资表明细!D:AR,41,0) -> #N/A | J25: =VLOOKUP(D25&"*",工资表明细!D:AT,43,0) -> #N/A | AC25: =E25-G25-H25-I25-J25 -> #N/A | AD25: =VLOOKUP(B25,工资表明细!C:AX,48,0)+VLOOKUP(B25,工资表明细!C:AU,45,0) -> #N/A | AE25: =AC25-AD25 -> #N/A
A26: 北分 | B26: 刘丽藏 | C26: 居民身份证 | D26: 130435199208291268 | E26: =VLOOKUP(D26&"*",工资表明细!D:BL,61,0) -> #N/A | F26: 3695.01 | G26: =VLOOKUP(D26&"*",工资表明细!D:AP,39,0) -> #N/A | H26: =VLOOKUP(D26&"*",工资表明细!D:AQ,40,0) -> #N/A | I26: =VLOOKUP(D26&"*",工资表明细!D:AR,41,0) -> #N/A | J26: =VLOOKUP(D26&"*",工资表明细!D:AT,43,0) -> #N/A | AC26: =E26-G26-H26-I26-J26 -> #N/A | AD26: =VLOOKUP(B26,工资表明细!C:AX,48,0)+VLOOKUP(B26,工资表明细!C:AU,45,0) -> #N/A | AE26: =AC26-AD26 -> #N/A
A27: 北分 | B27: 葛明明 | C27: 居民身份证 | D27: 130535200207021128 | E27: =VLOOKUP(D27&"*",工资表明细!D:BL,61,0) -> #N/A | G27: =VLOOKUP(D27&"*",工资表明细!D:AP,39,0) -> #N/A | H27: =VLOOKUP(D27&"*",工资表明细!D:AQ,40,0) -> #N/A | I27: =VLOOKUP(D27&"*",工资表明细!D:AR,41,0) -> #N/A | J27: =VLOOKUP(D27&"*",工资表明细!D:AT,43,0) -> #N/A | AC27: =E27-G27-H27-I27-J27 -> #N/A | AD27: =VLOOKUP(B27,工资表明细!C:AX,48,0)+VLOOKUP(B27,工资表明细!C:AU,45,0) -> #N/A | AE27: =AC27-AD27 -> #N/A
A28: 北分 | B28: 刘海星 | C28: 居民身份证 | D28: 130724198912104414 | E28: =VLOOKUP(D28&"*",工资表明细!D:BL,61,0) -> #N/A | G28: =VLOOKUP(D28&"*",工资表明细!D:AP,39,0) -> #N/A | H28: =VLOOKUP(D28&"*",工资表明细!D:AQ,40,0) -> #N/A | I28: =VLOOKUP(D28&"*",工资表明细!D:AR,41,0) -> #N/A | J28: =VLOOKUP(D28&"*",工资表明细!D:AT,43,0) -> #N/A | AC28: =E28-G28-H28-I28-J28 -> #N/A | AD28: =VLOOKUP(B28,工资表明细!C:AX,48,0)+VLOOKUP(B28,工资表明细!C:AU,45,0) -> #N/A | AE28: =AC28-AD28 -> #N/A
A29: 北分 | B29: 姜文肖 | C29: 居民身份证 | D29: 410922199312131347 | E29: =VLOOKUP(D29&"*",工资表明细!D:BL,61,0) -> #N/A | G29: =VLOOKUP(D29&"*",工资表明细!D:AP,39,0) -> #N/A | H29: =VLOOKUP(D29&"*",工资表明细!D:AQ,40,0) -> #N/A | I29: =VLOOKUP(D29&"*",工资表明细!D:AR,41,0) -> #N/A | J29: =VLOOKUP(D29&"*",工资表明细!D:AT,43,0) -> #N/A | AC29: =E29-G29-H29-I29-J29 -> #N/A | AD29: =VLOOKUP(B29,工资表明细!C:AX,48,0)+VLOOKUP(B29,工资表明细!C:AU,45,0) -> #N/A | AE29: =AC29-AD29 -> #N/A
A30: 北分 | B30: 张印达 | C30: 居民身份证 | D30: 131126199912010018 | E30: =VLOOKUP(D30&"*",工资表明细!D:BL,61,0) -> #N/A | G30: =VLOOKUP(D30&"*",工资表明细!D:AP,39,0) -> #N/A | H30: =VLOOKUP(D30&"*",工资表明细!D:AQ,40,0) -> #N/A | I30: =VLOOKUP(D30&"*",工资表明细!D:AR,41,0) -> #N/A | J30: =VLOOKUP(D30&"*",工资表明细!D:AT,43,0) -> #N/A | AC30: =E30-G30-H30-I30-J30 -> #N/A | AD30: =VLOOKUP(B30,工资表明细!C:AX,48,0)+VLOOKUP(B30,工资表明细!C:AU,45,0) -> #N/A | AE30: =AC30-AD30 -> #N/A
A31: 北分 | B31: 乔琳 | C31: 居民身份证 | D31: 130529199404255326 | E31: =VLOOKUP(D31&"*",工资表明细!D:BL,61,0) -> #N/A | G31: =VLOOKUP(D31&"*",工资表明细!D:AP,39,0) -> #N/A | H31: =VLOOKUP(D31&"*",工资表明细!D:AQ,40,0) -> #N/A | I31: =VLOOKUP(D31&"*",工资表明细!D:AR,41,0) -> #N/A | J31: =VLOOKUP(D31&"*",工资表明细!D:AT,43,0) -> #N/A | AC31: =E31-G31-H31-I31-J31 -> #N/A | AD31: =VLOOKUP(B31,工资表明细!C:AX,48,0)+VLOOKUP(B31,工资表明细!C:AU,45,0) -> #N/A | AE31: =AC31-AD31 -> #N/A
A32: 北分 | B32: 彭勇 | C32: 居民身份证 | D32: 370921199906164219 | E32: =VLOOKUP(D32&"*",工资表明细!D:BL,61,0) -> #N/A | G32: =VLOOKUP(D32&"*",工资表明细!D:AP,39,0) -> #N/A | H32: =VLOOKUP(D32&"*",工资表明细!D:AQ,40,0) -> #N/A | I32: =VLOOKUP(D32&"*",工资表明细!D:AR,41,0) -> #N/A | J32: =VLOOKUP(D32&"*",工资表明细!D:AT,43,0) -> #N/A | AC32: =E32-G32-H32-I32-J32 -> #N/A | AD32: =VLOOKUP(B32,工资表明细!C:AX,48,0)+VLOOKUP(B32,工资表明细!C:AU,45,0) -> #N/A | AE32: =AC32-AD32 -> #N/A
A33: 北分 | B33: 温丽敏 | C33: 居民身份证 | D33: 142431199803293020 | E33: =VLOOKUP(D33&"*",工资表明细!D:BL,61,0) -> #N/A | G33: =VLOOKUP(D33&"*",工资表明细!D:AP,39,0) -> #N/A | H33: =VLOOKUP(D33&"*",工资表明细!D:AQ,40,0) -> #N/A | I33: =VLOOKUP(D33&"*",工资表明细!D:AR,41,0) -> #N/A | J33: =VLOOKUP(D33&"*",工资表明细!D:AT,43,0) -> #N/A | AC33: =E33-G33-H33-I33-J33 -> #N/A | AD33: =VLOOKUP(B33,工资表明细!C:AX,48,0)+VLOOKUP(B33,工资表明细!C:AU,45,0) -> #N/A | AE33: =AC33-AD33 -> #N/A
A34: 杭州 | B34: 唐艳景 | C34: 居民身份证 | D34: 411324199508133468 | E34: =VLOOKUP(D34&"*",工资表明细!D:BL,61,0) -> #N/A | G34: =VLOOKUP(D34&"*",工资表明细!D:AP,39,0) -> #N/A | H34: =VLOOKUP(D34&"*",工资表明细!D:AQ,40,0) -> #N/A | I34: =VLOOKUP(D34&"*",工资表明细!D:AR,41,0) -> #N/A | J34: =VLOOKUP(D34&"*",工资表明细!D:AT,43,0) -> #N/A | AC34: =E34-G34-H34-I34-J34 -> #N/A | AD34: =VLOOKUP(B34,工资表明细!C:AX,48,0)+VLOOKUP(B34,工资表明细!C:AU,45,0) -> #N/A | AE34: =AC34-AD34 -> #N/A
A35: 北分 | B35: 朱瑞丽 | C35: 居民身份证 | D35: 371324200108129825 | E35: =VLOOKUP(D35&"*",工资表明细!D:BL,61,0) -> #N/A | G35: =VLOOKUP(D35&"*",工资表明细!D:AP,39,0) -> #N/A | H35: =VLOOKUP(D35&"*",工资表明细!D:AQ,40,0) -> #N/A | I35: =VLOOKUP(D35&"*",工资表明细!D:AR,41,0) -> #N/A | J35: =VLOOKUP(D35&"*",工资表明细!D:AT,43,0) -> #N/A | AC35: =E35-G35-H35-I35-J35 -> #N/A | AD35: =VLOOKUP(B35,工资表明细!C:AX,48,0)+VLOOKUP(B35,工资表明细!C:AU,45,0) -> #N/A | AE35: =AC35-AD35 -> #N/A
A36: 杭州 | B36: 陈楚冰 | C36: 居民身份证 | D36: 330681200010251588 | E36: =VLOOKUP(D36&"*",工资表明细!D:BL,61,0) -> #N/A | G36: =VLOOKUP(D36&"*",工资表明细!D:AP,39,0) -> #N/A | H36: =VLOOKUP(D36&"*",工资表明细!D:AQ,40,0) -> #N/A | I36: =VLOOKUP(D36&"*",工资表明细!D:AR,41,0) -> #N/A | J36: =VLOOKUP(D36&"*",工资表明细!D:AT,43,0) -> #N/A | AC36: =E36-G36-H36-I36-J36 -> #N/A | AD36: =VLOOKUP(B36,工资表明细!C:AX,48,0)+VLOOKUP(B36,工资表明细!C:AU,45,0) -> #N/A | AE36: =AC36-AD36 -> #N/A
A37: 深圳 | B37: 陈丽娟 | C37: 居民身份证 | D37: 230103197203163221 | E37: =VLOOKUP(D37&"*",工资表明细!D:BL,61,0) -> #N/A | G37: =VLOOKUP(D37&"*",工资表明细!D:AP,39,0) -> #N/A | H37: =VLOOKUP(D37&"*",工资表明细!D:AQ,40,0) -> #N/A | I37: =VLOOKUP(D37&"*",工资表明细!D:AR,41,0) -> #N/A | J37: =VLOOKUP(D37&"*",工资表明细!D:AT,43,0) -> #N/A | AC37: =E37-G37-H37-I37-J37 -> #N/A | AD37: =VLOOKUP(B37,工资表明细!C:AX,48,0)+VLOOKUP(B37,工资表明细!C:AU,45,0) -> #N/A | AE37: =AC37-AD37 -> #N/A
A38: 成都 | B38: 陈泓佳 | C38: 居民身份证 | D38: 510802198811120026 | E38: =VLOOKUP(D38&"*",工资表明细!D:BL,61,0) -> #N/A | G38: =VLOOKUP(D38&"*",工资表明细!D:AP,39,0) -> #N/A | H38: =VLOOKUP(D38&"*",工资表明细!D:AQ,40,0) -> #N/A | I38: =VLOOKUP(D38&"*",工资表明细!D:AR,41,0) -> #N/A | J38: =VLOOKUP(D38&"*",工资表明细!D:AT,43,0) -> #N/A | AC38: =E38-G38-H38-I38-J38 -> #N/A | AD38: =VLOOKUP(B38,工资表明细!C:AX,48,0)+VLOOKUP(B38,工资表明细!C:AU,45,0) -> #N/A | AE38: =AC38-AD38 -> #N/A
... A70: 北分 | B70: 蒋艳林 | C70: 居民身份证 | D70: 413026199909013086 | E70: =VLOOKUP(D70&"*",工资表明细!D:BL,61,0) -> #N/A | G70: =VLOOKUP(D70&"*",工资表明细!D:AP,39,0) -> #N/A | H70: =VLOOKUP(D70&"*",工资表明细!D:AQ,40,0) -> #N/A | I70: =VLOOKUP(D70&"*",工资表明细!D:AR,41,0) -> #N/A | J70: =VLOOKUP(D70&"*",工资表明细!D:AT,43,0) -> #N/A | AC70: =E70-G70-H70-I70-J70 -> #N/A | AD70: =VLOOKUP(B70,工资表明细!C:AX,48,0)+VLOOKUP(B70,工资表明细!C:AU,45,0) -> #N/A | AE70: =AC70-AD70 -> #N/A
A71: 北分 | B71: 李亚宁 | C71: 居民身份证 | D71: 130133200012020622 | E71: =VLOOKUP(D71&"*",工资表明细!D:BL,61,0) -> #N/A | G71: =VLOOKUP(D71&"*",工资表明细!D:AP,39,0) -> #N/A | H71: =VLOOKUP(D71&"*",工资表明细!D:AQ,40,0) -> #N/A | I71: =VLOOKUP(D71&"*",工资表明细!D:AR,41,0) -> #N/A | J71: =VLOOKUP(D71&"*",工资表明细!D:AT,43,0) -> #N/A | AC71: =E71-G71-H71-I71-J71 -> #N/A | AD71: =VLOOKUP(B71,工资表明细!C:AX,48,0)+VLOOKUP(B71,工资表明细!C:AU,45,0) -> #N/A | AE71: =AC71-AD71 -> #N/A | AF71: 赔偿金
A72: 北分 | B72: 王涛 | C72: 居民身份证 | D72: 110103198904200037 | E72: =VLOOKUP(D72&"*",工资表明细!D:BL,61,0) -> #N/A | G72: =VLOOKUP(D72&"*",工资表明细!D:AP,39,0) -> #N/A | H72: =VLOOKUP(D72&"*",工资表明细!D:AQ,40,0) -> #N/A | I72: =VLOOKUP(D72&"*",工资表明细!D:AR,41,0) -> #N/A | J72: =VLOOKUP(D72&"*",工资表明细!D:AT,43,0) -> #N/A | AC72: =E72-G72-H72-I72-J72 -> #N/A | AD72: =VLOOKUP(B72,工资表明细!C:AX,48,0)+VLOOKUP(B72,工资表明细!C:AU,45,0) -> #N/A | AE72: =AC72-AD72 -> #N/A

Sheet 报税-劳务
A1: 公司 | B1: *姓名 | C1: *证件类型 | D1: *证件号码 | E1: *所得项目 | F1: *收入 | G1: 免税收入 | H1: 商业健康保险 | I1: 税延养老保险 | J1: 其他 | K1: 允许扣除的税费 | L1: 减免税额 | M1: 备注
A2: =VLOOKUP(D2&"*",花名册!B:D,3,0) -> #N/A | B2: 汪和艺 | C2: 居民身份证 | D2: 340881197110130626 | F2: =VLOOKUP(D2&"*",工资表明细!D:BJ,59,0) -> #N/A
A3: =VLOOKUP(D3&"*",花名册!B:D,3,0) -> #N/A | B3: 汤修兰 | C3: 居民身份证 | D3: 512224197105265300 | F3: =VLOOKUP(D3&"*",工资表明细!D:BJ,59,0) -> #N/A
A4: =VLOOKUP(D4&"*",花名册!B:D,3,0) -> #N/A | B4: 王丽花 | C4: 居民身份证 | D4: 350500197206142522 | F4: =VLOOKUP(D4&"*",工资表明细!D:BJ,59,0) -> #N/A

Sheet 报税-经济补偿金
A1: 公司 | B1: *姓名 | C1: *证件类型 | D1: *证件号码 | E1: *一次性补偿收入 | F1: 免税收入 | G1: 其他 | H1: 准予扣除的捐赠额 | I1: 减免税额 | J1: 备注
